Workbook

Sheet Holdings
B2: =_xlfn.XLOOKUP(B3,Mapping!$C:$C,Mapping!$D:$D) -> #N/A | C2: =_xlfn.XLOOKUP(C3,Mapping!$C:$C,Mapping!$D:$D) -> #N/A | D2: =_xlfn.XLOOKUP(D3,Mapping!$C:$C,Mapping!$D:$D) -> #N/A | E2: =_xlfn.XLOOKUP(E3,Mapping!$C:$C,Mapping!$D:$D) -> #N/A | F2: =_xlfn.XLOOKUP(F3,Mapping!$C:$C,Mapping!$D:$D) -> Reporting Date | G2: =_xlfn.XLOOKUP(G3,Mapping!$C:$C,Mapping!$D:$D) -> Model Portfolio | H2: =_xlfn.XLOOKUP(H3,Mapping!$C:$C,Mapping!$D:$D) -> Portfolio | I2: =_xlfn.XLOOKUP(I3,Mapping!$C:$C,Mapping!$D:$D) -> Security ID | ... GA2: =_xlfn.XLOOKUP(GA3,Mapping!$C:$C,Mapping!$D:$D) -> #N/A
B3: Unique Identifier | C3: Investor Code | D3: Identification ID | E3: Code Name | F3: Reporting Date | G3: Model Portfolio | H3: Portfolio | I3: Security ID | J3: Security Name | K3: Portfolio Name | L3: Model Portfolio Name | M3: Portfolio Group | N3: Current Underlying Amount PC | O3: Current Underlying Amount RC | P3: Portfolio Currency | Q3: Security Type Name | R3: RA_Bullet | S3: Loan Code | T3: Asset Type RA | U3: RA Country | V3: RA Asset Country Name | W3: Underlying Asset Type | X3: CRDB Code | Y3: WAL | Z3: Quotation Currency | AA3: FX Rate EC | AB3: Forex | AC3: Initial Commitment Amount CCY | AD3: Gross Notional PC | AE3: Gross Notional RC | AF3: Balance Funded % | AG3: Balance Book Value PC | AH3: Balance Nominal/Number | AI3: Balance Unfunded Amount | AJ3: RA_Commitment QC | AK3: Current Drawn Amount CCY | AL3: Current Drawn Amount PC | AM3: RA_Referentiel Rate | AN3: Yield | AO3: Yield EUR | AP3: Yield GBP | AQ3: Purchase Price % | AR3: Clean Price for Weight | AS3: Purchase Date | AT3: Maturity Date | AU3: Next Coupon Date Format | AV3: Parent Issuer ID | AW3: Parent Issuer Name | AX3: RA_Listed Borrower | AY3: Issuer Name | AZ3: Issuer | BA3: Issuer Country | BB3: Group Name | BC3: LEI | BD3: TAB Status | BE3: CR Status | BF3: CR Limit | BG3: Current NDS | BH3: Underlying Parent Issuer ID | BI3: RA Commitment PC | BJ3: RA Commitment RC | BK3: Rate Type | BL3: Seniority | BM3: STEF Level | BN3: Modified Duration YTM | BO3: Time to Maturity | BP3: RA_Floored | BQ3: Make Whole Case | BR3: Nature | BS3: RA Ident | BT3: FM Controller Infra | BU3: FMCG Controller | BV3: Next Rate (Index) | BW3: Interest Payment Frequency | BX3: Basis | BY3: All-in Spread at Acquisition | BZ3: Spread | CA3: Next Coupon | CB3: Index | CC3: Internal Current Rating | CD3: Ext Sec Group_Rating_Closing | CE3: Rating Fitch | CF3: Rating S&P | CG3: Rating Moody's | CH3: Last Compliance Certification Date | CI3: ICR Limit | CJ3: ICR Current | CK3: ICR Day One | CL3: ICR Status | CM3: ICR Trend | CN3: ICR -3m | CO3: ICR -6m | CP3: ICR -9m | CQ3: ICR -1y | CR3: ICR -2y | CS3: LLCR Cash Trap | CT3: LLCR Covenant (RA) | CU3: LLCR Status | CV3: LTV -3m | CW3: LTV -6m | CX3: LTV -9m | CY3: LTV -1y | CZ3: LTV -2y | DA3: LTV Current | DB3: LTV Day One | DC3: LTV Limit | DD3: LTV Status | DE3: LTV Trend | DF3: LEV Cash Trap | DG3: LEV Limit | DH3: LEV Status | DI3: RA_LVG_D1 | DJ3: RA_COD_LVG | DK3: RA_NDRAB_CT | DL3: RA_COD_NDRAB | DM3: RA_DSC_D1 | DN3: RA_COD_DSC | DO3: PLCR Cash Trap | DP3: Cash Trap LTV Covenant | DQ3: Cash Trap ICR Covenant | DR3: Cash Trap DY Covenant | DS3: NAH Cash Trap | DT3: NDS Cash Trap | DU3: GR Cash Trap | DV3: CR Cash Trap | DW3: RA_CR_D1 | DX3: RA_ICR_D1 | DY3: RA_COD_ICR | DZ3: RA_COD_CR | EA3: PLCR Status | EB3: PLCR Covenant (RA) | EC3: DSC Trans | ED3: DSC Status | EE3: DSC Limit | EF3: DSC Cash Trap | EG3: RA_DC_CT | EH3: RA_DC_COV | EI3: DSC Day One | EJ3: DSC -3m | EK3: DSC -6m | EL3: DSC -9m | EM3: DSC -1y | EN3: DSC -2y | EO3: RA_COD_DC | EP3: DC Status | EQ3: RA_COD_DY | ER3: DY Trend | ES3: DY Status | ET3: DY Limit | EU3: RA_DY_D1 | EV3: DY -3m | EW3: DY -6m | EX3: DY -9m | EY3: DY -1y | EZ3: DY -2y | FA3: GR Status | FB3: GR Covenant | FC3: RA_LTV_D1 | FD3: RA_Infra Risk Profile | FE3: RA_Infra Rating | FF3: RA_COD_LTV | FG3: NAH Status | FH3: NAH Covenants | FI3: Current NAH | FJ3: NDS Status | FK3: NDS Covenant | FL3: Current FAV | FM3: Current PLCR (RA) | FN3: Current LLCR (RA) | FO3: Revenue -1y | FP3: Revenue -2y | FQ3: RA EBITDA | FR3: EBITDA -1y | FS3: EBITDA -2y | FT3: FO_RA_LTV Covenant | FU3: FO_RA_ICR Covenant | FV3: FO_RA_Current ICR | FW3: FO_RA_Current LTV | FX3: RA Revenue | FY3: FAV Cash Trap | FZ3: FAV Covenant | GA3: FAV Status
B4: =C4&"x"&I4 -> 61024x100200 | C4: =IF(G4="SINGLE",H4,G4) -> 61024 | D4: =_xlfn.XLOOKUP(I4,calculations!$t:$t,calculations!$s:$s) -> #VALUE! | E4: =_xlfn.XLOOKUP(I4,Mapping!$T:$T,Mapping!$Q:$Q) -> AURO01 | F4: 46203 | G4: 61024 | H4: 61024 | I4: 100200 | J4: Aurora Offshore | K4: Fund 4 Fund | L4: Fund 4 Fund | M4: Infra Debt | N4: 12462000 | O4: 12462000 | P4: EUR | Q4: Private Placement Note | R4: N | S4: L100200 | T4: Infrastructure Debt | U4: DE | V4: Germany | W4: Offshore wind | X4: CR1000 | Y4: 8.9 | Z4: EUR | AA4: 1 | AB4: N | AC4: 29748000 | AD4: 29748000 | AE4: 29748000 | AF4: 0.4189 | AG4: 12462000 | AH4: 12462000 | AI4: 17286000 | AJ4: 29748000 | AK4: 12462000 | AL4: 12462000 | AM4: EURIBOR 6M | AN4: 5.277 | AO4: 3.811 | AP4: 5.693 | AQ4: 100 | AR4: 100 | AS4: 42349 | AT4: 46915 | AU4: 46295 | AV4: PI2000 | AW4: Corvus Digital | AX4: N | AY4: Aurora Offshore Finance Ltd | AZ4: Aurora Offshore Finance | BA4: Germany | BB4: Corvus Digital | BC4: 529900SYNTH000000000 | BI4: 29748000 | BJ4: 29748000 | BK4: Floating | BL4: Senior Secured | BN4: 7.5 | BO4: 1.95 | BP4: Y | BQ4: N | BR4: Debt | BS4: RA100200 | BT4: E. Rossi | BU4: E. Rossi | BW4: Semi-annual | BX4: ACT/360 | BY4: 165 | BZ4: 165 | CB4: EURIBOR | CC4: BBB | CD4: BBB | CE4: BBB+ | CF4: BBB+ | CG4: NR | CH4: 46112 | CI4: 1.2 | CJ4: 2.43 | CK4: 2.55 | CL4: OK | DA4: 0.8 | DC4: 0.85 | DD4: Watch | ED4: OK | EE4: 1.05 | EI4: 1.48 | FQ4: 53363427
B5: =C5&"x"&I5 -> 61021x100200 | C5: =IF(G5="SINGLE",H5,G5) -> 61021 | D5: =_xlfn.XLOOKUP(I5,calculations!$t:$t,calculations!$s:$s) -> #VALUE! | E5: =_xlfn.XLOOKUP(I5,Mapping!$T:$T,Mapping!$Q:$Q) -> AURO01 | F5: 46203 | G5: 61021 | H5: 61021 | I5: 100200 | J5: Aurora Offshore | K5: Fund 1 Fund | L5: Fund 1 Fund | M5: Infra Debt | N5: 24863000 | O5: 24863000 | P5: EUR | Q5: Private Placement Note | R5: N | S5: L100200 | T5: Infrastructure Debt | U5: DE | V5: Germany | W5: Offshore wind | X5: CR1000 | Y5: 8.9 | Z5: EUR | AA5: 1 | AB5: N | AC5: 59352000 | AD5: 59352000 | AE5: 59352000 | AF5: 0.4189 | AG5: 24863000 | AH5: 24863000 | AI5: 34489000 | AJ5: 59352000 | AK5: 24863000 | AL5: 24863000 | AM5: EURIBOR 6M | AN5: 3.212 | AO5: 6.46 | AP5: 2.809 | AQ5: 100 | AR5: 100 | AS5: 42349 | AT5: 46915 | AU5: 46295 | AV5: PI2000 | AW5: Corvus Digital | AX5: N | AY5: Aurora Offshore Finance Ltd | AZ5: Aurora Offshore Finance | BA5: Germany | BB5: Corvus Digital | BC5: 529900SYNTH000000000 | BI5: 59352000 | BJ5: 59352000 | BK5: Floating | BL5: Senior Secured | BN5: 7.5 | BO5: 1.95 | BP5: Y | BQ5: N | BR5: Debt | BS5: RA100200 | BT5: E. Rossi | BU5: E. Rossi | BW5: Semi-annual | BX5: ACT/360 | BY5: 165 | BZ5: 165 | CB5: EURIBOR | CC5: BBB | CD5: BBB | CE5: BBB+ | CF5: BBB+ | CG5: NR | CH5: 46112 | CI5: 1.2 | CJ5: 2.29 | CK5: 2.4 | CL5: OK | DA5: 0.72 | DC5: 0.85 | DD5: OK | ED5: OK | EE5: 1.05 | EI5: 1.35 | FQ5: 83702383
B6: =C6&"x"&I6 -> 61015x100200 | C6: =IF(G6="SINGLE",H6,G6) -> 61015 | D6: =_xlfn.XLOOKUP(I6,calculations!$t:$t,calculations!$s:$s) -> #VALUE! | E6: =_xlfn.XLOOKUP(I6,Mapping!$T:$T,Mapping!$Q:$Q) -> AURO01 | F6: 46203 | G6: 61015 | H6: 61015 | I6: 100200 | J6: Aurora Offshore | K6: Investor 15 Mandate | L6: Investor 15 Mandate | M6: Infra Debt | N6: 13726000 | O6: 13726000 | P6: EUR | Q6: Private Placement Note | R6: N | S6: L100200 | T6: Infrastructure Debt | U6: DE | V6: Germany | W6: Offshore wind | X6: CR1000 | Y6: 8.9 | Z6: EUR | AA6: 1 | AB6: N | AC6: 32765000 | AD6: 32765000 | AE6: 32765000 | AF6: 0.4189 | AG6: 13726000 | AH6: 13726000 | AI6: 19039000 | AJ6: 32765000 | AK6: 13726000 | AL6: 13726000 | AM6: EURIBOR 6M | AN6: 2.908 | AO6: 4.526 | AP6: 6.012 | AQ6: 100 | AR6: 100 | AS6: 42349 | AT6: 46915 | AU6: 46295 | AV6: PI2000 | AW6: Corvus Digital | AX6: N | AY6: Aurora Offshore Finance Ltd | AZ6: Aurora Offshore Finance | BA6: Germany | BB6: Corvus Digital | BC6: 529900SYNTH000000000 | BI6: 32765000 | BJ6: 32765000 | BK6: Floating | BL6: Senior Secured | BN6: 7.5 | BO6: 1.95 | BP6: Y | BQ6: N | BR6: Debt | BS6: RA100200 | BT6: E. Rossi | BU6: D. Schäfer | BW6: Semi-annual | BX6: 30/360 | BY6: 165 | BZ6: 165 | CB6: EURIBOR | CC6: BBB | CD6: BBB | CE6: BBB+ | CF6: BBB+ | CG6: NR | CH6: 46112 | CI6: 1.2 | CJ6: 2.91 | CK6: 3.06 | CL6: OK | DA6: 0.79 | DC6: 0.85 | DD6: OK | ED6: Watch | EE6: 1.05 | EI6: 1.11 | FQ6: 62586420
B7: =C7&"x"&I7 -> 61007x100200 | C7: =IF(G7="SINGLE",H7,G7) -> 61007 | D7: =_xlfn.XLOOKUP(I7,calculations!$t:$t,calculations!$s:$s) -> #VALUE! | E7: =_xlfn.XLOOKUP(I7,Mapping!$T:$T,Mapping!$Q:$Q) -> AURO01 | F7: 46203 | G7: 61007 | H7: 61007 | I7: 100200 | J7: Aurora Offshore | K7: Investor 7 Portfolio | L7: Investor 7 Portfolio | M7: Infra Debt | N7: 23915000 | O7: 23915000 | P7: GBP | Q7: Private Placement Note | R7: N | S7: L100200 | T7: Infrastructure Debt | U7: DE | V7: Germany | W7: Offshore wind | X7: CR1000 | Y7: 8.9 | Z7: EUR | AA7: 1 | AB7: N | AC7: 57089000 | AD7: 57089000 | AE7: 57089000 | AF7: 0.4189 | AG7: 23915000 | AH7: 23915000 | AI7: 33174000 | AJ7: 57089000 | AK7: 23915000 | AL7: 23915000 | AM7: EURIBOR 6M | AN7: 4.386 | AO7: 4.368 | AP7: 5.244 | AQ7: 100 | AR7: 100 | AS7: 42349 | AT7: 46915 | AU7: 46295 | AV7: PI2000 | AW7: Corvus Digital | AX7: N | AY7: Aurora Offshore Finance Ltd | AZ7: Aurora Offshore Finance | BA7: Germany | BB7: Corvus Digital | BC7: 529900SYNTH000000000 | BI7: 57089000 | BJ7: 57089000 | BK7: Floating | BL7: Senior Secured | BN7: 7.5 | BO7: 1.95 | BP7: Y | BQ7: N | BR7: Debt | BS7: RA100200 | BT7: E. Rossi | BU7: B. Okoro | BW7: Semi-annual | BX7: 30/360 | BY7: 165 | BZ7: 165 | CB7: EURIBOR | CC7: BBB | CD7: BBB | CE7: BBB+ | CF7: BBB+ | CG7: NR | CH7: 46112 | CI7: 1.2 | CJ7: 1.78 | CK7: 1.87 | CL7: OK | DA7: 0.7 | DC7: 0.85 | DD7: OK | ED7: Watch | EE7: 1.05 | EI7: 1.1 | FQ7: 58695684
B8: =C8&"x"&I8 -> 61023x100200 | C8: =IF(G8="SINGLE",H8,G8) -> 61023 | D8: =_xlfn.XLOOKUP(I8,calculations!$t:$t,calculations!$s:$s) -> #VALUE! | E8: =_xlfn.XLOOKUP(I8,Mapping!$T:$T,Mapping!$Q:$Q) -> AURO01 | F8: 46203 | G8: 61023 | H8: 61023 | I8: 100200 | J8: Aurora Offshore | K8: Fund 3 Fund | L8: Fund 3 Fund | M8: Infra Debt | N8: 38584000 | O8: 38584000 | P8: EUR | Q8: Private Placement Note | R8: N | S8: L100200 | T8: Infrastructure Debt | U8: DE | V8: Germany | W8: Offshore wind | X8: CR1000 | Y8: 8.9 | Z8: EUR | AA8: 1 | AB8: N | AC8: 92104000 | AD8: 92104000 | AE8: 92104000 | AF8: 0.4189 | AG8: 38584000 | AH8: 38584000 | AI8: 53520000 | AJ8: 92104000 | AK8: 38584000 | AL8: 38584000 | AM8: EURIBOR 6M | AN8: 3.204 | AO8: 2.599 | AP8: 3.73 | AQ8: 100 | AR8: 100 | AS8: 42349 | AT8: 46915 | AU8: 46295 | AV8: PI2000 | AW8: Corvus Digital | AX8: N | AY8: Aurora Offshore Finance Ltd | AZ8: Aurora Offshore Finance | BA8: Germany | BB8: Corvus Digital | BC8: 529900SYNTH000000000 | BI8: 92104000 | BJ8: 92104000 | BK8: Floating | BL8: Senior Secured | BN8: 7.5 | BO8: 1.95 | BP8: Y | BQ8: N | BR8: Debt | BS8: RA100200 | BT8: E. Rossi | BU8: B. Okoro | BW8: Semi-annual | BX8: 30/360 | BY8: 165 | BZ8: 165 | CB8: EURIBOR | CC8: BBB | CD8: BBB | CE8: BBB+ | CF8: BBB+ | CG8: NR | CH8: 46112 | CI8: 1.2 | CJ8: 2.86 | CK8: 3 | CL8: OK | DA8: 0.81 | DC8: 0.85 | DD8: Watch | ED8: OK | EE8: 1.05 | EI8: 1.34 | FQ8: 69307283
B9: =C9&"x"&I9 -> 61003x100200 | C9: =IF(G9="SINGLE",H9,G9) -> 61003 | D9: =_xlfn.XLOOKUP(I9,calculations!$t:$t,calculations!$s:$s) -> #VALUE! | E9: =_xlfn.XLOOKUP(I9,Mapping!$T:$T,Mapping!$Q:$Q) -> AURO01 | F9: 46203 | G9: SINGLE | H9: 61003 | I9: 100200 | J9: Aurora Offshore | K9: Investor 19 Mandate | L9: Investor 19 Mandate | M9: Infra Debt | N9: 14535000 | O9: 14535000 | P9: EUR | Q9: Private Placement Note | R9: N | S9: L100200 | T9: Infrastructure Debt | U9: DE | V9: Germany | W9: Offshore wind | X9: CR1000 | Y9: 8.9 | Z9: EUR | AA9: 1 | AB9: N | AC9: 34696000 | AD9: 34696000 | AE9: 34696000 | AF9: 0.4189 | AG9: 14535000 | AH9: 14535000 | AI9: 20161000 | AJ9: 34696000 | AK9: 14535000 | AL9: 14535000 | AM9: EURIBOR 6M | AN9: 2.597 | AO9: 3.69 | AP9: 6.314 | AQ9: 100 | AR9: 100 | AS9: 42349 | AT9: 46915 | AU9: 46295 | AV9: PI2000 | AW9: Corvus Digital | AX9: N | AY9: Aurora Offshore Finance Ltd | AZ9: Aurora Offshore Finance | BA9: Germany | BB9: Corvus Digital | BC9: 529900SYNTH000000000 | BI9: 34696000 | BJ9: 34696000 | BK9: Floating | BL9: Senior Secured | BN9: 7.5 | BO9: 1.95 | BP9: Y | BQ9: N | BR9: Debt | BS9: RA100200 | BT9: E. Rossi | BU9: F. Lindqvist | BW9: Semi-annual | BX9: 30/360 | BY9: 165 | BZ9: 165 | CB9: EURIBOR | CC9: BBB | CD9: BBB | CE9: BBB+ | CF9: BBB+ | CG9: NR | CH9: 46112 | CI9: 1.2 | CJ9: 3.26 | CK9: 3.42 | CL9: OK | DA9: 0.48 | DC9: 0.85 | DD9: OK | ED9: OK | EE9: 1.05 | EI9: 1.55 | FQ9: 74889817
B10: =C10&"x"&I10 -> 61003x100201 | C10: =IF(G10="SINGLE",H10,G10) -> 61003 | D10: =_xlfn.XLOOKUP(I10,calculations!$t:$t,calculations!$s:$s) -> #VALUE! | E10: =_xlfn.XLOOKUP(I10,Mapping!$T:$T,Mapping!$Q:$Q) -> BEAC02 | F10: 46203 | G10: 61003 | H10: 61003 | I10: 100201 | J10: Beacon Airports | K10: Investor 3 Portfolio | L10: Investor 3 Portfolio | M10: Infra Debt | N10: 57363000 | O10: 67091228 | P10: EUR | Q10: Loan | R10: Y | S10: L100201 | T10: Infrastructure Debt | U10: GB | V10: United Kingdom | W10: Airports | X10: CR1001 | Y10: 10.5 | Z10: GBP | AA10: 0.855 | AB10: Y | AC10: 143610000 | AD10: 136771000 | AE10: 1.5996608e+08 | AF10: 0.4194 | AG10: 57363000 | AH10: 57363000 | AI10: 79408000 | AJ10: 136771000 | AK10: 57363000 | AL10: 57363000 | AM10: EURIBOR 6M | AN10: 3.228 | AO10: 3.234 | AP10: 4.545 | AQ10: 100 | AR10: 100 | AS10: 45048 | AT10: 50346 | AU10: 46295 | AV10: PI2001 | AW10: Aquila Utilities | AX10: N | AY10: Beacon Airports Finance Ltd | AZ10: Beacon Airports Finance | BA10: United Kingdom | BB10: Aquila Utilities | BC10: 529900SYNTH000000001 | BI10: 136771000 | BJ10: 1.5996608e+08 | BK10: Floating | BL10: Senior Secured | BN10: 8.7 | BO10: 11.34 | BP10: Y | BQ10: N | BR10: Debt | BS10: RA100201 | BT10: E. Rossi | BU10: B. Okoro | BW10: Semi-annual | BX10: 30/360 | BY10: 345 | BZ10: 345 | CB10: EURIBOR | CC10: BBB- | CD10: BBB- | CE10: BBB | CF10: NR | CG10: Baa2 | CH10: 46112 | CI10: 1.2 | CJ10: 1.93 | CK10: 2.03 | CL10: OK | DA10: 0.72 | DC10: 0.85 | DD10: OK | ED10: OK | EE10: 1.05 | EI10: 1.48 | FQ10: 74758575
B11: =C11&"x"&I11 -> 61014x100201 | C11: =IF(G11="SINGLE",H11,G11) -> 61014 | D11: =_xlfn.XLOOKUP(I11,calculations!$t:$t,calculations!$s:$s) -> #VALUE! | E11: =_xlfn.XLOOKUP(I11,Mapping!$T:$T,Mapping!$Q:$Q) -> BEAC02 | F11: 46203 | G11: 61014 | H11: 61014 | I11: 100201 | J11: Beacon Airports | K11: Investor 14 Mandate | L11: Investor 14 Mandate | M11: Infra Debt | N11: 113600000 | O11: 1.328655e+08 | P11: EUR | Q11: Loan | R11: Y | S11: L100201 | T11: Infrastructure Debt | U11: GB | V11: United Kingdom | W11: Airports | X11: CR1001 | Y11: 10.5 | Z11: GBP | AA11: 0.855 | AB11: Y | AC11: 284399000 | AD11: 270856000 | AE11: 3.1679064e+08 | AF11: 0.4194 | AG11: 113600000 | AH11: 113600000 | AI11: 157256000 | AJ11: 270856000 | AK11: 113600000 | AL11: 113600000 | AM11: EURIBOR 6M | AN11: 6.226 | AO11: 5.616 | AP11: 3.178 | AQ11: 100 | AR11: 100 | AS11: 45048 | AT11: 50346 | AU11: 46295 | AV11: PI2001 | AW11: Aquila Utilities | AX11: N | AY11: Beacon Airports Finance Ltd | AZ11: Beacon Airports Finance | BA11: United Kingdom | BB11: Aquila Utilities | BC11: 529900SYNTH000000001 | BI11: 270856000 | BJ11: 3.1679064e+08 | BK11: Floating | BL11: Senior Secured | BN11: 8.7 | BO11: 11.34 | BP11: Y | BQ11: N | BR11: Debt | BS11: RA100201 | BT11: E. Rossi | BU11: F. Lindqvist | BW11: Semi-annual | BX11: 30/360 | BY11: 345 | BZ11: 345 | CB11: EURIBOR | CC11: BBB- | CD11: BBB- | CE11: BBB | CF11: NR | CG11: Baa2 | CH11: 46112 | CI11: 1.2 | CJ11: 2.62 | CK11: 2.75 | CL11: OK | DA11: 0.69 | DC11: 0.85 | DD11: OK | ED11: OK | EE11: 1.05 | EI11: 1.49 | FQ11: 104056878
B12: =C12&"x"&I12 -> 61009x100202 | C12: =IF(G12="SINGLE",H12,G12) -> 61009 | D12: =_xlfn.XLOOKUP(I12,calculations!$t:$t,calculations!$s:$s) -> #VALUE! | E12: =_xlfn.XLOOKUP(I12,Mapping!$T:$T,Mapping!$Q:$Q) -> CASC03 | F12: 46203 | G12: 61009 | H12: 61009 | I12: 100202 | J12: Cascade Telecom | K12: Investor 9 Portfolio | L12: Investor 9 Portfolio | M12: Infra Debt | N12: 69543000 | O12: 69543000 | P12: USD | Q12: Loan | R12: N | S12: L100202 | T12: Infrastructure Debt | U12: DE | V12: Germany | W12: Telecom towers | X12: CR1002 | Y12: 12.6 | Z12: EUR | AA12: 1 | AB12: N | AC12: 72504000 | AD12: 72504000 | AE12: 72504000 | AF12: 0.9592 | AG12: 69543000 | AH12: 69543000 | AI12: 2961000 | AJ12: 72504000 | AK12: 69543000 | AL12: 69543000 | AN12: 3.671 | AO12: 5.067 | AP12: 3.783 | AQ12: 100 | AR12: 100 | AS12: 43414 | AT12: 51631 | AU12: 46295 | AV12: PI2002 | AW12: Silverline Transport | AX12: N | AY12: Cascade Telecom Finance Ltd | AZ12: Cascade Telecom Finance | BA12: Germany | BB12: Silverline Transport | BC12: 529900SYNTH000000002 | BI12: 72504000 | BJ12: 72504000 | BK12: Fixed | BL12: Senior Secured | BN12: 13.5 | BO12: 14.86 | BP12: N | BQ12: N | BR12: Debt | BS12: RA100202 | BT12: C. Dubois | BU12: F. Lindqvist | BW12: Semi-annual | BX12: 30/360 | BY12: 255 | BZ12: 255 | CC12: A | CD12: A | CE12: NR | CF12: NR | CG12: NR | CH12: 46112 | CI12: 1.2 | CJ12: 1.54 | CK12: 1.62 | CL12: OK | DA12: 0.8 | DC12: 0.85 | DD12: Watch | ED12: OK | EE12: 1.05 | EI12: 1.6 | FQ12: 58262138
B13: =C13&"x"&I13 -> 61014x100202 | C13: =IF(G13="SINGLE",H13,G13) -> 61014 | D13: =_xlfn.XLOOKUP(I13,calculations!$t:$t,calculations!$s:$s) -> #VALUE! | E13: =_xlfn.XLOOKUP(I13,Mapping!$T:$T,Mapping!$Q:$Q) -> CASC03 | F13: 46203 | G13: 61014 | H13: 61014 | I13: 100202 | J13: Cascade Telecom | K13: Investor 14 Mandate | L13: Investor 14 Mandate | M13: Infra Debt | N13: 84027000 | O13: 84027000 | P13: EUR | Q13: Loan | R13: N | S13: L100202 | T13: Infrastructure Debt | U13: DE | V13: Germany | W13: Telecom towers | X13: CR1002 | Y13: 12.6 | Z13: EUR | AA13: 1 | AB13: N | AC13: 87604000 | AD13: 87604000 | AE13: 87604000 | AF13: 0.9592 | AG13: 84027000 | AH13: 84027000 | AI13: 3577000 | AJ13: 87604000 | AK13: 84027000 | AL13: 84027000 | AN13: 6.402 | AO13: 6.252 | AP13: 5.575 | AQ13: 100 | AR13: 100 | AS13: 43414 | AT13: 51631 | AU13: 46295 | AV13: PI2002 | AW13: Silverline Transport | AX13: N | AY13: Cascade Telecom Finance Ltd | AZ13: Cascade Telecom Finance | BA13: Germany | BB13: Silverline Transport | BC13: 529900SYNTH000000002 | BI13: 87604000 | BJ13: 87604000 | BK13: Fixed | BL13: Senior Secured | BN13: 13.5 | BO13: 14.86 | BP13: N | BQ13: N | BR13: Debt | BS13: RA100202 | BT13: C. Dubois | BU13: F. Lindqvist | BW13: Semi-annual | BX13: ACT/360 | BY13: 255 | BZ13: 255 | CC13: A | CD13: A | CE13: NR | CF13: NR | CG13: NR | CH13: 46112 | CI13: 1.2 | CJ13: 2.14 | CK13: 2.25 | CL13: OK | DA13: 0.69 | DC13: 0.85 | DD13: OK | ED13: OK | EE13: 1.05 | EI13: 1.94 | FQ13: 56598815
B14: =C14&"x"&I14 -> 61019x100202 | C14: =IF(G14="SINGLE",H14,G14) -> 61019 | D14: =_xlfn.XLOOKUP(I14,calculations!$t:$t,calculations!$s:$s) -> #VALUE! | E14: =_xlfn.XLOOKUP(I14,Mapping!$T:$T,Mapping!$Q:$Q) -> CASC03 | F14: 46203 | G14: 61019 | H14: 61019 | I14: 100202 | J14: Cascade Telecom | K14: Investor 19 Mandate | L14: Investor 19 Mandate | M14: Infra Debt | N14: 64963000 | O14: 64963000 | P14: EUR | Q14: Loan | R14: N | S14: L100202 | T14: Infrastructure Debt | U14: DE | V14: Germany | W14: Telecom towers | X14: CR1002 | Y14: 12.6 | Z14: EUR | AA14: 1 | AB14: N | AC14: 67729000 | AD14: 67729000 | AE14: 67729000 | AF14: 0.9592 | AG14: 64963000 | AH14: 64963000 | AI14: 2766000 | AJ14: 67729000 | AK14: 64963000 | AL14: 64963000 | AN14: 3.926 | AO14: 2.913 | AP14: 5.202 | AQ14: 100 | AR14: 100 | AS14: 43414 | AT14: 51631 | AU14: 46295 | AV14: PI2002 | AW14: Silverline Transport | AX14: N | AY14: Cascade Telecom Finance Ltd | AZ14: Cascade Telecom Finance | BA14: Germany | BB14: Silverline Transport | BC14: 529900SYNTH000000002 | BI14: 67729000 | BJ14: 67729000 | BK14: Fixed | BL14: Senior Secured | BN14: 13.5 | BO14: 14.86 | BP14: N | BQ14: N | BR14: Debt | BS14: RA100202 | BT14: C. Dubois | BU14: C. Dubois | BW14: Quarterly | BX14: ACT/360 | BY14: 255 | BZ14: 255 | CC14: A | CD14: A | CE14: NR | CF14: NR | CG14: NR | CH14: 46112 | CI14: 1.2 | CJ14: 1.62 | CK14: 1.7 | CL14: OK | DA14: 0.56 | DC14: 0.85 | DD14: OK | ED14: OK | EE14: 1.05 | EI14: 1.23 | FQ14: 60658550
B15: =C15&"x"&I15 -> 61018x100202 | C15: =IF(G15="SINGLE",H15,G15) -> 61018 | D15: =_xlfn.XLOOKUP(I15,calculations!$t:$t,calculations!$s:$s) -> #VALUE! | E15: =_xlfn.XLOOKUP(I15,Mapping!$T:$T,Mapping!$Q:$Q) -> CASC03 | F15: 46203 | G15: 61018 | H15: 61018 | I15: 100202 | J15: Cascade Telecom | K15: Investor 18 Mandate | L15: Investor 18 Mandate | M15: Infra Debt | N15: 25434000 | O15: 25434000 | P15: EUR | Q15: Loan | R15: N | S15: L100202 | T15: Infrastructure Debt | U15: DE | V15: Germany | W15: Telecom towers | X15: CR1002 | Y15: 12.6 | Z15: EUR | AA15: 1 | AB15: N | AC15: 26517000 | AD15: 26517000 | AE15: 26517000 | AF15: 0.9592 | AG15: 25434000 | AH15: 25434000 | AI15: 1083000 | AJ15: 26517000 | AK15: 25434000 | AL15: 25434000 | AN15: 5.354 | AO15: 5.699 | AP15: 5.276 | AQ15: 100 | AR15: 100 | AS15: 43414 | AT15: 51631 | AU15: 46295 | AV15: PI2002 | AW15: Silverline Transport | AX15: N | AY15: Cascade Telecom Finance Ltd | AZ15: Cascade Telecom Finance | BA15: Germany | BB15: Silverline Transport | BC15: 529900SYNTH000000002 | BI15: 26517000 | BJ15: 26517000 | BK15: Fixed | BL15: Senior Secured | BN15: 13.5 | BO15: 14.86 | BP15: N | BQ15: N | BR15: Debt | BS15: RA100202 | BT15: C. Dubois | BU15: C. Dubois | BW15: Quarterly | BX15: ACT/360 | BY15: 255 | BZ15: 255 | CC15: A | CD15: A | CE15: NR | CF15: NR | CG15: NR | CH15: 46112 | CI15: 1.2 | CJ15: 2.87 | CK15: 3.01 | CL15: OK | DA15: 0.71 | DC15: 0.85 | DD15: OK | ED15: Watch | EE15: 1.05 | EI15: 1.18 | FQ15: 59484021
B16: =C16&"x"&I16 -> 61013x100203 | C16: =IF(G16="SINGLE",H16,G16) -> 61013 | D16: =_xlfn.XLOOKUP(I16,calculations!$t:$t,calculations!$s:$s) -> #VALUE! | E16: =_xlfn.XLOOKUP(I16,Mapping!$T:$T,Mapping!$Q:$Q) -> DELT04 | F16: 46203 | G16: 61013 | H16: 61013 | I16: 100203 | J16: Delta Water A | K16: Investor 13 Mandate | L16: Investor 13 Mandate | M16: Infra Debt | N16: 447000 | O16: 522807.02 | P16: EUR | Q16: Private Placement Note | R16: N | S16: L100203 | T16: Infrastructure Debt | U16: GB | V16: United Kingdom | W16: Water | X16: CR1003 | Y16: 14.2 | Z16: GBP | AA16: 0.855 | AB16: Y | AC16: 858000 | AD16: 858000 | AE16: 1003508.8 | AF16: 0.521 | AG16: 447000 | AH16: 447000 | AI16: 411000 | AJ16: 858000 | AK16: 447000 | AL16: 447000 | AN16: 5.084 | AO16: 5.506 | AP16: 4.799 | AQ16: 100 | AR16: 100 | AS16: 44791 | AT16: 54288 | AU16: 46295 | AV16: PI2003 | AW16: Corvus Digital | AX16: N | AY16: Delta Water Finance Ltd | AZ16: Delta Water Finance | BA16: United Kingdom | BB16: Corvus Digital | BC16: 529900SYNTH000000003 | BI16: 858000 | BJ16: 1003508.8 | BK16: Fixed | BL16: Senior Secured | BN16: 15.6 | BO16: 22.14 | BP16: N | BQ16: N | BR16: Debt | BS16: RA100203 | BT16: A. Martin | BU16: D. Schäfer | BW16: Semi-annual | BX16: 30/360 | BY16: 325 | BZ16: 325 | CC16: BBB+ | CD16: BBB+ | CE16: NR | CF16: NR | CG16: NR | CH16: 46112 | CI16: 1.2 | CJ16: 2.09 | CK16: 2.19 | CL16: OK | DA16: 0.49 | DC16: 0.85 | DD16: OK | ED16: OK | EE16: 1.05 | EI16: 1.63 | FQ16: 9462110
B17: =C17&"x"&I17 -> 61013x100204 | C17: =IF(G17="SINGLE",H17,G17) -> 61013 | D17: =_xlfn.XLOOKUP(I17,calculations!$t:$t,calculations!$s:$s) -> #VALUE! | E17: =_xlfn.XLOOKUP(I17,Mapping!$T:$T,Mapping!$Q:$Q) -> DELT04 | F17: 46203 | G17: 61013 | H17: 61013 | I17: 100204 | J17: Delta Water B | K17: Investor 13 Mandate | L17: Investor 13 Mandate | M17: Infra Debt | N17: 298000 | O17: 348538.01 | P17: EUR | Q17: Private Placement Note | R17: N | S17: L100204 | T17: Infrastructure Debt | U17: GB | V17: United Kingdom | W17: Water | X17: CR1003 | Y17: 14.2 | Z17: GBP | AA17: 0.855 | AB17: Y | AC17: 572000 | AD17: 572000 | AE17: 669005.85 | AF17: 0.521 | AG17: 298000 | AH17: 298000 | AI17: 274000 | AJ17: 572000 | AK17: 298000 | AL17: 298000 | AN17: 4.364 | AO17: 4.443 | AP17: 2.762 | AQ17: 100 | AR17: 100 | AS17: 44791 | AT17: 54288 | AU17: 46295 | AV17: PI2003 | AW17: Corvus Digital | AX17: N | AY17: Delta Water Finance Ltd | AZ17: Delta Water Finance | BA17: United Kingdom | BB17: Corvus Digital | BC17: 529900SYNTH000000003 | BI17: 572000 | BJ17: 669005.85 | BK17: Fixed | BL17: Senior Secured | BN17: 15.6 | BO17: 22.14 | BP17: N | BQ17: N | BR17: Debt | BS17: RA100204 | BT17: A. Martin | BU17: C. Dubois | BW17: Semi-annual | BX17: 30/360 | BY17: 325 | BZ17: 325 | CC17: BBB+ | CD17: BBB+ | CE17: NR | CF17: NR | CG17: NR | CH17: 46112 | CI17: 1.2 | CJ17: 1.92 | CK17: 2.02 | CL17: OK | DA17: 0.83 | DC17: 0.85 | DD17: Watch | ED17: Watch | EE17: 1.05 | EI17: 1.13 | FQ17: 11051966
B18: =C18&"x"&I18 -> 61022x100203 | C18: =IF(G18="SINGLE",H18,G18) -> 61022 | D18: =_xlfn.XLOOKUP(I18,calculations!$t:$t,calculations!$s:$s) -> #VALUE! | E18: =_xlfn.XLOOKUP(I18,Mapping!$T:$T,Mapping!$Q:$Q) -> DELT04 | F18: 46203 | G18: 61022 | H18: 61022 | I18: 100203 | J18: Delta Water A | K18: Fund 2 Fund | L18: Fund 2 Fund | M18: Infra Debt | N18: 1213000 | O18: 1418713.4 | P18: EUR | Q18: Private Placement Note | R18: N | S18: L100203 | T18: Infrastructure Debt | U18: GB | V18: United Kingdom | W18: Water | X18: CR1003 | Y18: 14.2 | Z18: GBP | AA18: 0.855 | AB18: Y | AC18: 2331000 | AD18: 2331000 | AE18: 2726315.8 | AF18: 0.5204 | AG18: 1213000 | AH18: 1213000 | AI18: 1118000 | AJ18: 2331000 | AK18: 1213000 | AL18: 1213000 | AN18: 3.159 | AO18: 5.725 | AP18: 2.703 | AQ18: 100 | AR18: 100 | AS18: 44791 | AT18: 54288 | AU18: 46295 | AV18: PI2003 | AW18: Corvus Digital | AX18: N | AY18: Delta Water Finance Ltd | AZ18: Delta Water Finance | BA18: United Kingdom | BB18: Corvus Digital | BC18: 529900SYNTH000000003 | BI18: 2331000 | BJ18: 2726315.8 | BK18: Fixed | BL18: Senior Secured | BN18: 15.6 | BO18: 22.14 | BP18: N | BQ18: N | BR18: Debt | BS18: RA100203 | BT18: A. Martin | BU18: B. Okoro | BW18: Semi-annual | BX18: 30/360 | BY18: 325 | BZ18: 325 | CC18: BBB+ | CD18: BBB+ | CE18: NR | CF18: NR | CG18: NR | CH18: 46112 | CI18: 1.2 | CJ18: 2.54 | CK18: 2.67 | CL18: OK | DA18: 0.73 | DC18: 0.85 | DD18: OK | ED18: OK | EE18: 1.05 | EI18: 1.94 | FQ18: 12516714
B19: =C19&"x"&I19 -> 61022x100204 | C19: =IF(G19="SINGLE",H19,G19) -> 61022 | D19: =_xlfn.XLOOKUP(I19,calculations!$t:$t,calculations!$s:$s) -> #VALUE! | E19: =_xlfn.XLOOKUP(I19,Mapping!$T:$T,Mapping!$Q:$Q) -> DELT04 | F19: 46203 | G19: 61022 | H19: 61022 | I19: 100204 | J19: Delta Water B | K19: Fund 2 Fund | L19: Fund 2 Fund | M19: Infra Debt | N19: 809000 | O19: 946198.83 | P19: EUR | Q19: Private Placement Note | R19: N | S19: L100204 | T19: Infrastructure Debt | U19: GB | V19: United Kingdom | W19: Water | X19: CR1003 | Y19: 14.2 | Z19: GBP | AA19: 0.855 | AB19: Y | AC19: 1554000 | AD19: 1554000 | AE19: 1817543.9 | AF19: 0.5206 | AG19: 809000 | AH19: 809000 | AI19: 745000 | AJ19: 1554000 | AK19: 809000 | AL19: 809000 | AN19: 3.808 | AO19: 2.822 | AP19: 2.923 | AQ19: 100 | AR19: 100 | AS19: 44791 | AT19: 54288 | AU19: 46295 | AV19: PI2003 | AW19: Corvus Digital | AX19: N | AY19: Delta Water Finance Ltd | AZ19: Delta Water Finance | BA19: United Kingdom | BB19: Corvus Digital | BC19: 529900SYNTH000000003 | BI19: 1554000 | BJ19: 1817543.9 | BK19: Fixed | BL19: Senior Secured | BN19: 15.6 | BO19: 22.14 | BP19: N | BQ19: N | BR19: Debt | BS19: RA100204 | BT19: A. Martin | BU19: F. Lindqvist | BW19: Quarterly | BX19: ACT/360 | BY19: 325 | BZ19: 325 | CC19: BBB+ | CD19: BBB+ | CE19: NR | CF19: NR | CG19: NR | CH19: 46112 | CI19: 1.2 | CJ19: 3.47 | CK19: 3.64 | CL19: OK | DA19: 0.53 | DC19: 0.85 | DD19: OK | ED19: OK | EE19: 1.05 | EI19: 1.62 | FQ19: 11587832
B20: =C20&"x"&I20 -> 61017x100203 | C20: =IF(G20="SINGLE",H20,G20) -> 61017 | D20: =_xlfn.XLOOKUP(I20,calculations!$t:$t,calculations!$s:$s) -> #VALUE! | E20: =_xlfn.XLOOKUP(I20,Mapping!$T:$T,Mapping!$Q:$Q) -> DELT04 | F20: 46203 | G20: 61017 | H20: 61017 | I20: 100203 | J20: Delta Water A | K20: Investor 17 Mandate | L20: Investor 17 Mandate | M20: Infra Debt | N20: 706000 | O20: 825730.99 | P20: EUR | Q20: Private Placement Note | R20: N | S20: L100203 | T20: Infrastructure Debt | U20: GB | V20: United Kingdom | W20: Water | X20: CR1003 | Y20: 14.2 | Z20: GBP | AA20: 0.855 | AB20: Y | AC20: 1356000 | AD20: 1356000 | AE20: 1585964.9 | AF20: 0.5206 | AG20: 706000 | AH20: 706000 | AI20: 650000 | AJ20: 1356000 | AK20: 706000 | AL20: 706000 | AN20: 2.942 | AO20: 3.274 | AP20: 3.515 | AQ20: 100 | AR20: 100 | AS20: 44791 | AT20: 54288 | AU20: 46295 | AV20: PI2003 | AW20: Corvus Digital | AX20: N | AY20: Delta Water Finance Ltd | AZ20: Delta Water Finance | BA20: United Kingdom | BB20: Corvus Digital | BC20: 529900SYNTH000000003 | BI20: 1356000 | BJ20: 1585964.9 | BK20: Fixed | BL20: Senior Secured | BN20: 15.6 | BO20: 22.14 | BP20: N | BQ20: N | BR20: Debt | BS20: RA100203 | BT20: A. Martin | BU20: A. Martin | BW20: Quarterly | BX20: 30/360 | BY20: 325 | BZ20: 325 | CC20: BBB+ | CD20: BBB+ | CE20: NR | CF20: NR | CG20: NR | CH20: 46112 | CI20: 1.2 | CJ20: 2.75 | CK20: 2.89 | CL20: OK | DA20: 0.54 | DC20: 0.85 | DD20: OK | ED20: OK | EE20: 1.05 | EI20: 1.46 | FQ20: 9298998
B21: =C21&"x"&I21 -> 61017x100204 | C21: =IF(G21="SINGLE",H21,G21) -> 61017 | D21: =_xlfn.XLOOKUP(I21,calculations!$t:$t,calculations!$s:$s) -> #VALUE! | E21: =_xlfn.XLOOKUP(I21,Mapping!$T:$T,Mapping!$Q:$Q) -> DELT04 | F21: 46203 | G21: 61017 | H21: 61017 | I21: 100204 | J21: Delta Water B | K21: Investor 17 Mandate | L21: Investor 17 Mandate | M21: Infra Debt | N21: 471000 | O21: 550877.19 | P21: EUR | Q21: Private Placement Note | R21: N | S21: L100204 | T21: Infrastructure Debt | U21: GB | V21: United Kingdom | W21: Water | X21: CR1003 | Y21: 14.2 | Z21: GBP | AA21: 0.855 | AB21: Y | AC21: 904000 | AD21: 904000 | AE21: 1057309.9 | AF21: 0.521 | AG21: 471000 | AH21: 471000 | AI21: 433000 | AJ21: 904000 | AK21: 471000 | AL21: 471000 | AN21: 4.253 | AO21: 4.45 | AP21: 5.654 | AQ21: 100 | AR21: 100 | AS21: 44791 | AT21: 54288 | AU21: 46295 | AV21: PI2003 | AW21: Corvus Digital | AX21: N | AY21: Delta Water Finance Ltd | AZ21: Delta Water Finance | BA21: United Kingdom | BB21: Corvus Digital | BC21: 529900SYNTH000000003 | BI21: 904000 | BJ21: 1057309.9 | BK21: Fixed | BL21: Senior Secured | BN21: 15.6 | BO21: 22.14 | BP21: N | BQ21: N | BR21: Debt | BS21: RA100204 | BT21: A. Martin | BU21: B. Okoro | BW21: Semi-annual | BX21: 30/360 | BY21: 325 | BZ21: 325 | CC21: BBB+ | CD21: BBB+ | CE21: NR | CF21: NR | CG21: NR | CH21: 46112 | CI21: 1.2 | CJ21: 3.12 | CK21: 3.28 | CL21: OK | DA21: 0.72 | DC21: 0.85 | DD21: OK | ED21: Watch | EE21: 1.05 | EI21: 1.14 | FQ21: 8993354
B22: =C22&"x"&I22 -> 61019x100203 | C22: =IF(G22="SINGLE",H22,G22) -> 61019 | D22: =_xlfn.XLOOKUP(I22,calculations!$t:$t,calculations!$s:$s) -> #VALUE! | E22: =_xlfn.XLOOKUP(I22,Mapping!$T:$T,Mapping!$Q:$Q) -> DELT04 | F22: 46203 | G22: 61019 | H22: 61019 | I22: 100203 | J22: Delta Water A | K22: Investor 19 Mandate | L22: Investor 19 Mandate | M22: Infra Debt | N22: 1258000 | O22: 1471345 | P22: EUR | Q22: Private Placement Note | R22: N | S22: L100203 | T22: Infrastructure Debt | U22: GB | V22: United Kingdom | W22: Water | X22: CR1003 | Y22: 14.2 | Z22: GBP | AA22: 0.855 | AB22: Y | AC22: 2417000 | AD22: 2417000 | AE22: 2826900.6 | AF22: 0.5205 | AG22: 1258000 | AH22: 1258000 | AI22: 1159000 | AJ22: 2417000 | AK22: 1258000 | AL22: 1258000 | AN22: 3.116 | AO22: 4.798 | AP22: 5.089 | AQ22: 100 | AR22: 100 | AS22: 44791 | AT22: 54288 | AU22: 46295 | AV22: PI2003 | AW22: Corvus Digital | AX22: N | AY22: Delta Water Finance Ltd | AZ22: Delta Water Finance | BA22: United Kingdom | BB22: Corvus Digital | BC22: 529900SYNTH000000003 | BI22: 2417000 | BJ22: 2826900.6 | BK22: Fixed | BL22: Senior Secured | BN22: 15.6 | BO22: 22.14 | BP22: N | BQ22: N | BR22: Debt | BS22: RA100203 | BT22: A. Martin | BU22: F. Lindqvist | BW22: Semi-annual | BX22: 30/360 | BY22: 325 | BZ22: 325 | CC22: BBB+ | CD22: BBB+ | CE22: NR | CF22: NR | CG22: NR | CH22: 46112 | CI22: 1.2 | CJ22: 2.11 | CK22: 2.22 | CL22: OK | DA22: 0.71 | DC22: 0.85 | DD22: OK | ED22: OK | EE22: 1.05 | EI22: 1.73 | FQ22: 9598306
B23: =C23&"x"&I23 -> 61019x100204 | C23: =IF(G23="SINGLE",H23,G23) -> 61019 | D23: =_xlfn.XLOOKUP(I23,calculations!$t:$t,calculations!$s:$s) -> #VALUE! | E23: =_xlfn.XLOOKUP(I23,Mapping!$T:$T,Mapping!$Q:$Q) -> DELT04 | F23: 46203 | G23: 61019 | H23: 61019 | I23: 100204 | J23: Delta Water B | K23: Investor 19 Mandate | L23: Investor 19 Mandate | M23: Infra Debt | N23: 839000 | O23: 981286.55 | P23: EUR | Q23: Private Placement Note | R23: N | S23: L100204 | T23: Infrastructure Debt | U23: GB | V23: United Kingdom | W23: Water | X23: CR1003 | Y23: 14.2 | Z23: GBP | AA23: 0.855 | AB23: Y | AC23: 1612000 | AD23: 1612000 | AE23: 1885380.1 | AF23: 0.5205 | AG23: 839000 | AH23: 839000 | AI23: 773000 | AJ23: 1612000 | AK23: 839000 | AL23: 839000 | AN23: 5.316 | AO23: 6.075 | AP23: 4.964 | AQ23: 100 | AR23: 100 | AS23: 44791 | AT23: 54288 | AU23: 46295 | AV23: PI2003 | AW23: Corvus Digital | AX23: N | AY23: Delta Water Finance Ltd | AZ23: Delta Water Finance | BA23: United Kingdom | BB23: Corvus Digital | BC23: 529900SYNTH000000003 | BI23: 1612000 | BJ23: 1885380.1 | BK23: Fixed | BL23: Senior Secured | BN23: 15.6 | BO23: 22.14 | BP23: N | BQ23: N | BR23: Debt | BS23: RA100204 | BT23: A. Martin | BU23: C. Dubois | BW23: Quarterly | BX23: ACT/360 | BY23: 325 | BZ23: 325 | CC23: BBB+ | CD23: BBB+ | CE23: NR | CF23: NR | CG23: NR | CH23: 46112 | CI23: 1.2 | CJ23: 1.23 | CK23: 1.29 | CL23: Watch | DA23: 0.78 | DC23: 0.85 | DD23: OK | ED23: OK | EE23: 1.05 | EI23: 1.73 | FQ23: 8770079
... B39: =C39&"x"&I39 -> 61005x100206 | C39: =IF(G39="SINGLE",H39,G39) -> 61005 | D39: =_xlfn.XLOOKUP(I39,calculations!$t:$t,calculations!$s:$s) -> #VALUE! | E39: =_xlfn.XLOOKUP(I39,Mapping!$T:$T,Mapping!$Q:$Q) -> EMBE05 | F39: 46203 | G39: 61005 | H39: 61005 | I39: 100206 | J39: Ember Battery B | K39: Investor 5 Portfolio | L39: Investor 5 Portfolio | M39: Infra Debt | N39: 5267000 | O39: 5267000 | P39: EUR | Q39: Loan | R39: N | S39: L100206 | T39: Infrastructure Debt | U39: IT | V39: Italy | W39: Battery storage | X39: CR1004 | Y39: 8.1 | Z39: EUR | AA39: 1 | AB39: N | AC39: 5683000 | AD39: 5683000 | AE39: 5683000 | AF39: 0.9268 | AG39: 5267000 | AH39: 5267000 | AI39: 416000 | AJ39: 5683000 | AK39: 5267000 | AL39: 5267000 | AN39: 4.278 | AO39: 3.432 | AP39: 5.278 | AQ39: 100 | AR39: 100 | AS39: 44791 | AT39: 48809 | AU39: 46295 | AV39: PI2004 | AW39: Terra Social Infra | AX39: N | AY39: Ember Battery Finance Ltd | AZ39: Ember Battery Finance | BA39: Italy | BB39: Terra Social Infra | BC39: 529900SYNTH000000004 | BI39: 5683000 | BJ39: 5683000 | BK39: Fixed | BL39: Senior Secured | BN39: 6.6 | BO39: 7.13 | BP39: N | BQ39: N | BR39: Debt | BS39: RA100206 | BT39: D. Schäfer | BU39: E. Rossi | BW39: Semi-annual | BX39: 30/360 | BY39: 245 | BZ39: 245 | CC39: BB- | CD39: BB- | CE39: BB- | CF39: NR | CG39: NR | CH39: 46112 | CI39: 1.2 | CJ39: 2.12 | CK39: 2.23 | CL39: OK | DA39: 0.59 | DC39: 0.85 | DD39: OK | ED39: OK | EE39: 1.05 | EI39: 1.51 | FQ39: 45818448
B40: =C40&"x"&I40 -> 61003x100207 | C40: =IF(G40="SINGLE",H40,G40) -> 61003 | D40: =_xlfn.XLOOKUP(I40,calculations!$t:$t,calculations!$s:$s) -> #VALUE! | E40: =_xlfn.XLOOKUP(I40,Mapping!$T:$T,Mapping!$Q:$Q) -> FALC06 | F40: 46203 | G40: 61003 | H40: 61003 | I40: 100207 | J40: Falcon Hospitals | K40: Investor 3 Portfolio | L40: Investor 3 Portfolio | M40: Infra Debt | N40: 23405000 | O40: 27374269 | P40: EUR | Q40: Private Placement Note | R40: Y | S40: L100207 | T40: Infrastructure Debt | U40: GB | V40: United Kingdom | W40: Hospitals (PPP) | X40: CR1005 | Y40: 10.6 | Z40: GBP | AA40: 0.855 | AB40: Y | AC40: 24564000 | AD40: 24564000 | AE40: 28729825 | AF40: 0.9528 | AG40: 23405000 | AH40: 23405000 | AI40: 1159000 | AJ40: 24564000 | AK40: 23405000 | AL40: 23405000 | AM40: EURIBOR 6M | AN40: 2.564 | AO40: 6.433 | AP40: 6.369 | AQ40: 100 | AR40: 100 | AS40: 45246 | AT40: 51456 | AU40: 46295 | AV40: PI2005 | AW40: Northwind Capital | AX40: N | AY40: Falcon Hospitals Finance Ltd | AZ40: Falcon Hospitals Finance | BA40: United Kingdom | BB40: Northwind Capital | BC40: 529900SYNTH000000005 | BI40: 24564000 | BJ40: 28729825 | BK40: Floating | BL40: Senior Secured | BN40: 10.2 | BO40: 14.38 | BP40: Y | BQ40: Y | BR40: Debt | BS40: RA100207 | BT40: B. Okoro | BU40: A. Martin | BW40: Semi-annual | BX40: ACT/360 | BY40: 255 | BZ40: 255 | CB40: EURIBOR | CC40: BBB | CD40: BBB | CE40: BBB+ | CF40: NR | CG40: Baa3 | CH40: 46112 | CI40: 1.2 | CJ40: 2.4 | CK40: 2.52 | CL40: OK | DA40: 0.45 | DC40: 0.85 | DD40: OK | ED40: OK | EE40: 1.05 | EI40: 1.94 | FQ40: 11531835
B41: =C41&"x"&I41 -> 61015x100207 | C41: =IF(G41="SINGLE",H41,G41) -> 61015 | D41: =_xlfn.XLOOKUP(I41,calculations!$t:$t,calculations!$s:$s) -> #VALUE! | E41: =_xlfn.XLOOKUP(I41,Mapping!$T:$T,Mapping!$Q:$Q) -> FALC06 | F41: 46203 | G41: 61015 | H41: 61015 | I41: 100207 | J41: Falcon Hospitals | K41: Investor 15 Mandate | L41: Investor 15 Mandate | M41: Infra Debt | N41: 15106000 | O41: 17667836 | P41: EUR | Q41: Private Placement Note | R41: Y | S41: L100207 | T41: Infrastructure Debt | U41: GB | V41: United Kingdom | W41: Hospitals (PPP) | X41: CR1005 | Y41: 10.6 | Z41: GBP | AA41: 0.855 | AB41: Y | AC41: 15854000 | AD41: 15854000 | AE41: 18542690 | AF41: 0.9528 | AG41: 15106000 | AH41: 15106000 | AI41: 748000 | AJ41: 15854000 | AK41: 15106000 | AL41: 15106000 | AM41: EURIBOR 6M | AN41: 6.262 | AO41: 2.776 | AP41: 5.614 | AQ41: 100 | AR41: 100 | AS41: 45246 | AT41: 51456 | AU41: 46295 | AV41: PI2005 | AW41: Northwind Capital | AX41: N | AY41: Falcon Hospitals Finance Ltd | AZ41: Falcon Hospitals Finance | BA41: United Kingdom | BB41: Northwind Capital | BC41: 529900SYNTH000000005 | BI41: 15854000 | BJ41: 18542690 | BK41: Floating | BL41: Senior Secured | BN41: 10.2 | BO41: 14.38 | BP41: Y | BQ41: Y | BR41: Debt | BS41: RA100207 | BT41: B. Okoro | BU41: D. Schäfer | BW41: Semi-annual | BX41: ACT/360 | BY41: 255 | BZ41: 255 | CB41: EURIBOR | CC41: BBB | CD41: BBB | CE41: BBB+ | CF41: NR | CG41: Baa3 | CH41: 46112 | CI41: 1.2 | CJ41: 2.5 | CK41: 2.63 | CL41: OK | DA41: 0.54 | DC41: 0.85 | DD41: OK | ED41: OK | EE41: 1.05 | EI41: 1.29 | FQ41: 17538903
B42: =C42&"x"&I42 -> 61019x100207 | C42: =IF(G42="SINGLE",H42,G42) -> 61019 | D42: =_xlfn.XLOOKUP(I42,calculations!$t:$t,calculations!$s:$s) -> #VALUE! | E42: =_xlfn.XLOOKUP(I42,Mapping!$T:$T,Mapping!$Q:$Q) -> FALC06 | F42: 46203 | G42: 61019 | H42: 61019 | I42: 100207 | J42: Falcon Hospitals | K42: Investor 19 Mandate | L42: Investor 19 Mandate | M42: Infra Debt | N42: 13357000 | O42: 15622222 | P42: EUR | Q42: Private Placement Note | R42: Y | S42: L100207 | T42: Infrastructure Debt | U42: GB | V42: United Kingdom | W42: Hospitals (PPP) | X42: CR1005 | Y42: 10.6 | Z42: GBP | AA42: 0.855 | AB42: Y | AC42: 14019000 | AD42: 14019000 | AE42: 16396491 | AF42: 0.9528 | AG42: 13357000 | AH42: 13357000 | AI42: 662000 | AJ42: 14019000 | AK42: 13357000 | AL42: 13357000 | AM42: EURIBOR 6M | AN42: 6.147 | AO42: 3.883 | AP42: 3.477 | AQ42: 100 | AR42: 100 | AS42: 45246 | AT42: 51456 | AU42: 46295 | AV42: PI2005 | AW42: Northwind Capital | AX42: N | AY42: Falcon Hospitals Finance Ltd | AZ42: Falcon Hospitals Finance | BA42: United Kingdom | BB42: Northwind Capital | BC42: 529900SYNTH000000005 | BI42: 14019000 | BJ42: 16396491 | BK42: Floating | BL42: Senior Secured | BN42: 10.2 | BO42: 14.38 | BP42: Y | BQ42: Y | BR42: Debt | BS42: RA100207 | BT42: B. Okoro | BU42: A. Martin | BW42: Semi-annual | BX42: 30/360 | BY42: 255 | BZ42: 255 | CB42: EURIBOR | CC42: BBB | CD42: BBB | CE42: BBB+ | CF42: NR | CG42: Baa3 | CH42: 46112 | CI42: 1.2 | CJ42: 2.66 | CK42: 2.79 | CL42: OK | DA42: 0.84 | DC42: 0.85 | DD42: Watch | ED42: OK | EE42: 1.05 | EI42: 1.63 | FQ42: 15740291
B43: =C43&"x"&I43 -> 61022x100207 | C43: =IF(G43="SINGLE",H43,G43) -> 61022 | D43: =_xlfn.XLOOKUP(I43,calculations!$t:$t,calculations!$s:$s) -> #VALUE! | E43: =_xlfn.XLOOKUP(I43,Mapping!$T:$T,Mapping!$Q:$Q) -> FALC06 | F43: 46203 | G43: 61022 | H43: 61022 | I43: 100207 | J43: Falcon Hospitals | K43: Fund 2 Fund | L43: Fund 2 Fund | M43: Infra Debt | N43: 21398000 | O43: 25026901 | P43: EUR | Q43: Private Placement Note | R43: Y | S43: L100207 | T43: Infrastructure Debt | U43: GB | V43: United Kingdom | W43: Hospitals (PPP) | X43: CR1005 | Y43: 10.6 | Z43: GBP | AA43: 0.855 | AB43: Y | AC43: 22458000 | AD43: 22458000 | AE43: 26266667 | AF43: 0.9528 | AG43: 21398000 | AH43: 21398000 | AI43: 1060000 | AJ43: 22458000 | AK43: 21398000 | AL43: 21398000 | AM43: EURIBOR 6M | AN43: 3.491 | AO43: 2.595 | AP43: 3.331 | AQ43: 100 | AR43: 100 | AS43: 45246 | AT43: 51456 | AU43: 46295 | AV43: PI2005 | AW43: Northwind Capital | AX43: N | AY43: Falcon Hospitals Finance Ltd | AZ43: Falcon Hospitals Finance | BA43: United Kingdom | BB43: Northwind Capital | BC43: 529900SYNTH000000005 | BI43: 22458000 | BJ43: 26266667 | BK43: Floating | BL43: Senior Secured | BN43: 10.2 | BO43: 14.38 | BP43: Y | BQ43: Y | BR43: Debt | BS43: RA100207 | BT43: B. Okoro | BU43: D. Schäfer | BW43: Quarterly | BX43: 30/360 | BY43: 255 | BZ43: 255 | CB43: EURIBOR | CC43: BBB | CD43: BBB | CE43: BBB+ | CF43: NR | CG43: Baa3 | CH43: 46112 | CI43: 1.2 | CJ43: 3.09 | CK43: 3.24 | CL43: OK | DA43: 0.64 | DC43: 0.85 | DD43: OK | ED43: OK | EE43: 1.05 | EI43: 1.75 | FQ43: 18858372
B44: =C44&"x"&I44 -> 61023x100208 | C44: =IF(G44="SINGLE",H44,G44) -> 61023 | D44: =_xlfn.XLOOKUP(I44,calculations!$t:$t,calculations!$s:$s) -> #VALUE! | E44: =_xlfn.XLOOKUP(I44,Mapping!$T:$T,Mapping!$Q:$Q) -> GRAN07 | F44: 46203 | G44: 61023 | H44: 61023 | I44: 100208 | J44: Granite Hydro | K44: Fund 3 Fund | L44: Fund 3 Fund | M44: Infra Debt | N44: 41561000 | O44: 41561000 | P44: EUR | Q44: Loan | R44: N | S44: L100208 | T44: Infrastructure Debt | U44: IE | V44: Ireland | W44: Hydro | X44: CR1006 | Y44: 8.7 | Z44: EUR | AA44: 1 | AB44: N | AC44: 41061000 | AD44: 41061000 | AE44: 41061000 | AF44: 1.0122 | AG44: 41561000 | AH44: 41561000 | AI44: -500000 | AJ44: 41061000 | AK44: 41561000 | AL44: 41561000 | AM44: EURIBOR 6M | AN44: 5.629 | AO44: 3.943 | AP44: 2.581 | AQ44: 100 | AR44: 100 | AS44: 42133 | AT44: 47431 | AU44: 46295 | AV44: PI2006 | AW44: Meridian Infrastructure | AX44: N | AY44: Granite Hydro Finance Ltd | AZ44: Granite Hydro Finance | BA44: Ireland | BB44: Meridian Infrastructure | BC44: 529900SYNTH000000006 | BI44: 41061000 | BJ44: 41061000 | BK44: Floating | BL44: Senior Secured | BN44: 8.7 | BO44: 3.36 | BP44: Y | BQ44: N | BR44: Debt | BS44: RA100208 | BT44: D. Schäfer | BU44: F. Lindqvist | BW44: Semi-annual | BX44: ACT/360 | BY44: 220 | BZ44: 220 | CB44: EURIBOR | CC44: AA- | CD44: AA- | CE44: AA- | CF44: AA | CG44: NR | CH44: 46112 | CI44: 1.2 | CJ44: 1.7 | CK44: 1.78 | CL44: OK | DA44: 0.55 | DC44: 0.85 | DD44: OK | ED44: OK | EE44: 1.05 | EI44: 1.7 | FQ44: 82486249
B45: =C45&"x"&I45 -> 61021x100208 | C45: =IF(G45="SINGLE",H45,G45) -> 61021 | D45: =_xlfn.XLOOKUP(I45,calculations!$t:$t,calculations!$s:$s) -> #VALUE! | E45: =_xlfn.XLOOKUP(I45,Mapping!$T:$T,Mapping!$Q:$Q) -> GRAN07 | F45: 46203 | G45: 61021 | H45: 61021 | I45: 100208 | J45: Granite Hydro | K45: Fund 1 Fund | L45: Fund 1 Fund | M45: Infra Debt | N45: 35221000 | O45: 35221000 | P45: EUR | Q45: Loan | R45: N | S45: L100208 | T45: Infrastructure Debt | U45: IE | V45: Ireland | W45: Hydro | X45: CR1006 | Y45: 8.7 | Z45: EUR | AA45: 1 | AB45: N | AC45: 35577000 | AD45: 35577000 | AE45: 35577000 | AF45: 0.99 | AG45: 35221000 | AH45: 35221000 | AI45: 356000 | AJ45: 35577000 | AK45: 35221000 | AL45: 35221000 | AM45: EURIBOR 6M | AN45: 3.58 | AO45: 3.56 | AP45: 6.015 | AQ45: 100 | AR45: 100 | AS45: 42133 | AT45: 47431 | AU45: 46295 | AV45: PI2006 | AW45: Meridian Infrastructure | AX45: N | AY45: Granite Hydro Finance Ltd | AZ45: Granite Hydro Finance | BA45: Ireland | BB45: Meridian Infrastructure | BC45: 529900SYNTH000000006 | BI45: 35577000 | BJ45: 35577000 | BK45: Floating | BL45: Senior Secured | BN45: 8.7 | BO45: 3.36 | BP45: Y | BQ45: N | BR45: Debt | BS45: RA100208 | BT45: D. Schäfer | BU45: E. Rossi | BW45: Quarterly | BX45: ACT/360 | BY45: 220 | BZ45: 220 | CB45: EURIBOR | CC45: AA- | CD45: AA- | CE45: AA- | CF45: AA | CG45: NR | CH45: 46112 | CI45: 1.2 | CJ45: 1.33 | CK45: 1.4 | CL45: OK | DA45: 0.79 | DC45: 0.85 | DD45: OK | ED45: Watch | EE45: 1.05 | EI45: 1.18 | FQ45: 62491674
B46: =C46&"x"&I46 -> 61007x100208 | C46: =IF(G46="SINGLE",H46,G46) -> 61007 | D46: =_xlfn.XLOOKUP(I46,calculations!$t:$t,calculations!$s:$s) -> #VALUE! | E46: =_xlfn.XLOOKUP(I46,Mapping!$T:$T,Mapping!$Q:$Q) -> GRAN07 | F46: 46203 | G46: 61007 | H46: 61007 | I46: 100208 | J46: Granite Hydro | K46: Investor 7 Portfolio | L46: Investor 7 Portfolio | M46: Infra Debt | N46: 61220000 | O46: 61220000 | P46: GBP | Q46: Loan | R46: N | S46: L100208 | T46: Infrastructure Debt | U46: IE | V46: Ireland | W46: Hydro | X46: CR1006 | Y46: 8.7 | Z46: EUR | AA46: 1 | AB46: N | AC46: 61840000 | AD46: 61840000 | AE46: 61840000 | AF46: 0.99 | AG46: 61220000 | AH46: 61220000 | AI46: 620000 | AJ46: 61840000 | AK46: 61220000 | AL46: 61220000 | AM46: EURIBOR 6M | AN46: 4.593 | AO46: 6.081 | AP46: 3.184 | AQ46: 100 | AR46: 100 | AS46: 42133 | AT46: 47431 | AU46: 46295 | AV46: PI2006 | AW46: Meridian Infrastructure | AX46: N | AY46: Granite Hydro Finance Ltd | AZ46: Granite Hydro Finance | BA46: Ireland | BB46: Meridian Infrastructure | BC46: 529900SYNTH000000006 | BI46: 61840000 | BJ46: 61840000 | BK46: Floating | BL46: Senior Secured | BN46: 8.7 | BO46: 3.36 | BP46: Y | BQ46: N | BR46: Debt | BS46: RA100208 | BT46: D. Schäfer | BU46: D. Schäfer | BW46: Quarterly | BX46: 30/360 | BY46: 220 | BZ46: 220 | CB46: EURIBOR | CC46: AA- | CD46: AA- | CE46: AA- | CF46: AA | CG46: NR | CH46: 46112 | CI46: 1.2 | CJ46: 1.4 | CK46: 1.47 | CL46: OK | DA46: 0.48 | DC46: 0.85 | DD46: OK | ED46: OK | EE46: 1.05 | EI46: 1.82 | FQ46: 90643678
B47: =C47&"x"&I47 -> 61005x100208 | C47: =IF(G47="SINGLE",H47,G47) -> 61005 | D47: =_xlfn.XLOOKUP(I47,calculations!$t:$t,calculations!$s:$s) -> #VALUE! | E47: =_xlfn.XLOOKUP(I47,Mapping!$T:$T,Mapping!$Q:$Q) -> GRAN07 | F47: 46203 | G47: 61005 | H47: 61005 | I47: 100208 | J47: Granite Hydro | K47: Investor 5 Portfolio | L47: Investor 5 Portfolio | M47: Infra Debt | N47: 45422000 | O47: 45422000 | P47: EUR | Q47: Loan | R47: N | S47: L100208 | T47: Infrastructure Debt | U47: IE | V47: Ireland | W47: Hydro | X47: CR1006 | Y47: 8.7 | Z47: EUR | AA47: 1 | AB47: N | AC47: 45882000 | AD47: 45882000 | AE47: 45882000 | AF47: 0.99 | AG47: 45422000 | AH47: 45422000 | AI47: 460000 | AJ47: 45882000 | AK47: 45422000 | AL47: 45422000 | AM47: EURIBOR 6M | AN47: 2.573 | AO47: 5.074 | AP47: 6.47 | AQ47: 100 | AR47: 100 | AS47: 42133 | AT47: 47431 | AU47: 46295 | AV47: PI2006 | AW47: Meridian Infrastructure | AX47: N | AY47: Granite Hydro Finance Ltd | AZ47: Granite Hydro Finance | BA47: Ireland | BB47: Meridian Infrastructure | BC47: 529900SYNTH000000006 | BI47: 45882000 | BJ47: 45882000 | BK47: Floating | BL47: Senior Secured | BN47: 8.7 | BO47: 3.36 | BP47: Y | BQ47: N | BR47: Debt | BS47: RA100208 | BT47: D. Schäfer | BU47: F. Lindqvist | BW47: Quarterly | BX47: ACT/360 | BY47: 220 | BZ47: 220 | CB47: EURIBOR | CC47: AA- | CD47: AA- | CE47: AA- | CF47: AA | CG47: NR | CH47: 46112 | CI47: 1.2 | CJ47: 2.26 | CK47: 2.37 | CL47: OK | DA47: 0.8 | DC47: 0.85 | DD47: Watch | ED47: Watch | EE47: 1.05 | EI47: 1.15 | FQ47: 72978372
B48: =C48&"x"&I48 -> 61025x100208 | C48: =IF(G48="SINGLE",H48,G48) -> 61025 | D48: =_xlfn.XLOOKUP(I48,calculations!$t:$t,calculations!$s:$s) -> #VALUE! | E48: =_xlfn.XLOOKUP(I48,Mapping!$T:$T,Mapping!$Q:$Q) -> GRAN07 | F48: 46203 | G48: 61025 | H48: 61025 | I48: 100208 | J48: Granite Hydro | K48: Fund 5 Fund | L48: Fund 5 Fund | M48: Infra Debt | N48: 27925000 | O48: 27925000 | P48: EUR | Q48: Loan | R48: N | S48: L100208 | T48: Infrastructure Debt | U48: IE | V48: Ireland | W48: Hydro | X48: CR1006 | Y48: 8.7 | Z48: EUR | AA48: 1 | AB48: N | AC48: 28208000 | AD48: 28208000 | AE48: 28208000 | AF48: 0.99 | AG48: 27925000 | AH48: 27925000 | AI48: 283000 | AJ48: 28208000 | AK48: 27925000 | AL48: 27925000 | AM48: EURIBOR 6M | AN48: 2.724 | AO48: 4.659 | AP48: 4.826 | AQ48: 100 | AR48: 100 | AS48: 42133 | AT48: 47431 | AU48: 46295 | AV48: PI2006 | AW48: Meridian Infrastructure | AX48: N | AY48: Granite Hydro Finance Ltd | AZ48: Granite Hydro Finance | BA48: Ireland | BB48: Meridian Infrastructure | BC48: 529900SYNTH000000006 | BI48: 28208000 | BJ48: 28208000 | BK48: Floating | BL48: Senior Secured | BN48: 8.7 | BO48: 3.36 | BP48: Y | BQ48: N | BR48: Debt | BS48: RA100208 | BT48: D. Schäfer | BU48: A. Martin | BW48: Semi-annual | BX48: ACT/360 | BY48: 220 | BZ48: 220 | CB48: EURIBOR | CC48: AA- | CD48: AA- | CE48: AA- | CF48: AA | CG48: NR | CH48: 46112 | CI48: 1.2 | CJ48: 2.53 | CK48: 2.66 | CL48: OK | DA48: 0.74 | DC48: 0.85 | DD48: OK | ED48: OK | EE48: 1.05 | EI48: 1.42 | FQ48: 71712307
B49: =C49&"x"&I49 -> 61022x100208 | C49: =IF(G49="SINGLE",H49,G49) -> 61022 | D49: =_xlfn.XLOOKUP(I49,calculations!$t:$t,calculations!$s:$s) -> #VALUE! | E49: =_xlfn.XLOOKUP(I49,Mapping!$T:$T,Mapping!$Q:$Q) -> GRAN07 | F49: 46203 | G49: 61022 | H49: 61022 | I49: 100208 | J49: Granite Hydro | K49: Fund 2 Fund | L49: Fund 2 Fund | M49: Infra Debt | N49: 33303000 | O49: 33303000 | P49: EUR | Q49: Loan | R49: N | S49: L100208 | T49: Infrastructure Debt | U49: IE | V49: Ireland | W49: Hydro | X49: CR1006 | Y49: 8.7 | Z49: EUR | AA49: 1 | AB49: N | AC49: 33640000 | AD49: 33640000 | AE49: 33640000 | AF49: 0.99 | AG49: 33303000 | AH49: 33303000 | AI49: 337000 | AJ49: 33640000 | AK49: 33303000 | AL49: 33303000 | AM49: EURIBOR 6M | AN49: 5.516 | AO49: 4.693 | AP49: 5.93 | AQ49: 100 | AR49: 100 | AS49: 42133 | AT49: 47431 | AU49: 46295 | AV49: PI2006 | AW49: Meridian Infrastructure | AX49: N | AY49: Granite Hydro Finance Ltd | AZ49: Granite Hydro Finance | BA49: Ireland | BB49: Meridian Infrastructure | BC49: 529900SYNTH000000006 | BI49: 33640000 | BJ49: 33640000 | BK49: Floating | BL49: Senior Secured | BN49: 8.7 | BO49: 3.36 | BP49: Y | BQ49: N | BR49: Debt | BS49: RA100208 | BT49: D. Schäfer | BU49: A. Martin | BW49: Quarterly | BX49: ACT/360 | BY49: 220 | BZ49: 220 | CB49: EURIBOR | CC49: AA- | CD49: AA- | CE49: AA- | CF49: AA | CG49: NR | CH49: 46112 | CI49: 1.2 | CJ49: 2.81 | CK49: 2.95 | CL49: OK | DA49: 0.47 | DC49: 0.85 | DD49: OK | ED49: OK | EE49: 1.05 | EI49: 1.42 | FQ49: 88445686
B50: =C50&"x"&I50 -> 61020x100209 | C50: =IF(G50="SINGLE",H50,G50) -> 61020 | D50: =_xlfn.XLOOKUP(I50,calculations!$t:$t,calculations!$s:$s) -> #VALUE! | E50: =_xlfn.XLOOKUP(I50,Mapping!$T:$T,Mapping!$Q:$Q) -> HARB08 | F50: 46203 | G50: 61020 | H50: 61020 | I50: 100209 | J50: Harbour Toll | K50: Investor 20 Mandate | L50: Investor 20 Mandate | M50: Infra Debt | N50: 28566000 | O50: 28566000 | P50: EUR | Q50: Loan | R50: Y | S50: L100209 | T50: Infrastructure Debt | U50: NL | V50: Netherlands | W50: Toll roads | X50: CR1007 | Y50: 11.5 | Z50: EUR | AA50: 1 | AB50: N | AC50: 29108000 | AD50: 29108000 | AE50: 29108000 | AF50: 0.9814 | AG50: 28566000 | AH50: 28566000 | AI50: 542000 | AJ50: 29108000 | AK50: 28566000 | AL50: 28566000 | AN50: 5.726 | AO50: 3.988 | AP50: 6.237 | AQ50: 100 | AR50: 100 | AS50: 45739 | AT50: 51948 | AU50: 46295 | AV50: PI2007 | AW50: Helios Partners | AX50: N | AY50: Harbour Toll Finance Ltd | AZ50: Harbour Toll Finance | BA50: Netherlands | BB50: Helios Partners | BC50: 529900SYNTH000000007 | BI50: 29108000 | BJ50: 29108000 | BK50: Fixed | BL50: Senior Secured | BN50: 10.2 | BO50: 15.73 | BP50: N | BQ50: Y | BR50: Debt | BS50: RA100209 | BT50: D. Schäfer | BU50: B. Okoro | BW50: Semi-annual | BX50: 30/360 | BY50: 305 | BZ50: 305 | CC50: BBB | CD50: BBB | CE50: NR | CF50: NR | CG50: NR | CH50: 46112 | CI50: 1.2 | CJ50: 1.62 | CK50: 1.7 | CL50: OK | DA50: 0.58 | DC50: 0.85 | DD50: OK | ED50: OK | EE50: 1.05 | EI50: 1.46 | FQ50: 36665988
B51: =C51&"x"&I51 -> 61017x100209 | C51: =IF(G51="SINGLE",H51,G51) -> 61017 | D51: =_xlfn.XLOOKUP(I51,calculations!$t:$t,calculations!$s:$s) -> #VALUE! | E51: =_xlfn.XLOOKUP(I51,Mapping!$T:$T,Mapping!$Q:$Q) -> HARB08 | F51: 46203 | G51: 61017 | H51: 61017 | I51: 100209 | J51: Harbour Toll | K51: Investor 17 Mandate | L51: Investor 17 Mandate | M51: Infra Debt | N51: 30236000 | O51: 30236000 | P51: EUR | Q51: Loan | R51: Y | S51: L100209 | T51: Infrastructure Debt | U51: NL | V51: Netherlands | W51: Toll roads | X51: CR1007 | Y51: 11.5 | Z51: EUR | AA51: 1 | AB51: N | AC51: 30810000 | AD51: 30810000 | AE51: 30810000 | AF51: 0.9814 | AG51: 30236000 | AH51: 30236000 | AI51: 574000 | AJ51: 30810000 | AK51: 30236000 | AL51: 30236000 | AN51: 3.119 | AO51: 4.088 | AP51: 5.873 | AQ51: 100 | AR51: 100 | AS51: 45739 | AT51: 51948 | AU51: 46295 | AV51: PI2007 | AW51: Helios Partners | AX51: N | AY51: Harbour Toll Finance Ltd | AZ51: Harbour Toll Finance | BA51: Netherlands | BB51: Helios Partners | BC51: 529900SYNTH000000007 | BI51: 30810000 | BJ51: 30810000 | BK51: Fixed | BL51: Senior Secured | BN51: 10.2 | BO51: 15.73 | BP51: N | BQ51: Y | BR51: Debt | BS51: RA100209 | BT51: D. Schäfer | BU51: B. Okoro | BW51: Quarterly | BX51: ACT/360 | BY51: 305 | BZ51: 305 | CC51: BBB | CD51: BBB | CE51: NR | CF51: NR | CG51: NR | CH51: 46112 | CI51: 1.2 | CJ51: 2.94 | CK51: 3.09 | CL51: OK | DA51: 0.72 | DC51: 0.85 | DD51: OK | ED51: OK | EE51: 1.05 | EI51: 1.38 | FQ51: 37799275
B52: =C52&"x"&I52 -> 61015x100209 | C52: =IF(G52="SINGLE",H52,G52) -> 61015 | D52: =_xlfn.XLOOKUP(I52,calculations!$t:$t,calculations!$s:$s) -> #VALUE! | E52: =_xlfn.XLOOKUP(I52,Mapping!$T:$T,Mapping!$Q:$Q) -> HARB08 | F52: 46203 | G52: 61015 | H52: 61015 | I52: 100209 | J52: Harbour Toll | K52: Investor 15 Mandate | L52: Investor 15 Mandate | M52: Infra Debt | N52: 17602000 | O52: 17602000 | P52: EUR | Q52: Loan | R52: Y | S52: L100209 | T52: Infrastructure Debt | U52: NL | V52: Netherlands | W52: Toll roads | X52: CR1007 | Y52: 11.5 | Z52: EUR | AA52: 1 | AB52: N | AC52: 17936000 | AD52: 17936000 | AE52: 17936000 | AF52: 0.9814 | AG52: 17602000 | AH52: 17602000 | AI52: 334000 | AJ52: 17936000 | AK52: 17602000 | AL52: 17602000 | AN52: 4.338 | AO52: 5.936 | AP52: 5.371 | AQ52: 100 | AR52: 100 | AS52: 45739 | AT52: 51948 | AU52: 46295 | AV52: PI2007 | AW52: Helios Partners | AX52: N | AY52: Harbour Toll Finance Ltd | AZ52: Harbour Toll Finance | BA52: Netherlands | BB52: Helios Partners | BC52: 529900SYNTH000000007 | BI52: 17936000 | BJ52: 17936000 | BK52: Fixed | BL52: Senior Secured | BN52: 10.2 | BO52: 15.73 | BP52: N | BQ52: Y | BR52: Debt | BS52: RA100209 | BT52: D. Schäfer | BU52: B. Okoro | BW52: Quarterly | BX52: ACT/360 | BY52: 305 | BZ52: 305 | CC52: BBB | CD52: BBB | CE52: NR | CF52: NR | CG52: NR | CH52: 46112 | CI52: 1.2 | CJ52: 3.25 | CK52: 3.41 | CL52: OK | DA52: 0.67 | DC52: 0.85 | DD52: OK | ED52: OK | EE52: 1.05 | EI52: 1.89 | FQ52: 36275326
B53: =C53&"x"&I53 -> 61012x100209 | C53: =IF(G53="SINGLE",H53,G53) -> 61012 | D53: =_xlfn.XLOOKUP(I53,calculations!$t:$t,calculations!$s:$s) -> #VALUE! | E53: =_xlfn.XLOOKUP(I53,Mapping!$T:$T,Mapping!$Q:$Q) -> HARB08 | F53: 46203 | G53: 61012 | H53: 61012 | I53: 100209 | J53: Harbour Toll | K53: Investor 12 Mandate | L53: Investor 12 Mandate | M53: Infra Debt | N53: 20372000 | O53: 20372000 | P53: GBP | Q53: Loan | R53: Y | S53: L100209 | T53: Infrastructure Debt | U53: NL | V53: Netherlands | W53: Toll roads | X53: CR1007 | Y53: 11.5 | Z53: EUR | AA53: 1 | AB53: N | AC53: 20759000 | AD53: 20759000 | AE53: 20759000 | AF53: 0.9814 | AG53: 20372000 | AH53: 20372000 | AI53: 387000 | AJ53: 20759000 | AK53: 20372000 | AL53: 20372000 | AN53: 5.736 | AO53: 5.814 | AP53: 5.126 | AQ53: 100 | AR53: 100 | AS53: 45739 | AT53: 51948 | AU53: 46295 | AV53: PI2007 | AW53: Helios Partners | AX53: N | AY53: Harbour Toll Finance Ltd | AZ53: Harbour Toll Finance | BA53: Netherlands | BB53: Helios Partners | BC53: 529900SYNTH000000007 | BI53: 20759000 | BJ53: 20759000 | BK53: Fixed | BL53: Senior Secured | BN53: 10.2 | BO53: 15.73 | BP53: N | BQ53: Y | BR53: Debt | BS53: RA100209 | BT53: D. Schäfer | BU53: D. Schäfer | BW53: Semi-annual | BX53: 30/360 | BY53: 305 | BZ53: 305 | CC53: BBB | CD53: BBB | CE53: NR | CF53: NR | CG53: NR | CH53: 46112 | CI53: 1.2 | CJ53: 2.87 | CK53: 3.01 | CL53: OK | DA53: 0.5 | DC53: 0.85 | DD53: OK | ED53: OK | EE53: 1.05 | EI53: 1.37 | FQ53: 43760510
B54: =C54&"x"&I54 -> 61002x100209 | C54: =IF(G54="SINGLE",H54,G54) -> 61002 | D54: =_xlfn.XLOOKUP(I54,calculations!$t:$t,calculations!$s:$s) -> #VALUE! | E54: =_xlfn.XLOOKUP(I54,Mapping!$T:$T,Mapping!$Q:$Q) -> HARB08 | F54: 46203 | G54: 61002 | H54: 61002 | I54: 100209 | J54: Harbour Toll | K54: Investor 2 Portfolio | L54: Investor 2 Portfolio | M54: Infra Debt | N54: 29139000 | O54: 29139000 | P54: EUR | Q54: Loan | R54: Y | S54: L100209 | T54: Infrastructure Debt | U54: NL | V54: Netherlands | W54: Toll roads | X54: CR1007 | Y54: 11.5 | Z54: EUR | AA54: 1 | AB54: N | AC54: 29692000 | AD54: 29692000 | AE54: 29692000 | AF54: 0.9814 | AG54: 29139000 | AH54: 29139000 | AI54: 553000 | AJ54: 29692000 | AK54: 29139000 | AL54: 29139000 | AN54: 4.927 | AO54: 4.887 | AP54: 5.803 | AQ54: 100 | AR54: 100 | AS54: 45739 | AT54: 51948 | AU54: 46295 | AV54: PI2007 | AW54: Helios Partners | AX54: N | AY54: Harbour Toll Finance Ltd | AZ54: Harbour Toll Finance | BA54: Netherlands | BB54: Helios Partners | BC54: 529900SYNTH000000007 | BI54: 29692000 | BJ54: 29692000 | BK54: Fixed | BL54: Senior Secured | BN54: 10.2 | BO54: 15.73 | BP54: N | BQ54: Y | BR54: Debt | BS54: RA100209 | BT54: D. Schäfer | BU54: C. Dubois | BW54: Quarterly | BX54: ACT/360 | BY54: 305 | BZ54: 305 | CC54: BBB | CD54: BBB | CE54: NR | CF54: NR | CG54: NR | CH54: 46112 | CI54: 1.2 | CJ54: 2.76 | CK54: 2.9 | CL54: OK | DA54: 0.46 | DC54: 0.85 | DD54: OK | ED54: Watch | EE54: 1.05 | EI54: 1.16 | FQ54: 26735204
B55: =C55&"x"&I55 -> 61005x100210 | C55: =IF(G55="SINGLE",H55,G55) -> 61005 | D55: =_xlfn.XLOOKUP(I55,calculations!$t:$t,calculations!$s:$s) -> #VALUE! | E55: =_xlfn.XLOOKUP(I55,Mapping!$T:$T,Mapping!$Q:$Q) -> IRIS09 | F55: 46203 | G55: 61005 | H55: 61005 | I55: 100210 | J55: Iris Fibre | K55: Investor 5 Portfolio | L55: Investor 5 Portfolio | M55: Infra Debt | N55: 24364000 | O55: 28495906 | P55: EUR | Q55: Loan | R55: N | S55: L100210 | T55: Infrastructure Debt | U55: GB | V55: United Kingdom | W55: Fibre networks | X55: CR1008 | Y55: 13.2 | Z55: GBP | AA55: 0.855 | AB55: Y | AC55: 24896000 | AD55: 24896000 | AE55: 29118129 | AF55: 0.9786 | AG55: 24364000 | AH55: 24364000 | AI55: 532000 | AJ55: 24896000 | AK55: 24364000 | AL55: 24364000 | AN55: 4.614 | AO55: 4.45 | AP55: 4.703 | AQ55: 100 | AR55: 100 | AS55: 42538 | AT55: 52034 | AU55: 46295 | AV55: PI2008 | AW55: Northwind Capital | AX55: N | AY55: Iris Fibre Finance Ltd | AZ55: Iris Fibre Finance | BA55: United Kingdom | BB55: Northwind Capital | BC55: 529900SYNTH000000008 | BI55: 24896000 | BJ55: 29118129 | BK55: Fixed | BL55: Senior Secured | BN55: 15.6 | BO55: 15.96 | BP55: N | BQ55: N | BR55: Debt | BS55: RA100210 | BT55: D. Schäfer | BU55: F. Lindqvist | BW55: Quarterly | BX55: ACT/360 | BY55: 245 | BZ55: 245 | CC55: BBB+ | CD55: BBB+ | CE55: NR | CF55: NR | CG55: NR | CH55: 46112 | CI55: 1.2 | CJ55: 2.38 | CK55: 2.5 | CL55: OK | DA55: 0.58 | DC55: 0.85 | DD55: OK | ED55: OK | EE55: 1.05 | EI55: 1.87 | FQ55: 105085150
B56: =C56&"x"&I56 -> 61003x100210 | C56: =IF(G56="SINGLE",H56,G56) -> 61003 | D56: =_xlfn.XLOOKUP(I56,calculations!$t:$t,calculations!$s:$s) -> #VALUE! | E56: =_xlfn.XLOOKUP(I56,Mapping!$T:$T,Mapping!$Q:$Q) -> IRIS09 | F56: 46203 | G56: 61003 | H56: 61003 | I56: 100210 | J56: Iris Fibre | K56: Investor 3 Portfolio | L56: Investor 3 Portfolio | M56: Infra Debt | N56: 33454000 | O56: 39127485 | P56: EUR | Q56: Loan | R56: N | S56: L100210 | T56: Infrastructure Debt | U56: GB | V56: United Kingdom | W56: Fibre networks | X56: CR1008 | Y56: 13.2 | Z56: GBP | AA56: 0.855 | AB56: Y | AC56: 34184000 | AD56: 34184000 | AE56: 39981287 | AF56: 0.9786 | AG56: 33454000 | AH56: 33454000 | AI56: 730000 | AJ56: 34184000 | AK56: 33454000 | AL56: 33454000 | AN56: 3.441 | AO56: 5.064 | AP56: 4.327 | AQ56: 100 | AR56: 100 | AS56: 42538 | AT56: 52034 | AU56: 46295 | AV56: PI2008 | AW56: Northwind Capital | AX56: N | AY56: Iris Fibre Finance Ltd | AZ56: Iris Fibre Finance | BA56: United Kingdom | BB56: Northwind Capital | BC56: 529900SYNTH000000008 | BI56: 34184000 | BJ56: 39981287 | BK56: Fixed | BL56: Senior Secured | BN56: 15.6 | BO56: 15.96 | BP56: N | BQ56: N | BR56: Debt | BS56: RA100210 | BT56: D. Schäfer | BU56: A. Martin | BW56: Quarterly | BX56: ACT/360 | BY56: 245 | BZ56: 245 | CC56: BBB+ | CD56: BBB+ | CE56: NR | CF56: NR | CG56: NR | CH56: 46112 | CI56: 1.2 | CJ56: 1.98 | CK56: 2.08 | CL56: OK | DA56: 0.83 | DC56: 0.85 | DD56: Watch | ED56: OK | EE56: 1.05 | EI56: 1.36 | FQ56: 86883881
B57: =C57&"x"&I57 -> 61020x100210 | C57: =IF(G57="SINGLE",H57,G57) -> 61020 | D57: =_xlfn.XLOOKUP(I57,calculations!$t:$t,calculations!$s:$s) -> #VALUE! | E57: =_xlfn.XLOOKUP(I57,Mapping!$T:$T,Mapping!$Q:$Q) -> IRIS09 | F57: 46203 | G57: 61020 | H57: 61020 | I57: 100210 | J57: Iris Fibre | K57: Investor 20 Mandate | L57: Investor 20 Mandate | M57: Infra Debt | N57: 34134000 | O57: 39922807 | P57: EUR | Q57: Loan | R57: N | S57: L100210 | T57: Infrastructure Debt | U57: GB | V57: United Kingdom | W57: Fibre networks | X57: CR1008 | Y57: 13.2 | Z57: GBP | AA57: 0.855 | AB57: Y | AC57: 34879000 | AD57: 34879000 | AE57: 40794152 | AF57: 0.9786 | AG57: 34134000 | AH57: 34134000 | AI57: 745000 | AJ57: 34879000 | AK57: 34134000 | AL57: 34134000 | AN57: 3.604 | AO57: 3.589 | AP57: 3.443 | AQ57: 100 | AR57: 100 | AS57: 42538 | AT57: 52034 | AU57: 46295 | AV57: PI2008 | AW57: Northwind Capital | AX57: N | AY57: Iris Fibre Finance Ltd | AZ57: Iris Fibre Finance | BA57: United Kingdom | BB57: Northwind Capital | BC57: 529900SYNTH000000008 | BI57: 34879000 | BJ57: 40794152 | BK57: Fixed | BL57: Senior Secured | BN57: 15.6 | BO57: 15.96 | BP57: N | BQ57: N | BR57: Debt | BS57: RA100210 | BT57: D. Schäfer | BU57: E. Rossi | BW57: Quarterly | BX57: 30/360 | BY57: 245 | BZ57: 245 | CC57: BBB+ | CD57: BBB+ | CE57: NR | CF57: NR | CG57: NR | CH57: 46112 | CI57: 1.2 | CJ57: 1.56 | CK57: 1.64 | CL57: OK | DA57: 0.8 | DC57: 0.85 | DD57: Watch | ED57: OK | EE57: 1.05 | EI57: 1.22 | FQ57: 64257699
B58: =C58&"x"&I58 -> 61017x100210 | C58: =IF(G58="SINGLE",H58,G58) -> 61017 | D58: =_xlfn.XLOOKUP(I58,calculations!$t:$t,calculations!$s:$s) -> #VALUE! | E58: =_xlfn.XLOOKUP(I58,Mapping!$T:$T,Mapping!$Q:$Q) -> IRIS09 | F58: 46203 | G58: 61017 | H58: 61017 | I58: 100210 | J58: Iris Fibre | K58: Investor 17 Mandate | L58: Investor 17 Mandate | M58: Infra Debt | N58: 17823000 | O58: 20845614 | P58: EUR | Q58: Loan | R58: N | S58: L100210 | T58: Infrastructure Debt | U58: GB | V58: United Kingdom | W58: Fibre networks | X58: CR1008 | Y58: 13.2 | Z58: GBP | AA58: 0.855 | AB58: Y | AC58: 18212000 | AD58: 18212000 | AE58: 21300585 | AF58: 0.9786 | AG58: 17823000 | AH58: 17823000 | AI58: 389000 | AJ58: 18212000 | AK58: 17823000 | AL58: 17823000 | AN58: 2.786 | AO58: 4.67 | AP58: 6.224 | AQ58: 100 | AR58: 100 | AS58: 42538 | AT58: 52034 | AU58: 46295 | AV58: PI2008 | AW58: Northwind Capital | AX58: N | AY58: Iris Fibre Finance Ltd | AZ58: Iris Fibre Finance | BA58: United Kingdom | BB58: Northwind Capital | BC58: 529900SYNTH000000008 | BI58: 18212000 | BJ58: 21300585 | BK58: Fixed | BL58: Senior Secured | BN58: 15.6 | BO58: 15.96 | BP58: N | BQ58: N | BR58: Debt | BS58: RA100210 | BT58: D. Schäfer | BU58: A. Martin | BW58: Quarterly | BX58: 30/360 | BY58: 245 | BZ58: 245 | CC58: BBB+ | CD58: BBB+ | CE58: NR | CF58: NR | CG58: NR | CH58: 46112 | CI58: 1.2 | CJ58: 2.83 | CK58: 2.97 | CL58: OK | DA58: 0.55 | DC58: 0.85 | DD58: OK | ED58: OK | EE58: 1.05 | EI58: 1.57 | FQ58: 99749326
B59: =C59&"x"&I59 -> 61016x100210 | C59: =IF(G59="SINGLE",H59,G59) -> 61016 | D59: =_xlfn.XLOOKUP(I59,calculations!$t:$t,calculations!$s:$s) -> #VALUE! | E59: =_xlfn.XLOOKUP(I59,Mapping!$T:$T,Mapping!$Q:$Q) -> IRIS09 | F59: 46203 | G59: 61016 | H59: 61016 | I59: 100210 | J59: Iris Fibre | K59: Investor 16 Mandate | L59: Investor 16 Mandate | M59: Infra Debt | N59: 36766000 | O59: 43001170 | P59: EUR | Q59: Loan | R59: N | S59: L100210 | T59: Infrastructure Debt | U59: GB | V59: United Kingdom | W59: Fibre networks | X59: CR1008 | Y59: 13.2 | Z59: GBP | AA59: 0.855 | AB59: Y | AC59: 37569000 | AD59: 37569000 | AE59: 43940351 | AF59: 0.9786 | AG59: 36766000 | AH59: 36766000 | AI59: 803000 | AJ59: 37569000 | AK59: 36766000 | AL59: 36766000 | AN59: 3.169 | AO59: 4.579 | AP59: 3.894 | AQ59: 100 | AR59: 100 | AS59: 42538 | AT59: 52034 | AU59: 46295 | AV59: PI2008 | AW59: Northwind Capital | AX59: N | AY59: Iris Fibre Finance Ltd | AZ59: Iris Fibre Finance | BA59: United Kingdom | BB59: Northwind Capital | BC59: 529900SYNTH000000008 | BI59: 37569000 | BJ59: 43940351 | BK59: Fixed | BL59: Senior Secured | BN59: 15.6 | BO59: 15.96 | BP59: N | BQ59: N | BR59: Debt | BS59: RA100210 | BT59: D. Schäfer | BU59: C. Dubois | BW59: Semi-annual | BX59: ACT/360 | BY59: 245 | BZ59: 245 | CC59: BBB+ | CD59: BBB+ | CE59: NR | CF59: NR | CG59: NR | CH59: 46112 | CI59: 1.2 | CJ59: 1.97 | CK59: 2.07 | CL59: OK | DA59: 0.5 | DC59: 0.85 | DD59: OK | ED59: OK | EE59: 1.05 | EI59: 1.38 | FQ59: 72086551
B60: =C60&"x"&I60 -> 61024x100210 | C60: =IF(G60="SINGLE",H60,G60) -> 61024 | D60: =_xlfn.XLOOKUP(I60,calculations!$t:$t,calculations!$s:$s) -> #VALUE! | E60: =_xlfn.XLOOKUP(I60,Mapping!$T:$T,Mapping!$Q:$Q) -> IRIS09 | F60: 46203 | G60: 61024 | H60: 61024 | I60: 100210 | J60: Iris Fibre | K60: Fund 4 Fund | L60: Fund 4 Fund | M60: Infra Debt | N60: 29874000 | O60: 34940351 | P60: EUR | Q60: Loan | R60: N | S60: L100210 | T60: Infrastructure Debt | U60: GB | V60: United Kingdom | W60: Fibre networks | X60: CR1008 | Y60: 13.2 | Z60: GBP | AA60: 0.855 | AB60: Y | AC60: 30526000 | AD60: 30526000 | AE60: 35702924 | AF60: 0.9786 | AG60: 29874000 | AH60: 29874000 | AI60: 652000 | AJ60: 30526000 | AK60: 29874000 | AL60: 29874000 | AN60: 6.437 | AO60: 2.854 | AP60: 5.143 | AQ60: 100 | AR60: 100 | AS60: 42538 | AT60: 52034 | AU60: 46295 | AV60: PI2008 | AW60: Northwind Capital | AX60: N | AY60: Iris Fibre Finance Ltd | AZ60: Iris Fibre Finance | BA60: United Kingdom | BB60: Northwind Capital | BC60: 529900SYNTH000000008 | BI60: 30526000 | BJ60: 35702924 | BK60: Fixed | BL60: Senior Secured | BN60: 15.6 | BO60: 15.96 | BP60: N | BQ60: N | BR60: Debt | BS60: RA100210 | BT60: D. Schäfer | BU60: E. Rossi | BW60: Quarterly | BX60: 30/360 | BY60: 245 | BZ60: 245 | CC60: BBB+ | CD60: BBB+ | CE60: NR | CF60: NR | CG60: NR | CH60: 46112 | CI60: 1.2 | CJ60: 1.31 | CK60: 1.38 | CL60: OK | DA60: 0.85 | DC60: 0.85 | DD60: Watch | ED60: OK | EE60: 1.05 | EI60: 1.45 | FQ60: 65740930
B61: =C61&"x"&I61 -> 61001x100211 | C61: =IF(G61="SINGLE",H61,G61) -> 61001 | D61: =_xlfn.XLOOKUP(I61,calculations!$t:$t,calculations!$s:$s) -> #VALUE! | E61: =_xlfn.XLOOKUP(I61,Mapping!$T:$T,Mapping!$Q:$Q) -> JUNI10 | F61: 46203 | G61: 61001 | H61: 61001 | I61: 100211 | J61: Juniper Gas | K61: Investor 1 Portfolio | L61: Investor 1 Portfolio | M61: Infra Debt | N61: 10158000 | O61: 10158000 | P61: EUR | Q61: Private Placement Note | R61: N | S61: L100211 | T61: Infrastructure Debt | U61: NL | V61: Netherlands | W61: Gas distribution | X61: CR1009 | Y61: 6 | Z61: EUR | AA61: 1 | AB61: N | AC61: 11265000 | AD61: 11265000 | AE61: 11265000 | AF61: 0.9017 | AG61: 10158000 | AH61: 10158000 | AI61: 1107000 | AJ61: 11265000 | AK61: 10158000 | AL61: 10158000 | AM61: EURIBOR 6M | AN61: 4.028 | AO61: 3.473 | AP61: 5.092 | AQ61: 100 | AR61: 100 | AS61: 43794 | AT61: 46898 | AU61: 46295 | AV61: PI2009 | AW61: Silverline Transport | AX61: N | AY61: Juniper Gas Finance Ltd | AZ61: Juniper Gas Finance | BA61: Netherlands | BB61: Silverline Transport | BC61: 529900SYNTH000000009 | BI61: 11265000 | BJ61: 11265000 | BK61: Floating | BL61: Senior Secured | BN61: 5.1 | BO61: 1.9 | BP61: Y | BQ61: N | BR61: Debt | BS61: RA100211 | BT61: F. Lindqvist | BU61: C. Dubois | BW61: Quarterly | BX61: ACT/360 | BY61: 45 | BZ61: 45 | CB61: EURIBOR | CC61: AA- | CD61: AA- | CE61: NR | CF61: NR | CG61: NR | CH61: 46112 | CI61: 1.2 | CJ61: 1.64 | CK61: 1.72 | CL61: OK | DA61: 0.56 | DC61: 0.85 | DD61: OK | ED61: OK | EE61: 1.05 | EI61: 1.37 | FQ61: 25665115
B62: =C62&"x"&I62 -> 61009x100211 | C62: =IF(G62="SINGLE",H62,G62) -> 61009 | D62: =_xlfn.XLOOKUP(I62,calculations!$t:$t,calculations!$s:$s) -> #VALUE! | E62: =_xlfn.XLOOKUP(I62,Mapping!$T:$T,Mapping!$Q:$Q) -> JUNI10 | F62: 46203 | G62: 61009 | H62: 61009 | I62: 100211 | J62: Juniper Gas | K62: Investor 9 Portfolio | L62: Investor 9 Portfolio | M62: Infra Debt | N62: 26826000 | O62: 26826000 | P62: USD | Q62: Private Placement Note | R62: N | S62: L100211 | T62: Infrastructure Debt | U62: NL | V62: Netherlands | W62: Gas distribution | X62: CR1009 | Y62: 6 | Z62: EUR | AA62: 1 | AB62: N | AC62: 29750000 | AD62: 29750000 | AE62: 29750000 | AF62: 0.9017 | AG62: 26826000 | AH62: 26826000 | AI62: 2924000 | AJ62: 29750000 | AK62: 26826000 | AL62: 26826000 | AM62: EURIBOR 6M | AN62: 3.946 | AO62: 5.227 | AP62: 5.619 | AQ62: 100 | AR62: 100 | AS62: 43794 | AT62: 46898 | AU62: 46295 | AV62: PI2009 | AW62: Silverline Transport | AX62: N | AY62: Juniper Gas Finance Ltd | AZ62: Juniper Gas Finance | BA62: Netherlands | BB62: Silverline Transport | BC62: 529900SYNTH000000009 | BI62: 29750000 | BJ62: 29750000 | BK62: Floating | BL62: Senior Secured | BN62: 5.1 | BO62: 1.9 | BP62: Y | BQ62: N | BR62: Debt | BS62: RA100211 | BT62: F. Lindqvist | BU62: F. Lindqvist | BW62: Semi-annual | BX62: ACT/360 | BY62: 45 | BZ62: 45 | CB62: EURIBOR | CC62: AA- | CD62: AA- | CE62: NR | CF62: NR | CG62: NR | CH62: 46112 | CI62: 1.2 | CJ62: 3.05 | CK62: 3.2 | CL62: OK | DA62: 0.71 | DC62: 0.85 | DD62: OK | ED62: Watch | EE62: 1.05 | EI62: 1.16 | FQ62: 19745445
B63: =C63&"x"&I63 -> 61002x100211 | C63: =IF(G63="SINGLE",H63,G63) -> 61002 | D63: =_xlfn.XLOOKUP(I63,calculations!$t:$t,calculations!$s:$s) -> #VALUE! | E63: =_xlfn.XLOOKUP(I63,Mapping!$T:$T,Mapping!$Q:$Q) -> JUNI10 | F63: 46203 | G63: 61002 | H63: 61002 | I63: 100211 | J63: Juniper Gas | K63: Investor 2 Portfolio | L63: Investor 2 Portfolio | M63: Infra Debt | N63: 20502000 | O63: 20502000 | P63: EUR | Q63: Private Placement Note | R63: N | S63: L100211 | T63: Infrastructure Debt | U63: NL | V63: Netherlands | W63: Gas distribution | X63: CR1009 | Y63: 6 | Z63: EUR | AA63: 1 | AB63: N | AC63: 22736000 | AD63: 22736000 | AE63: 22736000 | AF63: 0.9017 | AG63: 20502000 | AH63: 20502000 | AI63: 2234000 | AJ63: 22736000 | AK63: 20502000 | AL63: 20502000 | AM63: EURIBOR 6M | AN63: 5.657 | AO63: 4.52 | AP63: 4.538 | AQ63: 100 | AR63: 100 | AS63: 43794 | AT63: 46898 | AU63: 46295 | AV63: PI2009 | AW63: Silverline Transport | AX63: N | AY63: Juniper Gas Finance Ltd | AZ63: Juniper Gas Finance | BA63: Netherlands | BB63: Silverline Transport | BC63: 529900SYNTH000000009 | BI63: 22736000 | BJ63: 22736000 | BK63: Floating | BL63: Senior Secured | BN63: 5.1 | BO63: 1.9 | BP63: Y | BQ63: N | BR63: Debt | BS63: RA100211 | BT63: F. Lindqvist | BU63: B. Okoro | BW63: Semi-annual | BX63: 30/360 | BY63: 45 | BZ63: 45 | CB63: EURIBOR | CC63: AA- | CD63: AA- | CE63: NR | CF63: NR | CG63: NR | CH63: 46112 | CI63: 1.2 | CJ63: 1.87 | CK63: 1.96 | CL63: OK | DA63: 0.76 | DC63: 0.85 | DD63: OK | ED63: OK | EE63: 1.05 | EI63: 1.53 | FQ63: 23537270
B64: =C64&"x"&I64 -> 61020x100211 | C64: =IF(G64="SINGLE",H64,G64) -> 61020 | D64: =_xlfn.XLOOKUP(I64,calculations!$t:$t,calculations!$s:$s) -> #VALUE! | E64: =_xlfn.XLOOKUP(I64,Mapping!$T:$T,Mapping!$Q:$Q) -> JUNI10 | F64: 46203 | G64: 61020 | H64: 61020 | I64: 100211 | J64: Juniper Gas | K64: Investor 20 Mandate | L64: Investor 20 Mandate | M64: Infra Debt | N64: 10158000 | O64: 10158000 | P64: EUR | Q64: Private Placement Note | R64: N | S64: L100211 | T64: Infrastructure Debt | U64: NL | V64: Netherlands | W64: Gas distribution | X64: CR1009 | Y64: 6 | Z64: EUR | AA64: 1 | AB64: N | AC64: 11265000 | AD64: 11265000 | AE64: 11265000 | AF64: 0.9017 | AG64: 10158000 | AH64: 10158000 | AI64: 1107000 | AJ64: 11265000 | AK64: 10158000 | AL64: 10158000 | AM64: EURIBOR 6M | AN64: 5.802 | AO64: 4.64 | AP64: 5.647 | AQ64: 100 | AR64: 100 | AS64: 43794 | AT64: 46898 | AU64: 46295 | AV64: PI2009 | AW64: Silverline Transport | AX64: N | AY64: Juniper Gas Finance Ltd | AZ64: Juniper Gas Finance | BA64: Netherlands | BB64: Silverline Transport | BC64: 529900SYNTH000000009 | BI64: 11265000 | BJ64: 11265000 | BK64: Floating | BL64: Senior Secured | BN64: 5.1 | BO64: 1.9 | BP64: Y | BQ64: N | BR64: Debt | BS64: RA100211 | BT64: F. Lindqvist | BU64: E. Rossi | BW64: Semi-annual | BX64: 30/360 | BY64: 45 | BZ64: 45 | CB64: EURIBOR | CC64: BB | CD64: AA- | CE64: NR | CF64: NR | CG64: NR | CH64: 46112 | CI64: 1.2 | CJ64: 1.45 | CK64: 1.52 | CL64: OK | DA64: 0.67 | DC64: 0.85 | DD64: OK | ED64: OK | EE64: 1.05 | EI64: 1.84 | FQ64: 23382389
B65: =C65&"x"&I65 -> 61023x100211 | C65: =IF(G65="SINGLE",H65,G65) -> 61023 | D65: =_xlfn.XLOOKUP(I65,calculations!$t:$t,calculations!$s:$s) -> #VALUE! | E65: =_xlfn.XLOOKUP(I65,Mapping!$T:$T,Mapping!$Q:$Q) -> JUNI10 | F65: 46203 | G65: 61023 | H65: 61023 | I65: 100211 | J65: Juniper Gas | K65: Fund 3 Fund | L65: Fund 3 Fund | M65: Infra Debt | N65: 12034000 | O65: 12034000 | P65: EUR | Q65: Private Placement Note | R65: N | S65: L100211 | T65: Infrastructure Debt | U65: NL | V65: Netherlands | W65: Gas distribution | X65: CR1009 | Y65: 6 | Z65: EUR | AA65: 1 | AB65: N | AC65: 13345000 | AD65: 13345000 | AE65: 13345000 | AF65: 0.9018 | AG65: 12034000 | AH65: 12034000 | AI65: 1311000 | AJ65: 13345000 | AK65: 12034000 | AL65: 12034000 | AM65: EURIBOR 6M | AN65: 3.998 | AO65: 4.241 | AP65: 3.211 | AQ65: 100 | AR65: 100 | AS65: 43794 | AT65: 46898 | AU65: 46295 | AV65: PI2009 | AW65: Silverline Transport | AX65: N | AY65: Juniper Gas Finance Ltd | AZ65: Juniper Gas Finance | BA65: Netherlands | BB65: Silverline Transport | BC65: 529900SYNTH000000009 | BI65: 13345000 | BJ65: 13345000 | BK65: Floating | BL65: Senior Secured | BN65: 5.1 | BO65: 1.9 | BP65: Y | BQ65: N | BR65: Debt | BS65: RA100211 | BT65: F. Lindqvist | BU65: A. Martin | BW65: Semi-annual | BX65: 30/360 | BY65: 45 | BZ65: 45 | CB65: EURIBOR | CC65: AA- | CD65: AA- | CE65: NR | CF65: NR | CG65: NR | CH65: 46112 | CI65: 1.2 | CJ65: 3.04 | CK65: 3.19 | CL65: OK | DA65: 0.73 | DC65: 0.85 | DD65: OK | ED65: OK | EE65: 1.05 | EI65: 1.8 | FQ65: 24277260
B66: =C66&"x"&I66 -> 61024x100211 | C66: =IF(G66="SINGLE",H66,G66) -> 61024 | D66: =_xlfn.XLOOKUP(I66,calculations!$t:$t,calculations!$s:$s) -> #VALUE! | E66: =_xlfn.XLOOKUP(I66,Mapping!$T:$T,Mapping!$Q:$Q) -> JUNI10 | F66: 46203 | G66: 61024 | H66: 61024 | I66: 100211 | J66: Juniper Gas | K66: Fund 4 Fund | L66: Fund 4 Fund | M66: Infra Debt | N66: 13465000 | O66: 13465000 | P66: EUR | Q66: Private Placement Note | R66: N | S66: L100211 | T66: Infrastructure Debt | U66: NL | V66: Netherlands | W66: Gas distribution | X66: CR1009 | Y66: 6 | Z66: EUR | AA66: 1 | AB66: N | AC66: 14933000 | AD66: 14933000 | AE66: 14933000 | AF66: 0.9017 | AG66: 13465000 | AH66: 13465000 | AI66: 1468000 | AJ66: 14933000 | AK66: 13465000 | AL66: 13465000 | AM66: EURIBOR 6M | AN66: 6.392 | AO66: 3.849 | AP66: 3.177 | AQ66: 100 | AR66: 100 | AS66: 43794 | AT66: 46898 | AU66: 46295 | AV66: PI2009 | AW66: Silverline Transport | AX66: N | AY66: Juniper Gas Finance Ltd | AZ66: Juniper Gas Finance | BA66: Netherlands | BB66: Silverline Transport | BC66: 529900SYNTH000000009 | BI66: 14933000 | BJ66: 14933000 | BK66: Floating | BL66: Senior Secured | BN66: 5.1 | BO66: 1.9 | BP66: Y | BQ66: N | BR66: Debt | BS66: RA100211 | BT66: F. Lindqvist | BU66: A. Martin | BW66: Quarterly | BX66: ACT/360 | BY66: 45 | BZ66: 45 | CB66: EURIBOR | CC66: AA- | CD66: AA- | CE66: NR | CF66: NR | CG66: NR | CH66: 46112 | CI66: 1.2 | CJ66: 2.47 | CK66: 2.59 | CL66: OK | DA66: 0.55 | DC66: 0.85 | DD66: OK | ED66: OK | EE66: 1.05 | EI66: 1.36 | FQ66: 31382055
B67: =C67&"x"&I67 -> 61021x100212 | C67: =IF(G67="SINGLE",H67,G67) -> 61021 | D67: =_xlfn.XLOOKUP(I67,calculations!$t:$t,calculations!$s:$s) -> #VALUE! | E67: =_xlfn.XLOOKUP(I67,Mapping!$T:$T,Mapping!$Q:$Q) -> KEST11 | F67: 46203 | G67: 61021 | H67: 61021 | I67: 100212 | J67: Kestrel Battery | K67: Fund 1 Fund | L67: Fund 1 Fund | M67: Infra Debt | N67: 13268000 | O67: 13268000 | P67: EUR | Q67: Private Placement Note | R67: N | S67: L100212 | T67: Infrastructure Debt | U67: ES | V67: Spain | W67: Battery storage | X67: CR1010 | Y67: 17.4 | Z67: EUR | AA67: 1 | AB67: N | AC67: 13517000 | AD67: 13517000 | AE67: 13517000 | AF67: 0.9816 | AG67: 13268000 | AH67: 13268000 | AI67: 249000 | AJ67: 13517000 | AK67: 13268000 | AL67: 13268000 | AM67: EURIBOR 6M | AN67: 6.047 | AO67: 3.473 | AP67: 5.806 | AQ67: 100 | AR67: 100 | AS67: 44300 | AT67: 54162 | AU67: 46295 | AV67: PI2010 | AW67: Meridian Infrastructure | AX67: N | AY67: Kestrel Battery Finance Ltd | AZ67: Kestrel Battery Finance | BA67: Spain | BB67: Meridian Infrastructure | BC67: 529900SYNTH000000010 | BI67: 13517000 | BJ67: 13517000 | BK67: Floating | BL67: Senior Secured | BN67: 16.2 | BO67: 21.79 | BP67: Y | BQ67: N | BR67: Debt | BS67: RA100212 | BT67: E. Rossi | BU67: B. Okoro | BW67: Quarterly | BX67: 30/360 | BY67: 210 | BZ67: 210 | CB67: EURIBOR | CC67: BBB | CD67: BBB | CE67: BBB+ | CF67: NR | CG67: NR | CH67: 46112 | CI67: 1.2 | CJ67: 2.75 | CK67: 2.89 | CL67: OK | DA67: 0.76 | DC67: 0.85 | DD67: OK | ED67: OK | EE67: 1.05 | EI67: 1.6 | FQ67: 13641179
B68: =C68&"x"&I68 -> 61002x100212 | C68: =IF(G68="SINGLE",H68,G68) -> 61002 | D68: =_xlfn.XLOOKUP(I68,calculations!$t:$t,calculations!$s:$s) -> #VALUE! | E68: =_xlfn.XLOOKUP(I68,Mapping!$T:$T,Mapping!$Q:$Q) -> KEST11 | F68: 46203 | G68: 61002 | H68: 61002 | I68: 100212 | J68: Kestrel Battery | K68: Investor 2 Portfolio | L68: Investor 2 Portfolio | M68: Infra Debt | N68: 16871000 | O68: 16871000 | P68: EUR | Q68: Private Placement Note | R68: N | S68: L100212 | T68: Infrastructure Debt | U68: ES | V68: Spain | W68: Battery storage | X68: CR1010 | Y68: 17.4 | Z68: EUR | AA68: 1 | AB68: N | AC68: 17187000 | AD68: 17187000 | AE68: 17187000 | AF68: 0.9816 | AG68: 16871000 | AH68: 16871000 | AI68: 316000 | AJ68: 17187000 | AK68: 16871000 | AL68: 16871000 | AM68: EURIBOR 6M | AN68: 3.926 | AO68: 3.422 | AP68: 3.391 | AQ68: 100 | AR68: 100 | AS68: 44300 | AT68: 54162 | AU68: 46295 | AV68: PI2010 | AW68: Meridian Infrastructure | AX68: N | AY68: Kestrel Battery Finance Ltd | AZ68: Kestrel Battery Finance | BA68: Spain | BB68: Meridian Infrastructure | BC68: 529900SYNTH000000010 | BI68: 17187000 | BJ68: 17187000 | BK68: Floating | BL68: Senior Secured | BN68: 16.2 | BO68: 21.79 | BP68: Y | BQ68: N | BR68: Debt | BS68: RA100212 | BT68: E. Rossi | BU68: D. Schäfer | BW68: Semi-annual | BX68: ACT/360 | BY68: 210 | BZ68: 210 | CB68: EURIBOR | CC68: BBB | CD68: BBB | CE68: BBB+ | CF68: NR | CG68: NR | CH68: 46112 | CI68: 1.2 | CJ68: 2.3 | CK68: 2.42 | CL68: OK | DA68: 0.71 | DC68: 0.85 | DD68: OK | ED68: Watch | EE68: 1.05 | EI68: 1.12 | FQ68: 19825958
B69: =C69&"x"&I69 -> 61001x100213 | C69: =IF(G69="SINGLE",H69,G69) -> 61001 | D69: =_xlfn.XLOOKUP(I69,calculations!$t:$t,calculations!$s:$s) -> #VALUE! | E69: =_xlfn.XLOOKUP(I69,Mapping!$T:$T,Mapping!$Q:$Q) -> LUME12 | F69: 46203 | G69: 61001 | H69: 61001 | I69: 100213 | J69: Lumen Hospitals A | K69: Investor 1 Portfolio | L69: Investor 1 Portfolio | M69: Infra Debt | N69: 6470000 | O69: 6470000 | P69: EUR | Q69: Loan | R69: N | S69: L100213 | T69: Infrastructure Debt | U69: PT | V69: Portugal | W69: Hospitals (PPP) | X69: CR1011 | Y69: 11 | Z69: EUR | AA69: 1 | AB69: N | AC69: 6890000 | AD69: 6890000 | AE69: 6890000 | AF69: 0.939 | AG69: 6470000 | AH69: 6470000 | AI69: 420000 | AJ69: 6890000 | AK69: 6470000 | AL69: 6470000 | AN69: 3.477 | AO69: 3.862 | AP69: 3.298 | AQ69: 100 | AR69: 100 | AS69: 44813 | AT69: 51753 | AU69: 46295 | AV69: PI2011 | AW69: Helios Partners | AX69: N | AY69: Lumen Hospitals Finance Ltd | AZ69: Lumen Hospitals Finance | BA69: Portugal | BB69: Helios Partners | BC69: 529900SYNTH000000011 | BI69: 6890000 | BJ69: 6890000 | BK69: Fixed | BL69: Senior Secured | BN69: 11.4 | BO69: 15.2 | BP69: N | BQ69: N | BR69: Debt | BS69: RA100213 | BT69: D. Schäfer | BU69: B. Okoro | BW69: Quarterly | BX69: 30/360 | BY69: 140 | BZ69: 140 | CC69: A | CD69: A | CE69: NR | CF69: NR | CG69: NR | CH69: 46112 | CI69: 1.2 | CJ69: 2.99 | CK69: 3.14 | CL69: OK | DA69: 0.48 | DC69: 0.85 | DD69: OK | ED69: OK | EE69: 1.05 | EI69: 1.48 | FQ69: 27725621
B70: =C70&"x"&I70 -> 61001x100214 | C70: =IF(G70="SINGLE",H70,G70) -> 61001 | D70: =_xlfn.XLOOKUP(I70,calculations!$t:$t,calculations!$s:$s) -> #VALUE! | E70: =_xlfn.XLOOKUP(I70,Mapping!$T:$T,Mapping!$Q:$Q) -> LUME12 | F70: 46203 | G70: 61001 | H70: 61001 | I70: 100214 | J70: Lumen Hospitals B | K70: Investor 1 Portfolio | L70: Investor 1 Portfolio | M70: Infra Debt | N70: 4313000 | O70: 4313000 | P70: EUR | Q70: Loan | R70: N | S70: L100214 | T70: Infrastructure Debt | U70: PT | V70: Portugal | W70: Hospitals (PPP) | X70: CR1011 | Y70: 11 | Z70: EUR | AA70: 1 | AB70: N | AC70: 4593000 | AD70: 4593000 | AE70: 4593000 | AF70: 0.939 | AG70: 4313000 | AH70: 4313000 | AI70: 280000 | AJ70: 4593000 | AK70: 4313000 | AL70: 4313000 | AN70: 2.885 | AO70: 6.472 | AP70: 2.985 | AQ70: 100 | AR70: 100 | AS70: 44813 | AT70: 51753 | AU70: 46295 | AV70: PI2011 | AW70: Helios Partners | AX70: N | AY70: Lumen Hospitals Finance Ltd | AZ70: Lumen Hospitals Finance | BA70: Portugal | BB70: Helios Partners | BC70: 529900SYNTH000000011 | BI70: 4593000 | BJ70: 4593000 | BK70: Fixed | BL70: Senior Secured | BN70: 11.4 | BO70: 15.2 | BP70: N | BQ70: N | BR70: Debt | BS70: RA100214 | BT70: D. Schäfer | BU70: E. Rossi | BW70: Semi-annual | BX70: ACT/360 | BY70: 140 | BZ70: 140 | CC70: A | CD70: A | CE70: NR | CF70: NR | CG70: NR | CH70: 46112 | CI70: 1.2 | CJ70: 1.65 | CK70: 1.73 | CL70: OK | DA70: 0.71 | DC70: 0.85 | DD70: OK | ED70: OK | EE70: 1.05 | EI70: 1.78 | FQ70: 21050881
B71: =C71&"x"&I71 -> 61003x100213 | C71: =IF(G71="SINGLE",H71,G71) -> 61003 | D71: =_xlfn.XLOOKUP(I71,calculations!$t:$t,calculations!$s:$s) -> #VALUE! | E71: =_xlfn.XLOOKUP(I71,Mapping!$T:$T,Mapping!$Q:$Q) -> LUME12 | F71: 46203 | G71: 61003 | H71: 61003 | I71: 100213 | J71: Lumen Hospitals A | K71: Investor 3 Portfolio | L71: Investor 3 Portfolio | M71: Infra Debt | N71: 15810000 | O71: 15810000 | P71: EUR | Q71: Loan | R71: N | S71: L100213 | T71: Infrastructure Debt | U71: PT | V71: Portugal | W71: Hospitals (PPP) | X71: CR1011 | Y71: 11 | Z71: EUR | AA71: 1 | AB71: N | AC71: 16836000 | AD71: 16836000 | AE71: 16836000 | AF71: 0.9391 | AG71: 15810000 | AH71: 15810000 | AI71: 1026000 | AJ71: 16836000 | AK71: 15810000 | AL71: 15810000 | AN71: 2.955 | AO71: 3.952 | AP71: 6.342 | AQ71: 100 | AR71: 100 | AS71: 44813 | AT71: 51753 | AU71: 46295 | AV71: PI2011 | AW71: Helios Partners | AX71: N | AY71: Lumen Hospitals Finance Ltd | AZ71: Lumen Hospitals Finance | BA71: Portugal | BB71: Helios Partners | BC71: 529900SYNTH000000011 | BI71: 16836000 | BJ71: 16836000 | BK71: Fixed | BL71: Senior Secured | BN71: 11.4 | BO71: 15.2 | BP71: N | BQ71: N | BR71: Debt | BS71: RA100213 | BT71: D. Schäfer | BU71: C. Dubois | BW71: Semi-annual | BX71: ACT/360 | BY71: 140 | BZ71: 140 | CC71: A | CD71: A | CE71: NR | CF71: NR | CG71: NR | CH71: 46112 | CI71: 1.2 | CJ71: 2.04 | CK71: 2.14 | CL71: OK | DA71: 0.66 | DC71: 0.85 | DD71: OK | ED71: OK | EE71: 1.05 | EI71: 1.7 | FQ71: 27329550
B72: =C72&"x"&I72 -> 61003x100214 | C72: =IF(G72="SINGLE",H72,G72) -> 61003 | D72: =_xlfn.XLOOKUP(I72,calculations!$t:$t,calculations!$s:$s) -> #VALUE! | E72: =_xlfn.XLOOKUP(I72,Mapping!$T:$T,Mapping!$Q:$Q) -> LUME12 | F72: 46203 | G72: 61003 | H72: 61003 | I72: 100214 | J72: Lumen Hospitals B | K72: Investor 3 Portfolio | L72: Investor 3 Portfolio | M72: Infra Debt | N72: 10540000 | O72: 10540000 | P72: EUR | Q72: Loan | R72: N | S72: L100214 | T72: Infrastructure Debt | U72: PT | V72: Portugal | W72: Hospitals (PPP) | X72: CR1011 | Y72: 11 | Z72: EUR | AA72: 1 | AB72: N | AC72: 11224000 | AD72: 11224000 | AE72: 11224000 | AF72: 0.9391 | AG72: 10540000 | AH72: 10540000 | AI72: 684000 | AJ72: 11224000 | AK72: 10540000 | AL72: 10540000 | AN72: 6.335 | AO72: 5.056 | AP72: 5.534 | AQ72: 100 | AR72: 100 | AS72: 44813 | AT72: 51753 | AU72: 46295 | AV72: PI2011 | AW72: Helios Partners | AX72: N | AY72: Lumen Hospitals Finance Ltd | AZ72: Lumen Hospitals Finance | BA72: Portugal | BB72: Helios Partners | BC72: 529900SYNTH000000011 | BI72: 11224000 | BJ72: 11224000 | BK72: Fixed | BL72: Senior Secured | BN72: 11.4 | BO72: 15.2 | BP72: N | BQ72: N | BR72: Debt | BS72: RA100214 | BT72: D. Schäfer | BU72: E. Rossi | BW72: Semi-annual | BX72: 30/360 | BY72: 140 | BZ72: 140 | CC72: A | CD72: A | CE72: NR | CF72: NR | CG72: NR | CH72: 46112 | CI72: 1.2 | CJ72: 1.45 | CK72: 1.52 | CL72: OK | DA72: 0.76 | DC72: 0.85 | DD72: OK | ED72: OK | EE72: 1.05 | EI72: 1.93 | FQ72: 29006948
B73: =C73&"x"&I73 -> 61021x100213 | C73: =IF(G73="SINGLE",H73,G73) -> 61021 | D73: =_xlfn.XLOOKUP(I73,calculations!$t:$t,calculations!$s:$s) -> #VALUE! | E73: =_xlfn.XLOOKUP(I73,Mapping!$T:$T,Mapping!$Q:$Q) -> LUME12 | F73: 46203 | G73: 61021 | H73: 61021 | I73: 100213 | J73: Lumen Hospitals A | K73: Fund 1 Fund | L73: Fund 1 Fund | M73: Infra Debt | N73: 14083000 | O73: 14083000 | P73: EUR | Q73: Loan | R73: N | S73: L100213 | T73: Infrastructure Debt | U73: PT | V73: Portugal | W73: Hospitals (PPP) | X73: CR1011 | Y73: 11 | Z73: EUR | AA73: 1 | AB73: N | AC73: 14997000 | AD73: 14997000 | AE73: 14997000 | AF73: 0.9391 | AG73: 14083000 | AH73: 14083000 | AI73: 914000 | AJ73: 14997000 | AK73: 14083000 | AL73: 14083000 | AN73: 5.783 | AO73: 4.506 | AP73: 6.195 | AQ73: 100 | AR73: 100 | AS73: 44813 | AT73: 51753 | AU73: 46295 | AV73: PI2011 | AW73: Helios Partners | AX73: N | AY73: Lumen Hospitals Finance Ltd | AZ73: Lumen Hospitals Finance | BA73: Portugal | BB73: Helios Partners | BC73: 529900SYNTH000000011 | BI73: 14997000 | BJ73: 14997000 | BK73: Fixed | BL73: Senior Secured | BN73: 11.4 | BO73: 15.2 | BP73: N | BQ73: N | BR73: Debt | BS73: RA100213 | BT73: D. Schäfer | BU73: A. Martin | BW73: Semi-annual | BX73: 30/360 | BY73: 140 | BZ73: 140 | CC73: A | CD73: A | CE73: NR | CF73: NR | CG73: NR | CH73: 46112 | CI73: 1.2 | CJ73: 2.93 | CK73: 3.08 | CL73: OK | DA73: 0.65 | DC73: 0.85 | DD73: OK | ED73: OK | EE73: 1.05 | EI73: 1.32 | FQ73: 19292926
B74: =C74&"x"&I74 -> 61021x100214 | C74: =IF(G74="SINGLE",H74,G74) -> 61021 | D74: =_xlfn.XLOOKUP(I74,calculations!$t:$t,calculations!$s:$s) -> #VALUE! | E74: =_xlfn.XLOOKUP(I74,Mapping!$T:$T,Mapping!$Q:$Q) -> LUME12 | F74: 46203 | G74: 61021 | H74: 61021 | I74: 100214 | J74: Lumen Hospitals B | K74: Fund 1 Fund | L74: Fund 1 Fund | M74: Infra Debt | N74: 9389000 | O74: 9389000 | P74: EUR | Q74: Loan | R74: N | S74: L100214 | T74: Infrastructure Debt | U74: PT | V74: Portugal | W74: Hospitals (PPP) | X74: CR1011 | Y74: 11 | Z74: EUR | AA74: 1 | AB74: N | AC74: 9998000 | AD74: 9998000 | AE74: 9998000 | AF74: 0.9391 | AG74: 9389000 | AH74: 9389000 | AI74: 609000 | AJ74: 9998000 | AK74: 9389000 | AL74: 9389000 | AN74: 4.458 | AO74: 2.632 | AP74: 4.485 | AQ74: 100 | AR74: 100 | AS74: 44813 | AT74: 51753 | AU74: 46295 | AV74: PI2011 | AW74: Helios Partners | AX74: N | AY74: Lumen Hospitals Finance Ltd | AZ74: Lumen Hospitals Finance | BA74: Portugal | BB74: Helios Partners | BC74: 529900SYNTH000000011 | BI74: 9998000 | BJ74: 9998000 | BK74: Fixed | BL74: Senior Secured | BN74: 11.4 | BO74: 15.2 | BP74: N | BQ74: N | BR74: Debt | BS74: RA100214 | BT74: D. Schäfer | BU74: A. Martin | BW74: Quarterly | BX74: ACT/360 | BY74: 140 | BZ74: 140 | CC74: A | CD74: A | CE74: BBB – | CF74: NR | CG74: NR | CH74: 46112 | CI74: 1.2 | CJ74: 3.12 | CK74: 3.28 | CL74: OK | DA74: 0.85 | DC74: 0.85 | DD74: Watch | ED74: OK | EE74: 1.05 | EI74: 1.73 | FQ74: 21945402
B75: =C75&"x"&I75 -> 61017x100213 | C75: =IF(G75="SINGLE",H75,G75) -> 61017 | D75: =_xlfn.XLOOKUP(I75,calculations!$t:$t,calculations!$s:$s) -> #VALUE! | E75: =_xlfn.XLOOKUP(I75,Mapping!$T:$T,Mapping!$Q:$Q) -> LUME12 | F75: 46203 | G75: 61017 | H75: 61017 | I75: 100213 | J75: Lumen Hospitals A | K75: Investor 17 Mandate | L75: Investor 17 Mandate | M75: Infra Debt | N75: 10929000 | O75: 10929000 | P75: EUR | Q75: Loan | R75: N | S75: L100213 | T75: Infrastructure Debt | U75: PT | V75: Portugal | W75: Hospitals (PPP) | X75: CR1011 | Y75: 11 | Z75: EUR | AA75: 1 | AB75: N | AC75: 11638000 | AD75: 11638000 | AE75: 11638000 | AF75: 0.9391 | AG75: 10929000 | AH75: 10929000 | AI75: 709000 | AJ75: 11638000 | AK75: 10929000 | AL75: 10929000 | AN75: 4.247 | AO75: 6.213 | AP75: 2.677 | AQ75: 100 | AR75: 100 | AS75: 44813 | AT75: 51753 | AU75: 46295 | AV75: PI2011 | AW75: Helios Partners | AX75: N | AY75: Lumen Hospitals Finance Ltd | AZ75: Lumen Hospitals Finance | BA75: Portugal | BB75: Helios Partners | BC75: 529900SYNTH000000011 | BI75: 11638000 | BJ75: 11638000 | BK75: Fixed | BL75: Senior Secured | BN75: 11.4 | BO75: 15.2 | BP75: N | BQ75: N | BR75: Debt | BS75: RA100213 | BT75: D. Schäfer | BU75: E. Rossi | BW75: Semi-annual | BX75: ACT/360 | BY75: 140 | BZ75: 140 | CC75: A | CD75: A | CE75: NR | CF75: NR | CG75: NR | CH75: 46112 | CI75: 1.2 | CJ75: 2.86 | CK75: 3 | CL75: OK | DA75: 0.79 | DC75: 0.85 | DD75: OK | ED75: OK | EE75: 1.05 | EI75: 1.57 | FQ75: 33210385
B76: =C76&"x"&I76 -> 61017x100214 | C76: =IF(G76="SINGLE",H76,G76) -> 61017 | D76: =_xlfn.XLOOKUP(I76,calculations!$t:$t,calculations!$s:$s) -> #VALUE! | E76: =_xlfn.XLOOKUP(I76,Mapping!$T:$T,Mapping!$Q:$Q) -> LUME12 | F76: 46203 | G76: 61017 | H76: 61017 | I76: 100214 | J76: Lumen Hospitals B | K76: Investor 17 Mandate | L76: Investor 17 Mandate | M76: Infra Debt | N76: 7286000 | O76: 7286000 | P76: EUR | Q76: Loan | R76: N | S76: L100214 | T76: Infrastructure Debt | U76: PT | V76: Portugal | W76: Hospitals (PPP) | X76: CR1011 | Y76: 11 | Z76: EUR | AA76: 1 | AB76: N | AC76: 7759000 | AD76: 7759000 | AE76: 7759000 | AF76: 0.939 | AG76: 7286000 | AH76: 7286000 | AI76: 473000 | AJ76: 7759000 | AK76: 7286000 | AL76: 7286000 | AN76: 4.968 | AO76: 5.131 | AP76: 3.099 | AQ76: 100 | AR76: 100 | AS76: 44813 | AT76: 51753 | AU76: 46295 | AV76: PI2011 | AW76: Helios Partners | AX76: N | AY76: Lumen Hospitals Finance Ltd | AZ76: Lumen Hospitals Finance | BA76: Portugal | BB76: Helios Partners | BC76: 529900SYNTH000000011 | BI76: 7759000 | BJ76: 7759000 | BK76: Fixed | BL76: Senior Secured | BN76: 11.4 | BO76: 15.2 | BP76: N | BQ76: N | BR76: Debt | BS76: RA100214 | BT76: D. Schäfer | BU76: C. Dubois | BW76: Quarterly | BX76: 30/360 | BY76: 140 | BZ76: 140 | CC76: A | CD76: A | CE76: NR | CF76: NR | CG76: NR | CH76: 46112 | CI76: 1.2 | CJ76: 2.12 | CK76: 2.23 | CL76: OK | DA76: 0.62 | DC76: 0.85 | DD76: OK | ED76: OK | EE76: 1.05 | EI76: 1.53 | FQ76: 23995624
B77: =C77&"x"&I77 -> 61019x100213 | C77: =IF(G77="SINGLE",H77,G77) -> 61019 | D77: =_xlfn.XLOOKUP(I77,calculations!$t:$t,calculations!$s:$s) -> #VALUE! | E77: =_xlfn.XLOOKUP(I77,Mapping!$T:$T,Mapping!$Q:$Q) -> LUME12 | F77: 46203 | G77: 61019 | H77: 61019 | I77: 100213 | J77: Lumen Hospitals A | K77: Investor 19 Mandate | L77: Investor 19 Mandate | M77: Infra Debt | N77: 9851000 | O77: 9851000 | P77: EUR | Q77: Loan | R77: N | S77: L100213 | T77: Infrastructure Debt | U77: PT | V77: Portugal | W77: Hospitals (PPP) | X77: CR1011 | Y77: 11 | Z77: EUR | AA77: 1 | AB77: N | AC77: 10490000 | AD77: 10490000 | AE77: 10490000 | AF77: 0.9391 | AG77: 9851000 | AH77: 9851000 | AI77: 639000 | AJ77: 10490000 | AK77: 9851000 | AL77: 9851000 | AN77: 6.432 | AO77: 6.166 | AP77: 4.886 | AQ77: 100 | AR77: 100 | AS77: 44813 | AT77: 51753 | AU77: 46295 | AV77: PI2011 | AW77: Helios Partners | AX77: N | AY77: Lumen Hospitals Finance Ltd | AZ77: Lumen Hospitals Finance | BA77: Portugal | BB77: Helios Partners | BC77: 529900SYNTH000000011 | BI77: 10490000 | BJ77: 10490000 | BK77: Fixed | BL77: Senior Secured | BN77: 11.4 | BO77: 15.2 | BP77: N | BQ77: N | BR77: Debt | BS77: RA100213 | BT77: D. Schäfer | BU77: B. Okoro | BW77: Quarterly | BX77: 30/360 | BY77: 140 | BZ77: 140 | CC77: A | CD77: A | CE77: NR | CF77: NR | CG77: NR | CH77: 46112 | CI77: 1.2 | CJ77: 1.48 | CK77: 1.55 | CL77: OK | DA77: 0.81 | DC77: 0.85 | DD77: Watch | ED77: OK | EE77: 1.05 | EI77: 1.65 | FQ77: 23276432
B78: =C78&"x"&I78 -> 61019x100214 | C78: =IF(G78="SINGLE",H78,G78) -> 61019 | D78: =_xlfn.XLOOKUP(I78,calculations!$t:$t,calculations!$s:$s) -> #VALUE! | E78: =_xlfn.XLOOKUP(I78,Mapping!$T:$T,Mapping!$Q:$Q) -> LUME12 | F78: 46203 | G78: 61019 | H78: 61019 | I78: 100214 | J78: Lumen Hospitals B | K78: Investor 19 Mandate | L78: Investor 19 Mandate | M78: Infra Debt | N78: 6567000 | O78: 6567000 | P78: EUR | Q78: Loan | R78: N | S78: L100214 | T78: Infrastructure Debt | U78: PT | V78: Portugal | W78: Hospitals (PPP) | X78: CR1011 | Y78: 11 | Z78: EUR | AA78: 1 | AB78: N | AC78: 6993000 | AD78: 6993000 | AE78: 6993000 | AF78: 0.9391 | AG78: 6567000 | AH78: 6567000 | AI78: 426000 | AJ78: 6993000 | AK78: 6567000 | AL78: 6567000 | AN78: 4.696 | AO78: 6.254 | AP78: 2.987 | AQ78: 100 | AR78: 100 | AS78: 44813 | AT78: 51753 | AU78: 46295 | AV78: PI2011 | AW78: Helios Partners | AX78: N | AY78: Lumen Hospitals Finance Ltd | AZ78: Lumen Hospitals Finance | BA78: Portugal | BB78: Helios Partners | BC78: 529900SYNTH000000011 | BI78: 6993000 | BJ78: 6993000 | BK78: Fixed | BL78: Senior Secured | BN78: 11.4 | BO78: 15.2 | BP78: N | BQ78: N | BR78: Debt | BS78: RA100214 | BT78: D. Schäfer | BU78: A. Martin | BW78: Semi-annual | BX78: 30/360 | BY78: 140 | BZ78: 140 | CC78: A | CD78: A | CE78: NR | CF78: NR | CG78: NR | CH78: 46112 | CI78: 1.2 | CJ78: 2.01 | CK78: 2.11 | CL78: OK | DA78: 0.61 | DC78: 0.85 | DD78: OK | ED78: OK | EE78: 1.05 | EI78: 1.23 | FQ78: 25270519
B79: =C79&"x"&I79 -> 61012x100213 | C79: =IF(G79="SINGLE",H79,G79) -> 61012 | D79: =_xlfn.XLOOKUP(I79,calculations!$t:$t,calculations!$s:$s) -> #VALUE! | E79: =_xlfn.XLOOKUP(I79,Mapping!$T:$T,Mapping!$Q:$Q) -> LUME12 | F79: 46203 | G79: 61012 | H79: 61012 | I79: 100213 | J79: Lumen Hospitals A | K79: Investor 12 Mandate | L79: Investor 12 Mandate | M79: Infra Debt | N79: 11734000 | O79: 11734000 | P79: GBP | Q79: Loan | R79: N | S79: L100213 | T79: Infrastructure Debt | U79: PT | V79: Portugal | W79: Hospitals (PPP) | X79: CR1011 | Y79: 11 | Z79: EUR | AA79: 1 | AB79: N | AC79: 12496000 | AD79: 12496000 | AE79: 12496000 | AF79: 0.939 | AG79: 11734000 | AH79: 11734000 | AI79: 762000 | AJ79: 12496000 | AK79: 11734000 | AL79: 11734000 | AN79: 3.93 | AO79: 3.14 | AP79: 4.847 | AQ79: 100 | AR79: 100 | AS79: 44813 | AT79: 51753 | AU79: 46295 | AV79: PI2011 | AW79: Helios Partners | AX79: N | AY79: Lumen Hospitals Finance Ltd | AZ79: Lumen Hospitals Finance | BA79: Portugal | BB79: Helios Partners | BC79: 529900SYNTH000000011 | BI79: 12496000 | BJ79: 12496000 | BK79: Fixed | BL79: Senior Secured | BN79: 11.4 | BO79: 15.2 | BP79: N | BQ79: N | BR79: Debt | BS79: RA100213 | BT79: D. Schäfer | BU79: A. Martin | BW79: Semi-annual | BX79: ACT/360 | BY79: 140 | BZ79: 140 | CC79: A | CD79: A | CE79: NR | CF79: NR | CG79: NR | CH79: 46112 | CI79: 1.2 | CJ79: 2.49 | CK79: 2.61 | CL79: OK | DA79: 0.52 | DC79: 0.85 | DD79: OK | ED79: OK | EE79: 1.05 | EI79: 1.63 | FQ79: 25090287
B80: =C80&"x"&I80 -> 61012x100214 | C80: =IF(G80="SINGLE",H80,G80) -> 61012 | D80: =_xlfn.XLOOKUP(I80,calculations!$t:$t,calculations!$s:$s) -> #VALUE! | E80: =_xlfn.XLOOKUP(I80,Mapping!$T:$T,Mapping!$Q:$Q) -> LUME12 | F80: 46203 | G80: 61012 | H80: 61012 | I80: 100214 | J80: Lumen Hospitals B | K80: Investor 12 Mandate | L80: Investor 12 Mandate | M80: Infra Debt | N80: 7823000 | O80: 7823000 | P80: GBP | Q80: Loan | R80: N | S80: L100214 | T80: Infrastructure Debt | U80: PT | V80: Portugal | W80: Hospitals (PPP) | X80: CR1011 | Y80: 11 | Z80: EUR | AA80: 1 | AB80: N | AC80: 8331000 | AD80: 8331000 | AE80: 8331000 | AF80: 0.939 | AG80: 7823000 | AH80: 7823000 | AI80: 508000 | AJ80: 8331000 | AK80: 7823000 | AL80: 7823000 | AN80: 2.957 | AO80: 6.421 | AP80: 3.357 | AQ80: 100 | AR80: 100 | AS80: 44813 | AT80: 51753 | AU80: 46295 | AV80: PI2011 | AW80: Helios Partners | AX80: N | AY80: Lumen Hospitals Finance Ltd | AZ80: Lumen Hospitals Finance | BA80: Portugal | BB80: Helios Partners | BC80: 529900SYNTH000000011 | BI80: 8331000 | BJ80: 8331000 | BK80: Fixed | BL80: Senior Secured | BN80: 11.4 | BO80: 15.2 | BP80: N | BQ80: N | BR80: Debt | BS80: RA100214 | BT80: D. Schäfer | BU80: D. Schäfer | BW80: Quarterly | BX80: ACT/360 | BY80: 140 | BZ80: 140 | CC80: A | CD80: A | CE80: NR | CF80: NR | CG80: NR | CH80: 46112 | CI80: 1.2 | CJ80: 1.68 | CK80: 1.76 | CL80: OK | DA80: 0.61 | DC80: 0.85 | DD80: OK | ED80: OK | EE80: 1.05 | EI80: 1.35 | FQ80: 27802668
... B83: =C83&"x"&I83 -> 61005x100215 | C83: =IF(G83="SINGLE",H83,G83) -> 61005 | D83: =_xlfn.XLOOKUP(I83,calculations!$t:$t,calculations!$s:$s) -> #VALUE! | E83: =_xlfn.XLOOKUP(I83,Mapping!$T:$T,Mapping!$Q:$Q) -> MERI13 | F83: 46203 | G83: 61005 | H83: 61005 | I83: 100215 | J83: Meridian Solar | K83: Investor 5 Portfolio | L83: Investor 5 Portfolio | M83: Infra Debt | N83: 8778000 | O83: 8778000 | P83: EUR | Q83: Loan | R83: Y | S83: L100215 | T83: Infrastructure Debt | U83: IE | V83: Ireland | W83: Solar PV | X83: CR1012 | Y83: 10.3 | Z83: EUR | AA83: 1 | AB83: N | AC83: 9199000 | AD83: 9199000 | AE83: 9199000 | AF83: 0.9542 | AG83: 8778000 | AH83: 8778000 | AI83: 421000 | AJ83: 9199000 | AK83: 8778000 | AL83: 8778000 | AN83: 6.224 | AO83: 5.801 | AP83: 2.636 | AQ83: 100 | AR83: 100 | AS83: 42651 | AT83: 49590 | AU83: 46295 | AV83: PI2012 | AW83: Boreal Energy | AX83: N | AY83: Meridian Solar Finance Ltd | AZ83: Meridian Solar Finance | BA83: Ireland | BB83: Boreal Energy | BC83: 529900SYNTH000000012 | BI83: 9199000 | BJ83: 9199000 | BK83: Fixed | BL83: Senior Secured | BN83: 11.4 | BO83: 9.27 | BP83: N | BQ83: Y | BR83: Debt | BS83: RA100215 | BT83: D. Schäfer | BU83: B. Okoro | BW83: Quarterly | BX83: ACT/360 | BY83: 330 | BZ83: 330 | CC83: BBB | CD83: BBB | CE83: BBB- | CF83: NR | CG83: Baa2 | CH83: 46112 | CI83: 1.2 | CJ83: 3.24 | CK83: 3.4 | CL83: OK | DA83: 0.49 | DC83: 0.85 | DD83: OK | ED83: OK | EE83: 1.05 | EI83: 1.84 | FQ83: 49081248
B84: =C84&"x"&I84 -> 61018x100215 | C84: =IF(G84="SINGLE",H84,G84) -> 61018 | D84: =_xlfn.XLOOKUP(I84,calculations!$t:$t,calculations!$s:$s) -> #VALUE! | E84: =_xlfn.XLOOKUP(I84,Mapping!$T:$T,Mapping!$Q:$Q) -> MERI13 | F84: 46203 | G84: 61018 | H84: 61018 | I84: 100215 | J84: Meridian Solar | K84: Investor 18 Mandate | L84: Investor 18 Mandate | M84: Infra Debt | N84: 20808000 | O84: 20808000 | P84: EUR | Q84: Loan | R84: Y | S84: L100215 | T84: Infrastructure Debt | U84: IE | V84: Ireland | W84: Solar PV | X84: CR1012 | Y84: 10.3 | Z84: EUR | AA84: 1 | AB84: N | AC84: 21806000 | AD84: 21806000 | AE84: 21806000 | AF84: 0.9542 | AG84: 20808000 | AH84: 20808000 | AI84: 998000 | AJ84: 21806000 | AK84: 20808000 | AL84: 20808000 | AN84: 4.424 | AO84: 3.398 | AP84: 6.434 | AQ84: 100 | AR84: 100 | AS84: 42651 | AU84: 46295 | AV84: PI2012 | AW84: Boreal Energy | AX84: N | AY84: Meridian Solar Finance Ltd | AZ84: Meridian Solar Finance | BA84: Ireland | BB84: Boreal Energy | BC84: 529900SYNTH000000012 | BI84: 21806000 | BJ84: 21806000 | BK84: Fixed | BL84: Senior Secured | BN84: 11.4 | BO84: 9.27 | BP84: N | BQ84: Y | BR84: Debt | BS84: RA100215 | BT84: D. Schäfer | BU84: D. Schäfer | BW84: Quarterly | BX84: ACT/360 | BY84: 330 | BZ84: 330 | CC84: BBB | CD84: BBB | CE84: BBB- | CF84: NR | CG84: Baa2 | CH84: 46112 | CI84: 1.2 | CJ84: 2.59 | CK84: 2.72 | CL84: OK | DA84: 0.63 | DC84: 0.85 | DD84: OK | ED84: OK | EE84: 1.05 | EI84: 1.42 | FQ84: 65888359
B85: =C85&"x"&I85 -> 61015x100215 | C85: =IF(G85="SINGLE",H85,G85) -> 61015 | D85: =_xlfn.XLOOKUP(I85,calculations!$t:$t,calculations!$s:$s) -> #VALUE! | E85: =_xlfn.XLOOKUP(I85,Mapping!$T:$T,Mapping!$Q:$Q) -> MERI13 | F85: 46203 | G85: 61015 | H85: 61015 | I85: 100215 | J85: Meridian Solar | K85: Investor 15 Mandate | L85: Investor 15 Mandate | M85: Infra Debt | N85: 31277000 | O85: 31277000 | P85: EUR | Q85: Loan | R85: Y | S85: L100215 | T85: Infrastructure Debt | U85: IE | V85: Ireland | W85: Solar PV | X85: CR1012 | Y85: 10.3 | Z85: EUR | AA85: 1 | AB85: N | AC85: 32776000 | AD85: 32776000 | AE85: 32776000 | AF85: 0.9543 | AG85: 31277000 | AH85: 31277000 | AI85: 1499000 | AJ85: 32776000 | AK85: 31277000 | AL85: 31277000 | AN85: 2.567 | AO85: 4.908 | AP85: 5.828 | AQ85: 100 | AR85: 100 | AS85: 42651 | AT85: 49590 | AU85: 46295 | AV85: PI2012 | AW85: Boreal Energy | AX85: N | AY85: Meridian Solar Finance Ltd | AZ85: Meridian Solar Finance | BA85: Ireland | BB85: Boreal Energy | BC85: 529900SYNTH000000012 | BI85: 32776000 | BJ85: 32776000 | BK85: Fixed | BL85: Senior Secured | BN85: 11.4 | BO85: 9.27 | BP85: N | BQ85: Y | BR85: Debt | BS85: RA100215 | BT85: D. Schäfer | BU85: C. Dubois | BW85: Quarterly | BX85: 30/360 | BY85: 330 | BZ85: 330 | CC85: BBB | CD85: BBB | CE85: BBB- | CF85: NR | CG85: Baa2 | CH85: 46112 | CI85: 1.2 | CJ85: 1.55 | CK85: 1.63 | CL85: OK | DA85: 0.53 | DC85: 0.85 | DD85: OK | ED85: OK | EE85: 1.05 | EI85: 1.58 | FQ85: 75588706
B86: =C86&"x"&I86 -> 61004x100216 | C86: =IF(G86="SINGLE",H86,G86) -> 61004 | D86: =_xlfn.XLOOKUP(I86,calculations!$t:$t,calculations!$s:$s) -> #VALUE! | E86: =_xlfn.XLOOKUP(I86,Mapping!$T:$T,Mapping!$Q:$Q) -> NIMB14 | F86: 46203 | G86: 61004 | H86: 61004 | I86: 100216 | J86: Nimbus Airports | K86: Investor 4 Portfolio | L86: Investor 4 Portfolio | M86: Infra Debt | N86: 5122000 | O86: 5122000 | P86: EUR | Q86: Loan | R86: N | S86: L100216 | T86: Infrastructure Debt | U86: IE | V86: Ireland | W86: Airports | X86: CR1013 | Y86: 11.8 | Z86: EUR | AA86: 1 | AB86: N | AC86: 5217000 | AD86: 5217000 | AE86: 5217000 | AF86: 0.9818 | AG86: 5122000 | AH86: 5122000 | AI86: 95000 | AJ86: 5217000 | AK86: 5122000 | AL86: 5122000 | AN86: 3.155 | AO86: 3.022 | AP86: 3.621 | AQ86: 100 | AR86: 100 | AS86: 42217 | AT86: 50072 | AU86: 46295 | AV86: PI2013 | AW86: Silverline Transport | AX86: N | AY86: Nimbus Airports Finance Ltd | AZ86: Nimbus Airports Finance | BA86: Ireland | BB86: Silverline Transport | BC86: 529900SYNTH000000013 | BI86: 5217000 | BJ86: 5217000 | BK86: Fixed | BL86: Senior Secured | BN86: 12.9 | BO86: 10.59 | BP86: N | BQ86: N | BR86: Debt | BS86: RA100216 | BT86: A. Martin | BU86: D. Schäfer | BW86: Quarterly | BX86: 30/360 | BY86: 405 | BZ86: 405 | CC86: BB- | CD86: BB- | CE86: NR | CF86: NR | CG86: NR | CH86: 46112 | CI86: 1.2 | CJ86: 2.01 | CK86: 2.11 | CL86: OK | DA86: 0.73 | DC86: 0.85 | DD86: OK | ED86: Watch | EE86: 1.05 | EI86: 1.09 | FQ86: 7431952
B87: =C87&"x"&I87 -> 61015x100216 | C87: =IF(G87="SINGLE",H87,G87) -> 61015 | D87: =_xlfn.XLOOKUP(I87,calculations!$t:$t,calculations!$s:$s) -> #VALUE! | E87: =_xlfn.XLOOKUP(I87,Mapping!$T:$T,Mapping!$Q:$Q) -> NIMB14 | F87: 46203 | G87: 61015 | H87: 61015 | I87: 100216 | J87: Nimbus Airports | K87: Investor 15 Mandate | L87: Investor 15 Mandate | M87: Infra Debt | N87: 5681000 | O87: 5681000 | P87: EUR | Q87: Loan | R87: N | S87: L100216 | T87: Infrastructure Debt | U87: IE | V87: Ireland | W87: Airports | X87: CR1013 | Y87: 11.8 | Z87: EUR | AA87: 1 | AB87: N | AC87: 5786000 | AD87: 5786000 | AE87: 5786000 | AF87: 0.9819 | AG87: 5681000 | AH87: 5681000 | AI87: 105000 | AJ87: 5786000 | AK87: 5681000 | AL87: 5681000 | AN87: 3.076 | AO87: 5.974 | AP87: 3.636 | AQ87: 100 | AR87: 100 | AS87: 42217 | AT87: 50072 | AU87: 46295 | AV87: PI2013 | AW87: Silverline Transport | AX87: N | AY87: Nimbus Airports Finance Ltd | AZ87: Nimbus Airports Finance | BA87: Ireland | BB87: Silverline Transport | BC87: 529900SYNTH000000013 | BI87: 5786000 | BJ87: 5786000 | BK87: Fixed | BL87: Senior Secured | BN87: 12.9 | BO87: 10.59 | BP87: N | BQ87: N | BR87: Debt | BS87: RA100216 | BT87: A. Martin | BU87: E. Rossi | BW87: Semi-annual | BX87: ACT/360 | BY87: 405 | BZ87: 405 | CC87: BB- | CD87: BB- | CE87: NR | CF87: NR | CG87: NR | CH87: 46112 | CI87: 1.2 | CJ87: 2.54 | CK87: 2.67 | CL87: OK | DA87: 0.8 | DC87: 0.85 | DD87: Watch | ED87: Watch | EE87: 1.05 | EI87: 1.19 | FQ87: 11562130
B88: =C88&"x"&I88 -> 61026x100216 | C88: =IF(G88="SINGLE",H88,G88) -> 61026 | D88: =_xlfn.XLOOKUP(I88,calculations!$t:$t,calculations!$s:$s) -> #VALUE! | E88: =_xlfn.XLOOKUP(I88,Mapping!$T:$T,Mapping!$Q:$Q) -> NIMB14 | F88: 46203 | G88: 61026 | H88: 61026 | I88: 100216 | J88: Nimbus Airports | K88: Fund 6 Fund | L88: Fund 6 Fund | M88: Infra Debt | N88: 1498000 | O88: 1498000 | P88: EUR | Q88: Loan | R88: N | S88: L100216 | T88: Infrastructure Debt | U88: IE | V88: Ireland | W88: Airports | X88: CR1013 | Y88: 11.8 | Z88: EUR | AA88: 1 | AB88: N | AC88: 1526000 | AD88: 1526000 | AE88: 1526000 | AF88: 0.9817 | AG88: 1498000 | AH88: 1498000 | AI88: 28000 | AJ88: 1526000 | AK88: 1498000 | AL88: 1498000 | AN88: 5.135 | AO88: 5.732 | AP88: 4.914 | AQ88: 100 | AR88: 100 | AS88: 42217 | AT88: 50072 | AU88: 46295 | AV88: PI2013 | AW88: Silverline Transport | AX88: N | AY88: Nimbus Airports Finance Ltd | AZ88: Nimbus Airports Finance | BA88: Ireland | BB88: Silverline Transport | BC88: 529900SYNTH000000013 | BI88: 1526000 | BJ88: 1526000 | BK88: Fixed | BL88: Senior Secured | BN88: 12.9 | BO88: 10.59 | BP88: N | BQ88: N | BR88: Debt | BS88: RA100216 | BT88: A. Martin | BU88: B. Okoro | BW88: Semi-annual | BX88: ACT/360 | BY88: 405 | BZ88: 405 | CC88: BB- | CD88: BB- | CE88: NR | CF88: NR | CG88: NR | CH88: 46112 | CI88: 1.2 | CJ88: 3.19 | CK88: 3.35 | CL88: OK | DA88: 0.51 | DC88: 0.85 | DD88: OK | ED88: Watch | EE88: 1.05 | EI88: 1.19 | FQ88: 8570468
B89: =C89&"x"&I89 -> 61019x100216 | C89: =IF(G89="SINGLE",H89,G89) -> 61019 | D89: =_xlfn.XLOOKUP(I89,calculations!$t:$t,calculations!$s:$s) -> #VALUE! | E89: =_xlfn.XLOOKUP(I89,Mapping!$T:$T,Mapping!$Q:$Q) -> NIMB14 | F89: 46203 | G89: 61019 | H89: 61019 | I89: 100216 | J89: Nimbus Airports | K89: Investor 19 Mandate | L89: Investor 19 Mandate | M89: Infra Debt | N89: 3626000 | O89: 3626000 | P89: EUR | Q89: Loan | R89: N | S89: L100216 | T89: Infrastructure Debt | U89: IE | V89: Ireland | W89: Airports | X89: CR1013 | Y89: 11.8 | Z89: EUR | AA89: 1 | AB89: N | AC89: 3693000 | AD89: 3693000 | AE89: 3693000 | AF89: 0.9819 | AG89: 3626000 | AH89: 3626000 | AI89: 67000 | AJ89: 3693000 | AK89: 3626000 | AL89: 3626000 | AN89: 6.432 | AO89: 3.126 | AP89: 3.484 | AQ89: 100 | AR89: 100 | AS89: 42217 | AT89: 50072 | AU89: 46295 | AV89: PI2013 | AW89: Silverline Transport | AX89: N | AY89: Nimbus Airports Finance Ltd | AZ89: Nimbus Airports Finance | BA89: Ireland | BB89: Silverline Transport | BC89: 529900SYNTH000000013 | BI89: 3693000 | BJ89: 3693000 | BK89: Fixed | BL89: Senior Secured | BN89: 12.9 | BO89: 10.59 | BP89: N | BQ89: N | BR89: Debt | BS89: RA100216 | BT89: A. Martin | BU89: D. Schäfer | BW89: Semi-annual | BX89: ACT/360 | BY89: 405 | BZ89: 405 | CC89: BB- | CD89: BB- | CE89: NR | CF89: NR | CG89: NR | CH89: 46112 | CI89: 1.2 | CJ89: 1.53 | CK89: 1.61 | CL89: OK | DA89: 0.59 | DC89: 0.85 | DD89: OK | ED89: OK | EE89: 1.05 | EI89: 1.45 | FQ89: 10553719
B90: =C90&"x"&I90 -> 61014x100217 | C90: =IF(G90="SINGLE",H90,G90) -> 61014 | D90: =_xlfn.XLOOKUP(I90,calculations!$t:$t,calculations!$s:$s) -> #VALUE! | E90: =_xlfn.XLOOKUP(I90,Mapping!$T:$T,Mapping!$Q:$Q) -> ORIO15 | F90: 46203 | G90: 61014 | H90: 61014 | I90: 100217 | J90: Orion Fibre | K90: Investor 14 Mandate | L90: Investor 14 Mandate | M90: Infra Debt | N90: 14679000 | O90: 14679000 | P90: EUR | Q90: Loan | R90: Y | S90: L100217 | T90: Infrastructure Debt | U90: FI | V90: Finland | W90: Fibre networks | X90: CR1014 | Y90: 6.2 | Z90: EUR | AA90: 1 | AB90: N | AC90: 16151000 | AD90: 16151000 | AE90: 16151000 | AF90: 0.9089 | AG90: 14679000 | AH90: 14679000 | AI90: 1472000 | AJ90: 16151000 | AK90: 14679000 | AL90: 14679000 | AN90: 4.442 | AO90: 5.795 | AP90: 4.03 | AQ90: 100 | AR90: 100 | AS90: 44221 | AT90: 48785 | AU90: 46295 | AV90: PI2014 | AW90: Helios Partners | AX90: N | AY90: Orion Fibre Finance Ltd | AZ90: Orion Fibre Finance | BA90: Finland | BB90: Helios Partners | BC90: 529900SYNTH000000014 | BI90: 16151000 | BJ90: 16151000 | BK90: Fixed | BL90: Senior Secured | BN90: 7.5 | BO90: 7.07 | BP90: N | BQ90: N | BR90: Debt | BS90: RA100217 | BT90: F. Lindqvist | BU90: D. Schäfer | BW90: Semi-annual | BX90: ACT/360 | BY90: 365 | BZ90: 365 | CC90: BBB- | CD90: BBB- | CE90: BB+ | CF90: BB+ | CG90: NR | CH90: 46112 | CI90: 1.2 | CJ90: 1.37 | CK90: 1.44 | CL90: OK | DA90: 0.64 | DC90: 0.85 | DD90: OK | ED90: OK | EE90: 1.05 | EI90: 1.57 | FQ90: 30149770
B91: =C91&"x"&I91 -> 61024x100217 | C91: =IF(G91="SINGLE",H91,G91) -> 61024 | D91: =_xlfn.XLOOKUP(I91,calculations!$t:$t,calculations!$s:$s) -> #VALUE! | E91: =_xlfn.XLOOKUP(I91,Mapping!$T:$T,Mapping!$Q:$Q) -> ORIO15 | F91: 46203 | G91: 61024 | H91: 61024 | I91: 100217 | J91: Orion Fibre | K91: Fund 4 Fund | L91: Fund 4 Fund | M91: Infra Debt | N91: 12025000 | O91: 12025000 | P91: EUR | Q91: Loan | R91: Y | S91: L100217 | T91: Infrastructure Debt | U91: FI | V91: Finland | W91: Fibre networks | X91: CR1014 | Y91: 6.2 | Z91: EUR | AA91: 1 | AB91: N | AC91: 13231000 | AD91: 13231000 | AE91: 13231000 | AF91: 0.9089 | AG91: 12025000 | AH91: 12025000 | AI91: 1206000 | AJ91: 13231000 | AK91: 12025000 | AL91: 12025000 | AN91: 2.639 | AO91: 4.983 | AP91: 3.343 | AQ91: 100 | AR91: 100 | AS91: 44221 | AT91: 48785 | AU91: 46295 | AV91: PI2014 | AW91: Helios Partners | AX91: N | AY91: Orion Fibre Finance Ltd | AZ91: Orion Fibre Finance | BA91: Finland | BB91: Helios Partners | BC91: 529900SYNTH000000014 | BI91: 13231000 | BJ91: 13231000 | BK91: Fixed | BL91: Senior Secured | BN91: 7.5 | BO91: 7.07 | BP91: N | BQ91: N | BR91: Debt | BS91: RA100217 | BT91: F. Lindqvist | BU91: A. Martin | BW91: Quarterly | BX91: 30/360 | BY91: 365 | BZ91: 365 | CC91: BBB- | CD91: BBB- | CE91: BB+ | CF91: BB+ | CG91: NR | CH91: 46112 | CI91: 1.2 | CJ91: 2.28 | CK91: 2.39 | CL91: OK | DA91: 0.77 | DC91: 0.85 | DD91: OK | ED91: OK | EE91: 1.05 | EI91: 1.62 | FQ91: 19713554
B92: =C92&"x"&I92 -> 61016x100217 | C92: =IF(G92="SINGLE",H92,G92) -> 61016 | D92: =_xlfn.XLOOKUP(I92,calculations!$t:$t,calculations!$s:$s) -> #VALUE! | E92: =_xlfn.XLOOKUP(I92,Mapping!$T:$T,Mapping!$Q:$Q) -> ORIO15 | F92: 46203 | G92: 61016 | H92: 61016 | I92: 100217 | J92: Orion Fibre | K92: Investor 16 Mandate | L92: Investor 16 Mandate | M92: Infra Debt | N92: 7082000 | O92: 7082000 | P92: EUR | Q92: Loan | R92: Y | S92: L100217 | T92: Infrastructure Debt | U92: FI | V92: Finland | W92: Fibre networks | X92: CR1014 | Y92: 6.2 | Z92: EUR | AA92: 1 | AB92: N | AC92: 7792000 | AD92: 7792000 | AE92: 7792000 | AF92: 0.9089 | AG92: 7082000 | AH92: 7082000 | AI92: 710000 | AJ92: 7792000 | AK92: 7082000 | AL92: 7082000 | AN92: 4.046 | AO92: 3.086 | AP92: 2.621 | AQ92: 100 | AR92: 100 | AS92: 44221 | AT92: 48785 | AU92: 46295 | AV92: PI2014 | AW92: Helios Partners | AX92: N | AY92: Orion Fibre Finance Ltd | AZ92: Orion Fibre Finance | BA92: Finland | BB92: Helios Partners | BC92: 529900SYNTH000000014 | BI92: 7792000 | BJ92: 7792000 | BK92: Fixed | BL92: Senior Secured | BN92: 7.5 | BO92: 7.07 | BP92: N | BQ92: N | BR92: Debt | BS92: RA100217 | BT92: F. Lindqvist | BU92: C. Dubois | BW92: Quarterly | BX92: 30/360 | BY92: 365 | BZ92: 365 | CC92: BBB- | CD92: BBB- | CE92: BB+ | CF92: BB+ | CG92: NR | CH92: 46112 | CI92: 1.2 | CJ92: 3.3 | CK92: 3.46 | CL92: OK | DA92: 0.48 | DC92: 0.85 | DD92: OK | ED92: OK | EE92: 1.05 | EI92: 1.57 | FQ92: 20266650
B93: =C93&"x"&I93 -> 61009x100217 | C93: =IF(G93="SINGLE",H93,G93) -> 61009 | D93: =_xlfn.XLOOKUP(I93,calculations!$t:$t,calculations!$s:$s) -> #VALUE! | E93: =_xlfn.XLOOKUP(I93,Mapping!$T:$T,Mapping!$Q:$Q) -> ORIO15 | F93: 46203 | G93: 61009 | H93: 61009 | I93: 100217 | J93: Orion Fibre | K93: Investor 9 Portfolio | L93: Investor 9 Portfolio | M93: Infra Debt | N93: 7412000 | O93: 7412000 | P93: USD | Q93: Loan | R93: Y | S93: L100217 | T93: Infrastructure Debt | U93: FI | V93: Finland | W93: Fibre networks | X93: CR1014 | Y93: 6.2 | Z93: EUR | AA93: 1 | AB93: N | AC93: 8156000 | AD93: 8156000 | AE93: 8156000 | AF93: 0.9088 | AG93: 7412000 | AH93: 7412000 | AI93: 744000 | AJ93: 8156000 | AK93: 7412000 | AL93: 7412000 | AN93: 4.286 | AO93: 3.914 | AP93: 3.625 | AQ93: 100 | AR93: 100 | AS93: 44221 | AT93: 48785 | AU93: 46295 | AV93: PI2014 | AW93: Helios Partners | AX93: N | AY93: Orion Fibre Finance Ltd | AZ93: Orion Fibre Finance | BA93: Finland | BB93: Helios Partners | BC93: 529900SYNTH000000014 | BI93: 8156000 | BJ93: 8156000 | BK93: Fixed | BL93: Senior Secured | BN93: 7.5 | BO93: 7.07 | BP93: N | BQ93: N | BR93: Debt | BS93: RA100217 | BT93: F. Lindqvist | BU93: B. Okoro | BW93: Semi-annual | BX93: ACT/360 | BY93: 365 | BZ93: 365 | CC93: BBB- | CD93: BBB- | CE93: BB+ | CF93: BB+ | CG93: NR | CH93: 46112 | CI93: 1.2 | CJ93: 2.65 | CK93: 2.78 | CL93: OK | DA93: 0.63 | DC93: 0.85 | DD93: OK | ED93: OK | EE93: 1.05 | EI93: 1.39 | FQ93: 29188454
B94: =C94&"x"&I94 -> 61008x100218 | C94: =IF(G94="SINGLE",H94,G94) -> 61008 | D94: =_xlfn.XLOOKUP(I94,calculations!$t:$t,calculations!$s:$s) -> #VALUE! | E94: =_xlfn.XLOOKUP(I94,Mapping!$T:$T,Mapping!$Q:$Q) -> PION16 | F94: 46203 | G94: 61008 | H94: 61008 | I94: 100218 | J94: Pioneer Gas | K94: Investor 8 Portfolio | L94: Investor 8 Portfolio | M94: Infra Debt | N94: 26924000 | O94: 28045833 | P94: EUR | Q94: Loan | R94: N | S94: L100218 | T94: Infrastructure Debt | U94: CH | V94: Switzerland | W94: Gas distribution | X94: CR1015 | Y94: 9.4 | Z94: CHF | AA94: 0.96 | AB94: Y | AC94: 29480000 | AD94: 29480000 | AE94: 30708333 | AF94: 0.9133 | AG94: 26924000 | AH94: 26924000 | AI94: 2556000 | AJ94: 29480000 | AK94: 26924000 | AL94: 26924000 | AM94: EURIBOR 6M | AN94: 4.958 | AO94: 4.225 | AP94: 6.049 | AQ94: 100 | AR94: 100 | AS94: 42161 | AT94: 47093 | AU94: 46295 | AV94: PI2015 | AW94: Silverline Transport | AX94: N | AY94: Pioneer Gas Finance Ltd | AZ94: Pioneer Gas Finance | BA94: Switzerland | BB94: Silverline Transport | BC94: 529900SYNTH000000015 | BI94: 29480000 | BJ94: 30708333 | BK94: Floating | BL94: Senior Secured | BN94: 8.1 | BO94: 2.44 | BP94: Y | BQ94: N | BR94: Debt | BS94: RA100218 | BT94: F. Lindqvist | BU94: A. Martin | BW94: Quarterly | BX94: ACT/360 | BY94: 345 | BZ94: 345 | CB94: EURIBOR | CC94: BB | CD94: BB | CE94: NR | CF94: BB- | CG94: NR | CH94: 46112 | CI94: 1.2 | CJ94: 1.62 | CK94: 1.7 | CL94: OK | DA94: 0.51 | DC94: 0.85 | DD94: OK | ED94: OK | EE94: 1.05 | EI94: 1.8 | FQ94: 56179763
B95: =C95&"x"&I95 -> 61007x100218 | C95: =IF(G95="SINGLE",H95,G95) -> 61007 | D95: =_xlfn.XLOOKUP(I95,calculations!$t:$t,calculations!$s:$s) -> #VALUE! | E95: =_xlfn.XLOOKUP(I95,Mapping!$T:$T,Mapping!$Q:$Q) -> PION16 | F95: 46203 | G95: 61007 | H95: 61007 | I95: 100218 | J95: Pioneer Gas | K95: Investor 7 Portfolio | L95: Investor 7 Portfolio | M95: Infra Debt | N95: 28444000 | O95: 29629167 | P95: GBP | Q95: Loan | R95: N | S95: L100218 | T95: Infrastructure Debt | U95: CH | V95: Switzerland | W95: Gas distribution | X95: CR1015 | Y95: 9.4 | Z95: CHF | AA95: 0.96 | AB95: Y | AC95: 31144000 | AD95: 31144000 | AE95: 32441667 | AF95: 0.9133 | AG95: 28444000 | AH95: 28444000 | AI95: 2700000 | AJ95: 31144000 | AK95: 28444000 | AL95: 28444000 | AM95: EURIBOR 6M | AN95: 3.85 | AO95: 5.755 | AP95: 3.106 | AQ95: 100 | AR95: 100 | AS95: 42161 | AT95: 47093 | AU95: 46295 | AV95: PI2015 | AW95: Silverline Transport | AX95: N | AY95: Pioneer Gas Finance Ltd | AZ95: Pioneer Gas Finance | BA95: Switzerland | BB95: Silverline Transport | BC95: 529900SYNTH000000015 | BI95: 31144000 | BJ95: 32441667 | BK95: Floating | BL95: Senior Secured | BN95: 8.1 | BO95: 2.44 | BP95: Y | BQ95: N | BR95: Debt | BS95: RA100218 | BT95: F. Lindqvist | BU95: A. Martin | BW95: Semi-annual | BX95: 30/360 | BY95: 345 | BZ95: 345 | CB95: EURIBOR | CC95: BB | CD95: BB | CE95: NR | CF95: BB- | CG95: NR | CH95: 46112 | CI95: 1.2 | CJ95: 1.22 | CK95: 1.28 | CL95: Watch | DA95: 0.77 | DC95: 0.85 | DD95: OK | ED95: OK | EE95: 1.05 | EI95: 1.52 | FQ95: 86611693
B96: =C96&"x"&I96 -> 61011x100218 | C96: =IF(G96="SINGLE",H96,G96) -> 61011 | D96: =_xlfn.XLOOKUP(I96,calculations!$t:$t,calculations!$s:$s) -> #VALUE! | E96: =_xlfn.XLOOKUP(I96,Mapping!$T:$T,Mapping!$Q:$Q) -> PION16 | F96: 46203 | G96: 61011 | H96: 61011 | I96: 100218 | J96: Pioneer Gas | K96: Investor 11 Mandate | L96: Investor 11 Mandate | M96: Infra Debt | N96: 36447000 | O96: 37965625 | P96: EUR | Q96: Loan | R96: N | S96: L100218 | T96: Infrastructure Debt | U96: CH | V96: Switzerland | W96: Gas distribution | X96: CR1015 | Y96: 9.4 | Z96: CHF | AA96: 0.96 | AB96: Y | AC96: 39906000 | AD96: 39906000 | AE96: 41568750 | AF96: 0.9133 | AG96: 36447000 | AH96: 36447000 | AI96: 3459000 | AJ96: 39906000 | AK96: 36447000 | AL96: 36447000 | AM96: EURIBOR 6M | AN96: 5.417 | AO96: 3.34 | AP96: 5.12 | AQ96: 100 | AR96: 100 | AS96: 42161 | AT96: 47093 | AU96: 46295 | AV96: PI2015 | AW96: Silverline Transport | AX96: N | AY96: Pioneer Gas Finance Ltd | AZ96: Pioneer Gas Finance | BA96: Switzerland | BB96: Silverline Transport | BC96: 529900SYNTH000000015 | BI96: 39906000 | BJ96: 41568750 | BK96: Floating | BL96: Senior Secured | BN96: 8.1 | BO96: 2.44 | BP96: Y | BQ96: N | BR96: Debt | BS96: RA100218 | BT96: F. Lindqvist | BU96: D. Schäfer | BW96: Quarterly | BX96: ACT/360 | BY96: 345 | BZ96: 345 | CB96: EURIBOR | CC96: BB | CD96: BB | CE96: NR | CF96: BB- | CG96: NR | CH96: 46112 | CI96: 1.2 | CJ96: 2.27 | CK96: 2.38 | CL96: OK | DA96: 0.8 | DC96: 0.85 | DD96: Watch | ED96: OK | EE96: 1.05 | EI96: 1.55 | FQ96: 79971840
B97: =C97&"x"&I97 -> 61004x100218 | C97: =IF(G97="SINGLE",H97,G97) -> 61004 | D97: =_xlfn.XLOOKUP(I97,calculations!$t:$t,calculations!$s:$s) -> #VALUE! | E97: =_xlfn.XLOOKUP(I97,Mapping!$T:$T,Mapping!$Q:$Q) -> PION16 | F97: 46203 | G97: 61004 | H97: 61004 | I97: 100218 | J97: Pioneer Gas | K97: Investor 4 Portfolio | L97: Investor 4 Portfolio | M97: Infra Debt | N97: 31395000 | O97: 32703125 | P97: EUR | Q97: Loan | R97: N | S97: L100218 | T97: Infrastructure Debt | U97: CH | V97: Switzerland | W97: Gas distribution | X97: CR1015 | Y97: 9.4 | Z97: CHF | AA97: 0.96 | AB97: Y | AC97: 34375000 | AD97: 34375000 | AE97: 35807292 | AF97: 0.9133 | AG97: 31395000 | AH97: 31395000 | AI97: 2980000 | AJ97: 34375000 | AK97: 31395000 | AL97: 31395000 | AM97: EURIBOR 6M | AN97: 6.316 | AO97: 2.85 | AP97: 2.784 | AQ97: 100 | AR97: 100 | AS97: 42161 | AT97: 47093 | AU97: 46295 | AV97: PI2015 | AW97: Silverline Transport | AX97: N | AY97: Pioneer Gas Finance Ltd | AZ97: Pioneer Gas Finance | BA97: Switzerland | BB97: Silverline Transport | BC97: 529900SYNTH000000015 | BI97: 34375000 | BJ97: 35807292 | BK97: Floating | BL97: Senior Secured | BN97: 8.1 | BO97: 2.44 | BP97: Y | BQ97: N | BR97: Debt | BS97: RA100218 | BT97: F. Lindqvist | BU97: D. Schäfer | BW97: Semi-annual | BX97: ACT/360 | BY97: 345 | BZ97: 345 | CB97: EURIBOR | CC97: BB | CD97: BB | CE97: NR | CF97: BB- | CG97: NR | CH97: 46112 | CI97: 1.2 | CJ97: 1.49 | CK97: 1.56 | CL97: OK | DA97: 0.71 | DC97: 0.85 | DD97: OK | ED97: OK | EE97: 1.05 | EI97: 1.78 | FQ97: 66709930
B98: =C98&"x"&I98 -> 61013x100218 | C98: =IF(G98="SINGLE",H98,G98) -> 61013 | D98: =_xlfn.XLOOKUP(I98,calculations!$t:$t,calculations!$s:$s) -> #VALUE! | E98: =_xlfn.XLOOKUP(I98,Mapping!$T:$T,Mapping!$Q:$Q) -> PION16 | F98: 46203 | G98: 61013 | H98: 61013 | I98: 100218 | J98: Pioneer Gas | K98: Investor 13 Mandate | L98: Investor 13 Mandate | M98: Infra Debt | N98: 14026000 | O98: 14610417 | P98: EUR | Q98: Loan | R98: N | S98: L100218 | T98: Infrastructure Debt | U98: CH | V98: Switzerland | W98: Gas distribution | X98: CR1015 | Y98: 9.4 | Z98: CHF | AA98: 0.96 | AB98: Y | AC98: 15357000 | AD98: 15357000 | AE98: 15996875 | AF98: 0.9133 | AG98: 14026000 | AH98: 14026000 | AI98: 1331000 | AJ98: 15357000 | AK98: 14026000 | AL98: 14026000 | AM98: EURIBOR 6M | AN98: 3.293 | AO98: 6.287 | AP98: 5.996 | AQ98: 100 | AR98: 100 | AS98: 42161 | AT98: 47093 | AU98: 46295 | AV98: PI2015 | AW98: Silverline Transport | AX98: N | AY98: Pioneer Gas Finance Ltd | AZ98: Pioneer Gas Finance | BA98: Switzerland | BB98: Silverline Transport | BC98: 529900SYNTH000000015 | BI98: 15357000 | BJ98: 15996875 | BK98: Floating | BL98: Senior Secured | BN98: 8.1 | BO98: 2.44 | BP98: Y | BQ98: N | BR98: Debt | BS98: RA100218 | BT98: F. Lindqvist | BU98: B. Okoro | BW98: Quarterly | BX98: 30/360 | BY98: 345 | BZ98: 345 | CB98: EURIBOR | CC98: BB | CD98: BB | CE98: NR | CF98: BB- | CG98: NR | CH98: 46112 | CI98: 1.2 | CJ98: 1.35 | CK98: 1.42 | CL98: OK | DA98: 0.79 | DC98: 0.85 | DD98: OK | ED98: OK | EE98: 1.05 | EI98: 1.68 | FQ98: 58812316
B99: =C99&"x"&I99 -> 61025x100218 | C99: =IF(G99="SINGLE",H99,G99) -> 61025 | D99: =_xlfn.XLOOKUP(I99,calculations!$t:$t,calculations!$s:$s) -> #VALUE! | E99: =_xlfn.XLOOKUP(I99,Mapping!$T:$T,Mapping!$Q:$Q) -> PION16 | F99: 46203 | G99: 61025 | H99: 61025 | I99: 100218 | J99: Pioneer Gas | K99: Fund 5 Fund | L99: Fund 5 Fund | M99: Infra Debt | N99: 13666000 | O99: 14235417 | P99: EUR | Q99: Loan | R99: N | S99: L100218 | T99: Infrastructure Debt | U99: CH | V99: Switzerland | W99: Gas distribution | X99: CR1015 | Y99: 9.4 | Z99: CHF | AA99: 0.96 | AB99: Y | AC99: 14963000 | AD99: 14963000 | AE99: 15586458 | AF99: 0.9133 | AG99: 13666000 | AH99: 13666000 | AI99: 1297000 | AJ99: 14963000 | AK99: 13666000 | AL99: 13666000 | AM99: EURIBOR 6M | AN99: 3.62 | AO99: 4.733 | AP99: 5.266 | AQ99: 100 | AR99: 100 | AS99: 42161 | AT99: 47093 | AU99: 46295 | AV99: PI2015 | AW99: Silverline Transport | AX99: N | AY99: Pioneer Gas Finance Ltd | AZ99: Pioneer Gas Finance | BA99: Switzerland | BB99: Silverline Transport | BC99: 529900SYNTH000000015 | BI99: 14963000 | BJ99: 15586458 | BK99: Floating | BL99: Senior Secured | BN99: 8.1 | BO99: 2.44 | BP99: Y | BQ99: N | BR99: Debt | BS99: RA100218 | BT99: F. Lindqvist | BU99: A. Martin | BW99: Quarterly | BX99: ACT/360 | BY99: 345 | BZ99: 345 | CB99: EURIBOR | CC99: BB | CD99: BB | CE99: NR | CF99: BB- | CG99: NR | CH99: 46112 | CI99: 1.2 | CJ99: 3.09 | CK99: 3.24 | CL99: OK | DA99: 0.6 | DC99: 0.85 | DD99: OK | ED99: OK | EE99: 1.05 | EI99: 1.62 | FQ99: 67764310
B100: =C100&"x"&I100 -> 61008x100219 | C100: =IF(G100="SINGLE",H100,G100) -> 61008 | D100: =_xlfn.XLOOKUP(I100,calculations!$t:$t,calculations!$s:$s) -> #VALUE! | E100: =_xlfn.XLOOKUP(I100,Mapping!$T:$T,Mapping!$Q:$Q) -> QUAR17 | F100: 46203 | G100: 61008 | H100: 61008 | I100: 100219 | J100: Quartz Battery | K100: Investor 8 Portfolio | L100: Investor 8 Portfolio | M100: Infra Debt | N100: 28308000 | O100: 28308000 | P100: EUR | Q100: Private Placement Note | R100: Y | S100: L100219 | T100: Infrastructure Debt | U100: DE | V100: Germany | W100: Battery storage | X100: CR1016 | Y100: 9.2 | Z100: EUR | AA100: 1 | AB100: N | AC100: 29187000 | AD100: 29187000 | AE100: 29187000 | AF100: 0.9699 | AG100: 28308000 | AH100: 28308000 | AI100: 879000 | AJ100: 29187000 | AK100: 28308000 | AL100: 28308000 | AM100: EURIBOR 6M | AN100: 4.623 | AO100: 3.288 | AP100: 3.419 | AQ100: 100 | AR100: 100 | AS100: 43479 | AT100: 50235 | AU100: 46295 | AV100: PI2016 | AW100: Boreal Energy | AX100: N | AY100: Quartz Battery Finance Ltd | AZ100: Quartz Battery Finance | BA100: Germany | BB100: Boreal Energy | BC100: 529900SYNTH000000016 | BI100: 29187000 | BJ100: 29187000 | BK100: Floating | BL100: Senior Secured | BN100: 11.1 | BO100: 11.04 | BP100: Y | BQ100: N | BR100: Debt | BS100: RA100219 | BT100: B. Okoro | BU100: A. Martin | BW100: Quarterly | BX100: ACT/360 | BY100: 65 | BZ100: 65 | CB100: EURIBOR | CC100: AA- | CD100: AA- | CE100: NR | CF100: NR | CG100: NR | CH100: 46112 | CI100: 1.2 | CJ100: 1.68 | CK100: 1.76 | CL100: OK | DA100: 0.5 | DC100: 0.85 | DD100: OK | ED100: OK | EE100: 1.05 | EI100: 1.6 | FQ100: 35621427
B101: =C101&"x"&I101 -> 61019x100219 | C101: =IF(G101="SINGLE",H101,G101) -> 61019 | D101: =_xlfn.XLOOKUP(I101,calculations!$t:$t,calculations!$s:$s) -> #VALUE! | E101: =_xlfn.XLOOKUP(I101,Mapping!$T:$T,Mapping!$Q:$Q) -> QUAR17 | F101: 46203 | G101: 61019 | H101: 61019 | I101: 100219 | J101: Quartz Battery | K101: Investor 19 Mandate | L101: Investor 19 Mandate | M101: Infra Debt | N101: 31564000 | O101: 31564000 | P101: EUR | Q101: Private Placement Note | R101: Y | S101: L100219 | T101: Infrastructure Debt | U101: DE | V101: Germany | W101: Battery storage | X101: CR1016 | Y101: 9.2 | Z101: EUR | AA101: 1 | AB101: N | AC101: 32544000 | AD101: 32544000 | AE101: 32544000 | AF101: 0.9699 | AG101: 31564000 | AH101: 31564000 | AI101: 980000 | AJ101: 32544000 | AK101: 31564000 | AL101: 31564000 | AM101: EURIBOR 6M | AN101: 5.262 | AO101: 4.522 | AP101: 3.655 | AQ101: 100 | AR101: 100 | AS101: 43479 | AT101: 50235 | AU101: 46295 | AV101: PI2016 | AW101: Boreal Energy | AX101: N | AY101: Quartz Battery Finance Ltd | AZ101: Quartz Battery Finance | BA101: Germany | BB101: Boreal Energy | BC101: 529900SYNTH000000016 | BI101: 32544000 | BJ101: 32544000 | BK101: Floating | BL101: Senior Secured | BN101: 11.1 | BO101: 11.04 | BP101: Y | BQ101: N | BR101: Debt | BS101: RA100219 | BT101: B. Okoro | BU101: E. Rossi | BW101: Quarterly | BX101: 30/360 | BY101: 65 | BZ101: 65 | CB101: EURIBOR | CC101: AA- | CD101: AA- | CE101: NR | CF101: NR | CG101: NR | CH101: 46112 | CI101: 1.2 | CJ101: 1.29 | CK101: 1.35 | CL101: Watch | DA101: 0.6 | DC101: 0.85 | DD101: OK | ED101: OK | EE101: 1.05 | EI101: 1.8 | FQ101: 37503879
B102: =C102&"x"&I102 -> 61011x100219 | C102: =IF(G102="SINGLE",H102,G102) -> 61011 | D102: =_xlfn.XLOOKUP(I102,calculations!$t:$t,calculations!$s:$s) -> #VALUE! | E102: =_xlfn.XLOOKUP(I102,Mapping!$T:$T,Mapping!$Q:$Q) -> QUAR17 | F102: 46203 | G102: 61011 | H102: 61011 | I102: 100219 | J102: Quartz Battery | K102: Investor 11 Mandate | L102: Investor 11 Mandate | M102: Infra Debt | N102: 35906000 | O102: 35906000 | P102: EUR | Q102: Private Placement Note | R102: Y | S102: L100219 | T102: Infrastructure Debt | U102: DE | V102: Germany | W102: Battery storage | X102: CR1016 | Y102: 9.2 | Z102: EUR | AA102: 1 | AB102: N | AC102: 37021000 | AD102: 37021000 | AE102: 37021000 | AF102: 0.9699 | AG102: 35906000 | AH102: 35906000 | AI102: 1115000 | AJ102: 37021000 | AK102: 35906000 | AL102: 35906000 | AM102: EURIBOR 6M | AN102: 5.376 | AO102: 4.937 | AP102: 5.923 | AQ102: 100 | AR102: 100 | AS102: 43479 | AT102: 50235 | AU102: 46295 | AV102: PI2016 | AW102: Boreal Energy | AX102: N | AY102: Quartz Battery Finance Ltd | AZ102: Quartz Battery Finance | BA102: Germany | BB102: Boreal Energy | BC102: 529900SYNTH000000016 | BI102: 37021000 | BJ102: 37021000 | BK102: Floating | BL102: Senior Secured | BN102: 11.1 | BO102: 11.04 | BP102: Y | BQ102: N | BR102: Debt | BS102: RA100219 | BT102: B. Okoro | BU102: B. Okoro | BW102: Quarterly | BX102: ACT/360 | BY102: 65 | BZ102: 65 | CB102: EURIBOR | CC102: AA- | CD102: AA- | CE102: NR | CF102: NR | CG102: NR | CH102: 46112 | CI102: 1.2 | CJ102: 1.99 | CK102: 2.09 | CL102: OK | DA102: 0.61 | DC102: 0.85 | DD102: OK | ED102: OK | EE102: 1.05 | EI102: 1.58 | FQ102: 38670006
B103: =C103&"x"&I103 -> 61015x100219 | C103: =IF(G103="SINGLE",H103,G103) -> 61015 | D103: =_xlfn.XLOOKUP(I103,calculations!$t:$t,calculations!$s:$s) -> #VALUE! | E103: =_xlfn.XLOOKUP(I103,Mapping!$T:$T,Mapping!$Q:$Q) -> QUAR17 | F103: 46203 | G103: 61015 | H103: 61015 | I103: 100219 | J103: Quartz Battery | K103: Investor 15 Mandate | L103: Investor 15 Mandate | M103: Infra Debt | N103: 22499000 | O103: 22499000 | P103: EUR | Q103: Private Placement Note | R103: Y | S103: L100219 | T103: Infrastructure Debt | U103: DE | V103: Germany | W103: Battery storage | X103: CR1016 | Y103: 9.2 | Z103: EUR | AA103: 1 | AB103: N | AC103: 23197000 | AD103: 23197000 | AE103: 23197000 | AF103: 0.9699 | AG103: 22499000 | AH103: 22499000 | AI103: 698000 | AJ103: 23197000 | AK103: 22499000 | AL103: 22499000 | AM103: EURIBOR 6M | AN103: 6.337 | AO103: 5.467 | AP103: 5.964 | AQ103: 100 | AR103: 100 | AS103: 43479 | AT103: 50235 | AU103: 46295 | AV103: PI2016 | AW103: Boreal Energy | AX103: N | AY103: Quartz Battery Finance Ltd | AZ103: Quartz Battery Finance | BA103: Germany | BB103: Boreal Energy | BC103: 529900SYNTH000000016 | BI103: 23197000 | BJ103: 23197000 | BK103: Floating | BL103: Senior Secured | BN103: 11.1 | BO103: 11.04 | BP103: Y | BQ103: N | BR103: Debt | BS103: RA100219 | BT103: B. Okoro | BU103: E. Rossi | BW103: Quarterly | BX103: 30/360 | BY103: 65 | BZ103: 65 | CB103: EURIBOR | CC103: AA- | CD103: AA- | CE103: NR | CF103: NR | CG103: NR | CH103: 46112 | CI103: 1.2 | CJ103: 2.57 | CK103: 2.7 | CL103: OK | DA103: 0.66 | DC103: 0.85 | DD103: OK | ED103: OK | EE103: 1.05 | EI103: 1.65 | FQ103: 43643299
B104: =C104&"x"&I104 -> 61014x100219 | C104: =IF(G104="SINGLE",H104,G104) -> 61014 | D104: =_xlfn.XLOOKUP(I104,calculations!$t:$t,calculations!$s:$s) -> #VALUE! | E104: =_xlfn.XLOOKUP(I104,Mapping!$T:$T,Mapping!$Q:$Q) -> QUAR17 | F104: 46203 | G104: 61014 | H104: 61014 | I104: 100219 | J104: Quartz Battery | K104: Investor 14 Mandate | L104: Investor 14 Mandate | M104: Infra Debt | N104: 34784000 | O104: 34784000 | P104: EUR | Q104: Private Placement Note | R104: Y | S104: L100219 | T104: Infrastructure Debt | U104: DE | V104: Germany | W104: Battery storage | X104: CR1016 | Y104: 9.2 | Z104: EUR | AA104: 1 | AB104: N | AC104: 35864000 | AD104: 35864000 | AE104: 35864000 | AF104: 0.9699 | AG104: 34784000 | AH104: 34784000 | AI104: 1080000 | AJ104: 35864000 | AK104: 34784000 | AL104: 34784000 | AM104: EURIBOR 6M | AN104: 3.737 | AO104: 4.267 | AP104: 6.356 | AQ104: 100 | AR104: 100 | AS104: 43479 | AT104: 50235 | AU104: 46295 | AV104: PI2016 | AW104: Boreal Energy | AX104: N | AY104: Quartz Battery Finance Ltd | AZ104: Quartz Battery Finance | BA104: Germany | BB104: Boreal Energy | BC104: 529900SYNTH000000016 | BI104: 35864000 | BJ104: 35864000 | BK104: Floating | BL104: Senior Secured | BN104: 11.1 | BO104: 11.04 | BP104: Y | BQ104: N | BR104: Debt | BS104: RA100219 | BT104: B. Okoro | BU104: A. Martin | BW104: Quarterly | BX104: 30/360 | BY104: 65 | BZ104: 65 | CB104: EURIBOR | CC104: AA- | CD104: AA- | CE104: NR | CF104: NR | CG104: NR | CH104: 46112 | CI104: 1.2 | CJ104: 2.25 | CK104: 2.36 | CL104: OK | DA104: 0.47 | DC104: 0.85 | DD104: OK | ED104: OK | EE104: 1.05 | EI104: 1.6 | FQ104: 41332942
B105: =C105&"x"&I105 -> 61008x100220 | C105: =IF(G105="SINGLE",H105,G105) -> 61008 | D105: =_xlfn.XLOOKUP(I105,calculations!$t:$t,calculations!$s:$s) -> #VALUE! | E105: =_xlfn.XLOOKUP(I105,Mapping!$T:$T,Mapping!$Q:$Q) -> RIDG18 | F105: 46203 | G105: 61008 | H105: 61008 | I105: 100220 | J105: Ridge Student | K105: Investor 8 Portfolio | L105: Investor 8 Portfolio | M105: Infra Debt | N105: 9605000 | O105: 850000 | P105: EUR | Q105: Loan | R105: N | S105: L100220 | T105: Infrastructure Debt | U105: SE | V105: Sweden | W105: Student accommodation | X105: CR1017 | Y105: 9.6 | Z105: SEK | AA105: 11.3 | AB105: Y | AC105: 10385000 | AD105: 10385000 | AE105: 919026.55 | AF105: 0.9249 | AG105: 9605000 | AH105: 9605000 | AI105: 780000 | AJ105: 10385000 | AK105: 9605000 | AL105: 9605000 | AM105: EURIBOR 6M | AN105: 6.141 | AO105: 4.935 | AP105: 4.993 | AQ105: 100 | AR105: 100 | AS105: 44201 | AT105: 50045 | AU105: 46295 | AV105: PI2017 | AW105: Northwind Capital | AX105: N | AY105: Ridge Student Finance Ltd | AZ105: Ridge Student Finance | BA105: Sweden | BB105: Northwind Capital | BC105: 529900SYNTH000000017 | BI105: 10385000 | BJ105: 919026.55 | BK105: Floating | BL105: Senior Secured | BN105: 9.6 | BO105: 10.52 | BP105: Y | BQ105: N | BR105: Debt | BS105: RA100220 | BT105: F. Lindqvist | BU105: B. Okoro | BW105: Semi-annual | BX105: 30/360 | BY105: 190 | BZ105: 190 | CB105: EURIBOR | CC105: A | CD105: A | CE105: NR | CF105: NR | CG105: NR | CH105: 46112 | CI105: 1.2 | CJ105: 2.7 | CK105: 2.84 | CL105: OK | DA105: 0.63 | DC105: 0.85 | DD105: OK | ED105: OK | EE105: 1.05 | EI105: 1.9 | FQ105: 15878094
... B113: =C113&"x"&I113 -> 61010x100222 | C113: =IF(G113="SINGLE",H113,G113) -> 61010 | D113: =_xlfn.XLOOKUP(I113,calculations!$t:$t,calculations!$s:$s) -> #VALUE! | E113: =_xlfn.XLOOKUP(I113,Mapping!$T:$T,Mapping!$Q:$Q) -> TIDA20 | F113: 46203 | G113: 61010 | H113: 61010 | I113: 100222 | J113: Tidal Toll | K113: Investor 10 Portfolio | L113: Investor 10 Portfolio | M113: Infra Debt | N113: 73296000 | O113: 73296000 | P113: EUR | Q113: Loan | R113: Y | S113: L100222 | T113: Infrastructure Debt | U113: FR | V113: France | W113: Toll roads | X113: CR1019 | Y113: 7.3 | Z113: EUR | AA113: 1 | AB113: N | AC113: 80554000 | AD113: 80554000 | AE113: 80554000 | AF113: 0.9099 | AG113: 73296000 | AH113: 73296000 | AI113: 7258000 | AJ113: 80554000 | AK113: 73296000 | AL113: 73296000 | AM113: EURIBOR 6M | AN113: 5.48 | AO113: 5.52 | AP113: 6.494 | AQ113: 100 | AR113: 100 | AS113: 44292 | AT113: 49588 | AU113: 46295 | AV113: PI2019 | AW113: Helios Partners | AX113: N | AY113: Tidal Toll Finance Ltd | AZ113: Tidal Toll Finance | BA113: France | BB113: Helios Partners | BC113: 529900SYNTH000000019 | BI113: 80554000 | BJ113: 80554000 | BK113: Floating | BL113: Senior Secured | BN113: 8.7 | BO113: 9.27 | BP113: Y | BQ113: N | BR113: Debt | BS113: RA100222 | BT113: C. Dubois | BU113: D. Schäfer | BW113: Quarterly | BX113: ACT/360 | BY113: 180 | BZ113: 180 | CB113: EURIBOR | CC113: BBB- | CD113: BBB- | CE113: NR | CF113: NR | CG113: NR | CH113: 46112 | CI113: 1.2 | CJ113: 2.79 | CK113: 2.93 | CL113: OK | DA113: 0.64 | DC113: 0.85 | DD113: OK | ED113: Watch | EE113: 1.05 | EI113: 1.15 | FQ113: 41285331
B114: =C114&"x"&I114 -> 61012x100223 | C114: =IF(G114="SINGLE",H114,G114) -> 61012 | D114: =_xlfn.XLOOKUP(I114,calculations!$t:$t,calculations!$s:$s) -> #VALUE! | E114: =_xlfn.XLOOKUP(I114,Mapping!$T:$T,Mapping!$Q:$Q) -> UMBR21 | F114: 46203 | G114: 61012 | H114: 61012 | I114: 100223 | J114: Umbra Data | K114: Investor 12 Mandate | L114: Investor 12 Mandate | M114: Infra Debt | N114: 27526000 | O114: 28672917 | P114: GBP | Q114: Loan | R114: N | S114: L100223 | T114: Infrastructure Debt | U114: CH | V114: Switzerland | W114: Data centres | X114: CR1020 | Y114: 5.6 | Z114: CHF | AA114: 0.96 | AB114: Y | AC114: 43445000 | AD114: 43445000 | AE114: 45255208 | AF114: 0.6336 | AG114: 27526000 | AH114: 27526000 | AI114: 15919000 | AJ114: 43445000 | AK114: 27526000 | AL114: 27526000 | AN114: 5.542 | AO114: 3.978 | AP114: 4.096 | AQ114: 100 | AR114: 100 | AS114: 43888 | AT114: 46992 | AU114: 46295 | AV114: PI2020 | AW114: Helios Partners | AX114: N | AY114: Umbra Data Finance Ltd | AZ114: Umbra Data Finance | BA114: Switzerland | BB114: Helios Partners | BC114: 529900SYNTH000000020 | BI114: 43445000 | BJ114: 45255208 | BK114: Fixed | BL114: Senior Secured | BN114: 5.1 | BO114: 2.16 | BP114: N | BQ114: N | BR114: Debt | BS114: RA100223 | BT114: A. Martin | BU114: B. Okoro | BW114: Semi-annual | BX114: ACT/360 | BY114: 170 | BZ114: 170 | CC114: BBB- | CD114: BBB- | CE114: BB+ | CF114: NR | CG114: Baa2 | CH114: 46112 | CI114: 1.2 | CJ114: 3.48 | CK114: 3.65 | CL114: OK | DA114: 0.84 | DC114: 0.85 | DD114: Watch | ED114: Watch | EE114: 1.05 | EI114: 1.19 | FQ114: 54270954
B115: =C115&"x"&I115 -> 61015x100223 | C115: =IF(G115="SINGLE",H115,G115) -> 61015 | D115: =_xlfn.XLOOKUP(I115,calculations!$t:$t,calculations!$s:$s) -> #VALUE! | E115: =_xlfn.XLOOKUP(I115,Mapping!$T:$T,Mapping!$Q:$Q) -> UMBR21 | F115: 46203 | G115: 61015 | H115: 61015 | I115: 100223 | J115: Umbra Data | K115: Investor 15 Mandate | L115: Investor 15 Mandate | M115: Infra Debt | N115: 12194000 | O115: 12702083 | P115: EUR | Q115: Loan | R115: N | S115: L100223 | T115: Infrastructure Debt | U115: CH | V115: Switzerland | W115: Data centres | X115: CR1020 | Y115: 5.6 | Z115: CHF | AA115: 0.96 | AB115: Y | AC115: 19246000 | AD115: 19246000 | AE115: 20047917 | AF115: 0.6336 | AG115: 12194000 | AH115: 12194000 | AI115: 7052000 | AJ115: 19246000 | AK115: 12194000 | AL115: 12194000 | AN115: 3.382 | AO115: 3.558 | AP115: 2.562 | AQ115: 100 | AR115: 100 | AS115: 43888 | AT115: 46992 | AU115: 46295 | AV115: PI2020 | AW115: Helios Partners | AX115: N | AY115: Umbra Data Finance Ltd | AZ115: Umbra Data Finance | BA115: Switzerland | BB115: Helios Partners | BC115: 529900SYNTH000000020 | BI115: 19246000 | BJ115: 20047917 | BK115: Fixed | BL115: Senior Secured | BN115: 5.1 | BO115: 2.16 | BP115: N | BQ115: N | BR115: Debt | BS115: RA100223 | BT115: A. Martin | BU115: A. Martin | BW115: Semi-annual | BX115: ACT/360 | BY115: 170 | BZ115: 170 | CC115: BBB- | CD115: BBB- | CE115: BB+ | CF115: NR | CG115: Baa2 | CH115: 46112 | CI115: 1.2 | CJ115: 2.72 | CK115: 2.86 | CL115: OK | DA115: 0.7 | DC115: 0.85 | DD115: OK | ED115: Watch | EE115: 1.05 | EI115: 1.13 | FQ115: 58066350
B116: =C116&"x"&I116 -> 61014x100223 | C116: =IF(G116="SINGLE",H116,G116) -> 61014 | D116: =_xlfn.XLOOKUP(I116,calculations!$t:$t,calculations!$s:$s) -> #VALUE! | E116: =_xlfn.XLOOKUP(I116,Mapping!$T:$T,Mapping!$Q:$Q) -> UMBR21 | F116: 46203 | G116: 61014 | H116: 61014 | I116: 100223 | J116: Umbra Data | K116: Investor 14 Mandate | L116: Investor 14 Mandate | M116: Infra Debt | N116: 22308000 | O116: 23237500 | P116: EUR | Q116: Loan | R116: N | S116: L100223 | T116: Infrastructure Debt | U116: CH | V116: Switzerland | W116: Data centres | X116: CR1020 | Y116: 5.6 | Z116: CHF | AA116: 0.96 | AB116: Y | AC116: 35209000 | AD116: 35209000 | AE116: 36676042 | AF116: 0.6336 | AG116: 22308000 | AH116: 22308000 | AI116: 12901000 | AJ116: 35209000 | AK116: 22308000 | AL116: 22308000 | AN116: 4.991 | AO116: 3.697 | AP116: 5.67 | AQ116: 100 | AR116: 100 | AS116: 43888 | AT116: 46992 | AU116: 46295 | AV116: PI2020 | AW116: Helios Partners | AX116: N | AY116: Umbra Data Finance Ltd | AZ116: Umbra Data Finance | BA116: Switzerland | BB116: Helios Partners | BC116: 529900SYNTH000000020 | BI116: 35209000 | BJ116: 36676042 | BK116: Fixed | BL116: Senior Secured | BN116: 5.1 | BO116: 2.16 | BP116: N | BQ116: N | BR116: Debt | BS116: RA100223 | BT116: A. Martin | BU116: B. Okoro | BW116: Semi-annual | BX116: ACT/360 | BY116: 170 | BZ116: 170 | CC116: BBB- | CD116: BBB- | CE116: BB+ | CF116: NR | CG116: Baa2 | CH116: 46112 | CI116: 1.2 | CJ116: 1.42 | CK116: 1.49 | CL116: OK | DA116: 0.64 | DC116: 0.85 | DD116: OK | ED116: OK | EE116: 1.05 | EI116: 1.62 | FQ116: 53603706
B117: =C117&"x"&I117 -> 61021x100223 | C117: =IF(G117="SINGLE",H117,G117) -> 61021 | D117: =_xlfn.XLOOKUP(I117,calculations!$t:$t,calculations!$s:$s) -> #VALUE! | E117: =_xlfn.XLOOKUP(I117,Mapping!$T:$T,Mapping!$Q:$Q) -> UMBR21 | F117: 46203 | G117: 61021 | H117: 61021 | I117: 100223 | J117: Umbra Data | K117: Fund 1 Fund | L117: Fund 1 Fund | M117: Infra Debt | N117: 17764000 | O117: 18504167 | P117: EUR | Q117: Loan | R117: N | S117: L100223 | T117: Infrastructure Debt | U117: CH | V117: Switzerland | W117: Data centres | X117: CR1020 | Y117: 5.6 | Z117: CHF | AA117: 0.96 | AB117: Y | AC117: 28037000 | AD117: 28037000 | AE117: 29205208 | AF117: 0.6336 | AG117: 17764000 | AH117: 17764000 | AI117: 10273000 | AJ117: 28037000 | AK117: 17764000 | AL117: 17764000 | AN117: 4.29 | AO117: 2.854 | AP117: 4.372 | AQ117: 100 | AR117: 100 | AS117: 43888 | AT117: 46992 | AU117: 46295 | AV117: PI2020 | AW117: Helios Partners | AX117: N | AY117: Umbra Data Finance Ltd | AZ117: Umbra Data Finance | BA117: Switzerland | BB117: Helios Partners | BC117: 529900SYNTH000000020 | BI117: 28037000 | BJ117: 29205208 | BK117: Fixed | BL117: Senior Secured | BN117: 5.1 | BO117: 2.16 | BP117: N | BQ117: N | BR117: Debt | BS117: RA100223 | BT117: A. Martin | BU117: D. Schäfer | BW117: Quarterly | BX117: ACT/360 | BY117: 170 | BZ117: 170 | CC117: BBB- | CD117: BBB- | CE117: BB+ | CF117: NR | CG117: Baa2 | CH117: 46112 | CI117: 1.2 | CJ117: 2.59 | CK117: 2.72 | CL117: OK | DA117: 0.76 | DC117: 0.85 | DD117: OK | ED117: OK | EE117: 1.05 | EI117: 1.41 | FQ117: 56294768
B118: =C118&"x"&I118 -> 61007x100223 | C118: =IF(G118="SINGLE",H118,G118) -> 61007 | D118: =_xlfn.XLOOKUP(I118,calculations!$t:$t,calculations!$s:$s) -> #VALUE! | E118: =_xlfn.XLOOKUP(I118,Mapping!$T:$T,Mapping!$Q:$Q) -> UMBR21 | F118: 46203 | G118: 61007 | H118: 61007 | I118: 100223 | J118: Umbra Data | K118: Investor 7 Portfolio | L118: Investor 7 Portfolio | M118: Infra Debt | N118: 8688000 | O118: 9050000 | P118: GBP | Q118: Loan | R118: N | S118: L100223 | T118: Infrastructure Debt | U118: CH | V118: Switzerland | W118: Data centres | X118: CR1020 | Y118: 5.6 | Z118: CHF | AA118: 0.96 | AB118: Y | AC118: 13713000 | AD118: 13713000 | AE118: 14284375 | AF118: 0.6336 | AG118: 8688000 | AH118: 8688000 | AI118: 5025000 | AJ118: 13713000 | AK118: 8688000 | AL118: 8688000 | AN118: 3.172 | AO118: 3.594 | AP118: 4.384 | AQ118: 100 | AR118: 100 | AS118: 43888 | AT118: 46992 | AU118: 46295 | AV118: PI2020 | AW118: Helios Partners | AX118: N | AY118: Umbra Data Finance Ltd | AZ118: Umbra Data Finance | BA118: Switzerland | BB118: Helios Partners | BC118: 529900SYNTH000000020 | BI118: 13713000 | BJ118: 14284375 | BK118: Fixed | BL118: Senior Secured | BN118: 5.1 | BO118: 2.16 | BP118: N | BQ118: N | BR118: Debt | BS118: RA100223 | BT118: A. Martin | BU118: F. Lindqvist | BW118: Semi-annual | BX118: ACT/360 | BY118: 170 | BZ118: 170 | CC118: BBB- | CD118: BBB- | CE118: BB+ | CF118: NR | CG118: Baa2 | CH118: 46112 | CI118: 1.2 | CJ118: 1.66 | CK118: 1.74 | CL118: OK | DA118: 0.51 | DC118: 0.85 | DD118: OK | ED118: OK | EE118: 1.05 | EI118: 1.3 | FQ118: 55899632
B119: =C119&"x"&I119 -> 61005x100223 | C119: =IF(G119="SINGLE",H119,G119) -> 61005 | D119: =_xlfn.XLOOKUP(I119,calculations!$t:$t,calculations!$s:$s) -> #VALUE! | E119: =_xlfn.XLOOKUP(I119,Mapping!$T:$T,Mapping!$Q:$Q) -> UMBR21 | F119: 46203 | G119: 61005 | H119: 61005 | I119: 100223 | J119: Umbra Data | K119: Investor 5 Portfolio | L119: Investor 5 Portfolio | M119: Infra Debt | N119: 25831000 | O119: 26907292 | P119: EUR | Q119: Loan | R119: N | S119: L100223 | T119: Infrastructure Debt | U119: CH | V119: Switzerland | W119: Data centres | X119: CR1020 | Y119: 5.6 | Z119: CHF | AA119: 0.96 | AB119: Y | AC119: 40770000 | AD119: 40770000 | AE119: 42468750 | AF119: 0.6336 | AG119: 25831000 | AH119: 25831000 | AI119: 14939000 | AJ119: 40770000 | AK119: 25831000 | AL119: 25831000 | AN119: 2.949 | AO119: 4.413 | AP119: 6.362 | AQ119: 100 | AR119: 100 | AS119: 43888 | AT119: 46992 | AU119: 46295 | AV119: PI2020 | AW119: Helios Partners | AX119: N | AY119: Umbra Data Finance Ltd | AZ119: Umbra Data Finance | BA119: Switzerland | BB119: Helios Partners | BC119: 529900SYNTH000000020 | BI119: 40770000 | BJ119: 42468750 | BK119: Fixed | BL119: Senior Secured | BN119: 5.1 | BO119: 2.16 | BP119: N | BQ119: N | BR119: Debt | BS119: RA100223 | BT119: A. Martin | BU119: E. Rossi | BW119: Quarterly | BX119: 30/360 | BY119: 170 | BZ119: 170 | CC119: BBB- | CD119: BBB- | CE119: BB+ | CF119: NR | CG119: Baa2 | CH119: 46112 | CI119: 1.2 | CJ119: 1.9 | CK119: 1.99 | CL119: OK | DA119: 0.45 | DC119: 0.85 | DD119: OK | ED119: OK | EE119: 1.05 | EI119: 1.83 | FQ119: 72088675
B120: =C120&"x"&I120 -> 61016x100224 | C120: =IF(G120="SINGLE",H120,G120) -> 61016 | D120: =_xlfn.XLOOKUP(I120,calculations!$t:$t,calculations!$s:$s) -> #VALUE! | E120: =_xlfn.XLOOKUP(I120,Mapping!$T:$T,Mapping!$Q:$Q) -> VERT22 | F120: 46203 | G120: 61016 | H120: 61016 | I120: 100224 | J120: Vertex Electricity | K120: Investor 16 Mandate | L120: Investor 16 Mandate | M120: Infra Debt | N120: 61647000 | O120: 61647000 | P120: EUR | Q120: Loan | R120: Y | S120: L100224 | T120: Infrastructure Debt | U120: ES | V120: Spain | W120: Electricity networks | X120: CR1021 | Y120: 5.3 | Z120: EUR | AA120: 1 | AB120: N | AC120: 65981000 | AD120: 65981000 | AE120: 65981000 | AF120: 0.9343 | AG120: 61647000 | AH120: 61647000 | AI120: 4334000 | AJ120: 65981000 | AK120: 61647000 | AL120: 61647000 | AN120: 2.957 | AO120: 3.223 | AP120: 3.419 | AQ120: 100 | AR120: 100 | AS120: 44097 | AT120: 47749 | AU120: 46295 | AV120: PI2021 | AW120: Aquila Utilities | AX120: N | AY120: Vertex Electricity Finance Ltd | AZ120: Vertex Electricity Finance | BA120: Spain | BB120: Aquila Utilities | BC120: 529900SYNTH000000021 | BI120: 65981000 | BJ120: 65981000 | BK120: Fixed | BL120: Senior Secured | BN120: 6 | BO120: 4.23 | BP120: N | BQ120: Y | BR120: Debt | BS120: RA100224 | BT120: A. Martin | BU120: D. Schäfer | BW120: Quarterly | BX120: 30/360 | BY120: 125 | BZ120: 125 | CC120: AA- | CD120: AA- | CE120: NR | CF120: NR | CG120: NR | CH120: 46112 | CI120: 1.2 | CJ120: 1.32 | CK120: 1.39 | CL120: OK | DA120: 0.79 | DC120: 0.85 | DD120: OK | ED120: OK | EE120: 1.05 | EI120: 1.33 | FQ120: 53667969
B121: =C121&"x"&I121 -> 61021x100224 | C121: =IF(G121="SINGLE",H121,G121) -> 61021 | D121: =_xlfn.XLOOKUP(I121,calculations!$t:$t,calculations!$s:$s) -> #VALUE! | E121: =_xlfn.XLOOKUP(I121,Mapping!$T:$T,Mapping!$Q:$Q) -> VERT22 | F121: 46203 | G121: 61021 | H121: 61021 | I121: 100224 | J121: Vertex Electricity | K121: Fund 1 Fund | L121: Fund 1 Fund | M121: Infra Debt | N121: 22316000 | O121: 22316000 | P121: EUR | Q121: Loan | R121: Y | S121: L100224 | T121: Infrastructure Debt | U121: ES | V121: Spain | W121: Electricity networks | X121: CR1021 | Y121: 5.3 | Z121: EUR | AA121: 1 | AB121: N | AC121: 23885000 | AD121: 23885000 | AE121: 23885000 | AF121: 0.9343 | AG121: 22316000 | AH121: 22316000 | AI121: 1569000 | AJ121: 23885000 | AK121: 22316000 | AL121: 22316000 | AN121: 3.1 | AO121: 5.331 | AP121: 3.927 | AQ121: 100 | AR121: 100 | AS121: 44097 | AT121: 47749 | AU121: 46295 | AV121: PI2021 | AW121: Aquila Utilities | AX121: N | AY121: Vertex Electricity Finance Ltd | AZ121: Vertex Electricity Finance | BA121: Spain | BB121: Aquila Utilities | BC121: 529900SYNTH000000021 | BI121: 23885000 | BJ121: 23885000 | BK121: Fixed | BL121: Senior Secured | BN121: 6 | BO121: 4.23 | BP121: N | BQ121: Y | BR121: Debt | BS121: RA100224 | BT121: A. Martin | BU121: F. Lindqvist | BW121: Semi-annual | BX121: 30/360 | BY121: 125 | BZ121: 125 | CC121: AA- | CD121: AA- | CE121: NR | CF121: NR | CG121: NR | CH121: 46112 | CI121: 1.2 | CJ121: 2.92 | CK121: 3.07 | CL121: OK | DA121: 0.61 | DC121: 0.85 | DD121: OK | ED121: OK | EE121: 1.05 | EI121: 1.46 | FQ121: 34039285
B122: =C122&"x"&I122 -> 61006x100224 | C122: =IF(G122="SINGLE",H122,G122) -> 61006 | D122: =_xlfn.XLOOKUP(I122,calculations!$t:$t,calculations!$s:$s) -> #VALUE! | E122: =_xlfn.XLOOKUP(I122,Mapping!$T:$T,Mapping!$Q:$Q) -> VERT22 | F122: 46203 | G122: 61006 | H122: 61006 | I122: 100224 | J122: Vertex Electricity | K122: Investor 6 Portfolio | L122: Investor 6 Portfolio | M122: Infra Debt | N122: 53533000 | O122: 53533000 | P122: CHF | Q122: Loan | R122: Y | S122: L100224 | T122: Infrastructure Debt | U122: ES | V122: Spain | W122: Electricity networks | X122: CR1021 | Y122: 5.3 | Z122: EUR | AA122: 1 | AB122: N | AC122: 57297000 | AD122: 57297000 | AE122: 57297000 | AF122: 0.9343 | AG122: 53533000 | AH122: 53533000 | AI122: 3764000 | AJ122: 57297000 | AK122: 53533000 | AL122: 53533000 | AN122: 5.024 | AO122: 3.092 | AP122: 4.598 | AQ122: 100 | AR122: 100 | AS122: 44097 | AT122: 47749 | AU122: 46295 | AV122: PI2021 | AW122: Aquila Utilities | AX122: N | AY122: Vertex Electricity Finance Ltd | AZ122: Vertex Electricity Finance | BA122: Spain | BB122: Aquila Utilities | BC122: 529900SYNTH000000021 | BI122: 57297000 | BJ122: 57297000 | BK122: Fixed | BL122: Senior Secured | BN122: 6 | BO122: 4.23 | BP122: N | BQ122: Y | BR122: Debt | BS122: RA100224 | BT122: A. Martin | BU122: C. Dubois | BW122: Semi-annual | BX122: ACT/360 | BY122: 125 | BZ122: 125 | CC122: AA- | CD122: AA- | CE122: NR | CF122: NR | CG122: NR | CH122: 46112 | CI122: 1.2 | CJ122: 2.23 | CK122: 2.34 | CL122: OK | DA122: 0.76 | DC122: 0.85 | DD122: OK | ED122: OK | EE122: 1.05 | EI122: 1.52 | FQ122: 42697761
B123: =C123&"x"&I123 -> 61004x100224 | C123: =IF(G123="SINGLE",H123,G123) -> 61004 | D123: =_xlfn.XLOOKUP(I123,calculations!$t:$t,calculations!$s:$s) -> #VALUE! | E123: =_xlfn.XLOOKUP(I123,Mapping!$T:$T,Mapping!$Q:$Q) -> VERT22 | F123: 46203 | G123: 61004 | H123: 61004 | I123: 100224 | J123: Vertex Electricity | K123: Investor 4 Portfolio | L123: Investor 4 Portfolio | M123: Infra Debt | N123: 41655000 | O123: 41655000 | P123: EUR | Q123: Loan | R123: Y | S123: L100224 | T123: Infrastructure Debt | U123: ES | V123: Spain | W123: Electricity networks | X123: CR1021 | Y123: 5.3 | Z123: EUR | AA123: 1 | AB123: N | AC123: 44583000 | AD123: 44583000 | AE123: 44583000 | AF123: 0.9343 | AG123: 41655000 | AH123: 41655000 | AI123: 2928000 | AJ123: 44583000 | AK123: 41655000 | AL123: 41655000 | AN123: 3.775 | AO123: 3.081 | AP123: 6.099 | AQ123: 100 | AR123: 100 | AS123: 44097 | AT123: 47749 | AU123: 46295 | AV123: PI2021 | AW123: Aquila Utilities | AX123: N | AY123: Vertex Electricity Finance Ltd | AZ123: Vertex Electricity Finance | BA123: Spain | BB123: Aquila Utilities | BC123: 529900SYNTH000000021 | BI123: 44583000 | BJ123: 44583000 | BK123: Fixed | BL123: Senior Secured | BN123: 6 | BO123: 4.23 | BP123: N | BQ123: Y | BR123: Debt | BS123: RA100224 | BT123: A. Martin | BU123: F. Lindqvist | BW123: Quarterly | BX123: ACT/360 | BY123: 125 | BZ123: 125 | CC123: AA- | CD123: AA- | CE123: NR | CF123: NR | CG123: NR | CH123: 46112 | CI123: 1.2 | CJ123: 1.59 | CK123: 1.67 | CL123: OK | DA123: 0.63 | DC123: 0.85 | DD123: OK | ED123: OK | EE123: 1.05 | EI123: 1.97 | FQ123: 39551162
B124: =C124&"x"&I124 -> 61017x100225 | C124: =IF(G124="SINGLE",H124,G124) -> 61017 | D124: =_xlfn.XLOOKUP(I124,calculations!$t:$t,calculations!$s:$s) -> #VALUE! | E124: =_xlfn.XLOOKUP(I124,Mapping!$T:$T,Mapping!$Q:$Q) -> WILL23 | F124: 46203 | G124: 61017 | H124: 61017 | I124: 100225 | J124: Willow EV | K124: Investor 17 Mandate | L124: Investor 17 Mandate | M124: Infra Debt | N124: 26299000 | O124: 26299000 | P124: EUR | Q124: Loan | R124: N | S124: L100225 | T124: Infrastructure Debt | U124: DE | V124: Germany | W124: EV charging | X124: CR1022 | Y124: 13 | Z124: EUR | AA124: 1 | AB124: N | AC124: 60488000 | AD124: 60488000 | AE124: 60488000 | AF124: 0.4348 | AG124: 26299000 | AH124: 26299000 | AI124: 34189000 | AJ124: 60488000 | AK124: 26299000 | AL124: 26299000 | AM124: EURIBOR 6M | AN124: 4.527 | AO124: 4.642 | AP124: 5.677 | AQ124: 100 | AR124: 100 | AS124: 45183 | AT124: 52304 | AU124: 46295 | AV124: PI2022 | AW124: Meridian Infrastructure | AX124: N | AY124: Willow EV Finance Ltd | AZ124: Willow EV Finance | BA124: Germany | BB124: Meridian Infrastructure | BC124: 529900SYNTH000000022 | BI124: 60488000 | BJ124: 60488000 | BK124: Floating | BL124: Senior Secured | BN124: 11.7 | BO124: 16.7 | BP124: Y | BQ124: N | BR124: Debt | BS124: RA100225 | BT124: E. Rossi | BU124: E. Rossi | BW124: Semi-annual | BX124: 30/360 | BY124: 125 | BZ124: 125 | CB124: EURIBOR | CC124: AA- | CD124: AA- | CE124: NR | CF124: NR | CG124: NR | CH124: 46112 | CI124: 1.2 | CJ124: 1.76 | CK124: 1.85 | CL124: OK | DA124: 0.82 | DC124: 0.85 | DD124: Watch | ED124: OK | EE124: 1.05 | EI124: 1.24 | FQ124: 67169444
B125: =C125&"x"&I125 -> 61021x100225 | C125: =IF(G125="SINGLE",H125,G125) -> 61021 | D125: =_xlfn.XLOOKUP(I125,calculations!$t:$t,calculations!$s:$s) -> #VALUE! | E125: =_xlfn.XLOOKUP(I125,Mapping!$T:$T,Mapping!$Q:$Q) -> WILL23 | F125: 46203 | G125: 61021 | H125: 61021 | I125: 100225 | J125: Willow EV | K125: Fund 1 Fund | L125: Fund 1 Fund | M125: Infra Debt | N125: 23607000 | O125: 23607000 | P125: EUR | Q125: Loan | R125: N | S125: L100225 | T125: Infrastructure Debt | U125: DE | V125: Germany | W125: EV charging | X125: CR1022 | Y125: 13 | Z125: EUR | AA125: 1 | AB125: N | AC125: 54298000 | AD125: 54298000 | AE125: 54298000 | AF125: 0.4348 | AG125: 23607000 | AH125: 23607000 | AI125: 30691000 | AJ125: 54298000 | AK125: 23607000 | AL125: 23607000 | AM125: EURIBOR 6M | AN125: 4.137 | AO125: 5.689 | AP125: 5.665 | AQ125: 100 | AR125: 100 | AS125: 45183 | AT125: 52304 | AU125: 46295 | AV125: PI2022 | AW125: Meridian Infrastructure | AX125: N | AY125: Willow EV Finance Ltd | AZ125: Willow EV Finance | BA125: Germany | BB125: Meridian Infrastructure | BC125: 529900SYNTH000000022 | BI125: 54298000 | BJ125: 54298000 | BK125: Floating | BL125: Senior Secured | BN125: 11.7 | BO125: 16.7 | BP125: Y | BQ125: N | BR125: Debt | BS125: RA100225 | BT125: E. Rossi | BU125: B. Okoro | BW125: Quarterly | BX125: ACT/360 | BY125: 125 | BZ125: 125 | CB125: EURIBOR | CC125: AA- | CD125: AA- | CE125: NR | CF125: NR | CG125: NR | CH125: 46112 | CI125: 1.2 | CJ125: 2.49 | CK125: 2.61 | CL125: OK | DA125: 0.77 | DC125: 0.85 | DD125: OK | ED125: OK | EE125: 1.05 | EI125: 1.48 | FQ125: 56014658
...

Sheet Mapping
C2: References | H2: Active Assets | Q2: Security Mapping | Y2: Funding Name | AC2: Investment Grade Mapping | AH2: Fund Check
C3: Columns in Holdings tab | D3: Output Names | H3: Views (Portfolios / Investors) | I3: List | J3: Mapping | K3: Active Assets Output | L3: Selected Assets | M3: Number | Q3: Code Name | R3: Holdings Name | S3: Identification ID | T3: Holding ID | U3: Transaction Group | Y3: Fund Name | Z3: Holdings Name | AA3: Holdings ID | AC3: Rating | AD3: Score | AE3: Scale | AH3: Mapping | AI3: Holdings | AJ3: Check
C4: Reporting Date | D4: Reporting Date | H4: Total platform | I4: Aurora Offshore | J4: AURO01 | K4: AURO01 | M4: 1 | P4: =T4 -> 100200 | Q4: AURO01 | R4: Aurora Offshore | S4: 100200 | T4: 100200 | U4: TG-001 | Y4: Investor 1 Portfolio | Z4: Investor 1 | AA4: 61001 | AC4: AAA | AD4: 100 | AE4: S&P / Fitch | AH4: Fund 1 Fund | AI4: Fund 1 | AJ4: OK
C5: Model Portfolio | D5: Model Portfolio | H5: Group | I5: Beacon Airports | J5: BEAC02 | K5: BEAC02 | M5: 2 | P5: =T5 -> 100201 | Q5: BEAC02 | R5: Beacon Airports | S5: 100201 | T5: 100201 | U5: TG-001 | Y5: Investor 2 Portfolio | Z5: Investor 2 | AA5: 61002 | AC5: AA+ | AD5: 200 | AE5: S&P / Fitch | AH5: Fund 2 Fund | AI5: Fund 2 | AJ5: OK
C6: Portfolio | D6: Portfolio | H6: Region A | I6: Cascade Telecom | J6: CASC03 | K6: CASC03 | M6: 3 | P6: =T6 -> 100202 | Q6: CASC03 | R6: Cascade Telecom | S6: 100202 | T6: 100202 | U6: TG-002 | Y6: Investor 3 Portfolio | Z6: Investor 3 | AA6: 61003 | AC6: AA | AD6: 250 | AE6: S&P / Fitch | AH6: Fund 3 Fund | AI6: Fund 3 | AJ6: OK
C7: Security ID | D7: Security ID | H7: Investor 1 incl. part in funds | I7: Delta Water A | J7: DELT04 | K7: DELT04 | M7: 4 | P7: =T7 -> 100203 | Q7: DELT04 | R7: Delta Water | S7: 100203 | T7: 100203 | U7: TG-002 | Y7: Investor 4 Portfolio | Z7: Investor 4 | AA7: 61004 | AC7: AA- | AD7: 300 | AE7: S&P / Fitch | AH7: Fund 4 Fund | AI7: Fund 4 | AJ7: OK
C8: Security Name | D8: Security Name | H8: Investor 2 incl. part in funds | I8: Delta Water B | J8: DELT04 | K8: EMBE05 | M8: 5 | P8: =T8 -> 100204 | Q8: DELT04 | R8: Delta Water | S8: 100203 | T8: 100204 | U8: TG-002 | Y8: Investor 5 Portfolio | Z8: Investor 5 | AA8: 61005 | AC8: A+ | AD8: 350 | AE8: S&P / Fitch | AH8: Fund 5 Fund | AI8: Fund 5 | AJ8: OK
C9: Portfolio Currency | D9: Portfolio Currency | H9: Region A incl. part in funds | I9: Ember Battery A | J9: EMBE05 | K9: FALC06 | M9: 6 | P9: =T9 -> 100205 | Q9: EMBE05 | R9: Ember Battery | S9: 100205 | T9: 100205 | U9: TG-003 | Y9: Investor 6 Portfolio | Z9: Investor 6 | AA9: 61006 | AC9: A | AD9: 400 | AE9: S&P / Fitch | AH9: Fund 6 Fund | AI9: Fund 6 | AJ9: OK
C10: Security Type Name | D10: Instrument | H10: Investor 1 | I10: Ember Battery B | J10: EMBE05 | K10: GRAN07 | M10: 7 | P10: =T10 -> 100206 | Q10: EMBE05 | R10: Ember Battery | S10: 100205 | T10: 100206 | U10: TG-003 | Y10: Investor 7 Portfolio | Z10: Investor 7 | AA10: 61007 | AC10: A- | AD10: 450 | AE10: S&P / Fitch | AH10: Fund 7 Fund | AI10: Fund 7 | AJ10: OK
C11: RA_Bullet | D11: Bullet | H11: Investor 2 | I11: Falcon Hospitals | J11: FALC06 | K11: HARB08 | M11: 8 | P11: =T11 -> 100207 | Q11: FALC06 | R11: Falcon Hospitals | S11: 100207 | T11: 100207 | U11: TG-003 | Y11: Investor 8 Portfolio | Z11: Investor 8 | AA11: 61008 | AC11: BBB+ | AD11: 500 | AE11: S&P / Fitch
C12: RA Asset Country Name | D12: Country | H12: Investor 11 | I12: Granite Hydro | J12: GRAN07 | K12: IRIS09 | M12: 9 | P12: =T12 -> 100208 | Q12: GRAN07 | R12: Granite Hydro | S12: 100208 | T12: 100208 | U12: TG-004 | Y12: Investor 9 Portfolio | Z12: Investor 9 | AA12: 61009 | AC12: BBB | AD12: 550 | AE12: S&P / Fitch
C13: WAL | D13: WAL | H13: Investor 12 | I13: Harbour Toll | J13: HARB08 | K13: JUNI10 | M13: 10 | P13: =T13 -> 100209 | Q13: HARB08 | R13: Harbour Toll | S13: 100209 | T13: 100209 | U13: TG-004 | Y13: Investor 10 Portfolio | Z13: Investor 10 | AA13: 61010 | AC13: BBB- | AD13: 600 | AE13: S&P / Fitch
C14: Quotation Currency | D14: Currency | H14: Fund 1 | I14: Iris Fibre | J14: IRIS09 | K14: KEST11 | M14: 11 | P14: =T14 -> 100210 | Q14: IRIS09 | R14: Iris Fibre | S14: 100210 | T14: 100210 | U14: TG-005 | Y14: Investor 11 Mandate | Z14: Investor 11 | AA14: 61011 | AC14: BB+ | AD14: 700 | AE14: S&P / Fitch
C15: FX Rate EC | D15: FX Rate | H15: Fund 2 | I15: Juniper Gas | J15: JUNI10 | K15: LUME12 | M15: 12 | P15: =T15 -> 100211 | Q15: JUNI10 | R15: Juniper Gas | S15: 100211 | T15: 100211 | U15: TG-005 | Y15: Investor 12 Mandate | Z15: Investor 12 | AA15: 61012 | AC15: BB | AD15: 750 | AE15: S&P / Fitch
C16: Initial Commitment Amount CCY | D16: Commitment | I16: Kestrel Battery | J16: KEST11 | K16: MERI13 | M16: 13 | P16: =T16 -> 100212 | Q16: KEST11 | R16: Kestrel Battery | S16: 100212 | T16: 100212 | U16: TG-006 | Y16: Investor 13 Mandate | Z16: Investor 13 | AA16: 61013 | AC16: BB- | AD16: 800 | AE16: S&P / Fitch
C17: RA_Commitment QC | D17: Nominal | I17: Lumen Hospitals A | J17: LUME12 | K17: NIMB14 | M17: 14 | P17: =T17 -> 100213 | Q17: LUME12 | R17: Lumen Hospitals | S17: 100213 | T17: 100213 | U17: TG-006 | Y17: Investor 14 Mandate | Z17: Investor 14 | AA17: 61014 | AC17: B+ | AD17: 850 | AE17: S&P / Fitch
C18: Current Drawn Amount CCY | D18: Drawn | I18: Lumen Hospitals B | J18: LUME12 | K18: ORIO15 | M18: 15 | P18: =T18 -> 100214 | Q18: LUME12 | R18: Lumen Hospitals | S18: 100213 | T18: 100214 | U18: TG-006 | Y18: Investor 15 Mandate | Z18: Investor 15 | AA18: 61015 | AC18: B | AD18: 900 | AE18: S&P / Fitch
C19: RA Commitment RC | D19: Nominal RC | I19: Meridian Solar | J19: MERI13 | K19: PION16 | M19: 16 | P19: =T19 -> 100215 | Q19: MERI13 | R19: Meridian Solar | S19: 100215 | T19: 100215 | U19: TG-007 | Y19: Investor 16 Mandate | Z19: Investor 16 | AA19: 61016 | AC19: B- | AD19: 950 | AE19: S&P / Fitch
C20: Purchase Date | D20: Purchase Date | I20: Nimbus Airports | J20: NIMB14 | K20: QUAR17 | M20: 17 | P20: =T20 -> 100216 | Q20: NIMB14 | R20: Nimbus Airports | S20: 100216 | T20: 100216 | U20: TG-007 | Y20: Investor 17 Mandate | Z20: Investor 17 | AA20: 61017 | AC20: CCC+ | AD20: 1000 | AE20: S&P / Fitch
C21: Maturity Date | D21: Maturity Date | I21: Orion Fibre | J21: ORIO15 | K21: RIDG18 | M21: 18 | P21: =T21 -> 100217 | Q21: ORIO15 | R21: Orion Fibre | S21: 100217 | T21: 100217 | U21: TG-008 | Y21: Investor 18 Mandate | Z21: Investor 18 | AA21: 61018 | AC21: CCC | AD21: 1050 | AE21: S&P / Fitch
C22: Parent Issuer Name | D22: Parent Issuer | I22: Pioneer Gas | J22: PION16 | K22: SUMM19 | M22: 19 | P22: =T22 -> 100218 | Q22: PION16 | R22: Pioneer Gas | S22: 100218 | T22: 100218 | U22: TG-008 | Y22: Investor 19 Mandate | Z22: Investor 19 | AA22: 61019 | AC22: Aaa | AD22: 100 | AE22: Moody's
C23: Issuer Country | D23: Issuer Country | I23: Quartz Battery | J23: QUAR17 | K23: TIDA20 | M23: 20 | P23: =T23 -> 100219 | Q23: QUAR17 | R23: Quartz Battery | S23: 100219 | T23: 100219 | U23: TG-009 | Y23: Investor 20 Mandate | Z23: Investor 20 | AA23: 61020 | AC23: Aa1 | AD23: 200 | AE23: Moody's
C24: Rate Type | D24: Rate Type | I24: Ridge Student | J24: RIDG18 | K24: UMBR21 | M24: 21 | P24: =T24 -> 100220 | Q24: RIDG18 | R24: Ridge Student | S24: 100220 | T24: 100220 | U24: TG-009 | Y24: Fund 1 Fund | Z24: Fund 1 | AA24: 61021 | AC24: Aa2 | AD24: 250 | AE24: Moody's
C25: Seniority | D25: Seniority | I25: Summit Hydro | J25: SUMM19 | K25: VERT22 | M25: 22 | P25: =T25 -> 100221 | Q25: SUMM19 | R25: Summit Hydro | S25: 100221 | T25: 100221 | U25: TG-010 | Y25: Fund 2 Fund | Z25: Fund 2 | AA25: 61022 | AC25: Aa3 | AD25: 300 | AE25: Moody's
C26: Time to Maturity | D26: Time to Maturity | I26: Tidal Toll | J26: TIDA20 | K26: WILL23 | M26: 23 | P26: =T26 -> 100222 | Q26: TIDA20 | R26: Tidal Toll | S26: 100222 | T26: 100222 | U26: TG-010 | Y26: Fund 3 Fund | Z26: Fund 3 | AA26: 61023 | AC26: A1 | AD26: 350 | AE26: Moody's
C27: All-in Spread at Acquisition | D27: Spread at Acquisition | I27: Umbra Data | J27: UMBR21 | K27: ZENI24 | M27: 24 | P27: =T27 -> 100223 | Q27: UMBR21 | R27: Umbra Data | S27: 100223 | T27: 100223 | U27: TG-011 | Y27: Fund 4 Fund | Z27: Fund 4 | AA27: 61024 | AC27: A2 | AD27: 400 | AE27: Moody's
... C30: Ext Sec Group_Rating_Closing | D30: Closing Rating | I30: Zenith Education A | J30: ZENI24 | K30: COBA27 | M30: 27 | P30: =T30 -> 100226 | Q30: ZENI24 | R30: Zenith Education | S30: 100226 | T30: 100226 | U30: TG-012 | Y30: Fund 7 Fund | Z30: Fund 7 | AA30: 61027 | AC30: Baa2 | AD30: 550 | AE30: Moody's
C31: Rating Fitch | D31: Fitch | I31: Zenith Education B | J31: ZENI24 | K31: DUNE28 | M31: 28 | P31: =T31 -> 100227 | Q31: ZENI24 | R31: Zenith Education | S31: 100226 | T31: 100227 | U31: TG-012 | AC31: Baa3 | AD31: 600 | AE31: Moody's
C32: Rating S&P | D32: S&P | I32: Alder Offshore A | J32: ALDE25 | K32: ECHO29 | M32: 29 | P32: =T32 -> 100228 | Q32: ALDE25 | R32: Alder Offshore | S32: 100228 | T32: 100228 | U32: TG-013 | AC32: Ba1 | AD32: 700 | AE32: Moody's
C33: Rating Moody's | D33: Moody's | I33: Alder Offshore B | J33: ALDE25 | K33: FJOR30 | M33: 30 | P33: =T33 -> 100229 | Q33: ALDE25 | R33: Alder Offshore | S33: 100228 | T33: 100229 | U33: TG-013 | AC33: Ba2 | AD33: 750 | AE33: Moody's
C34: ICR Current | D34: ICR | I34: Birch Ports | J34: BIRC26 | K34: GLAC31 | M34: 31 | P34: =T34 -> 100230 | Q34: BIRC26 | R34: Birch Ports | S34: 100230 | T34: 100230 | U34: TG-013 | AC34: Ba3 | AD34: 800 | AE34: Moody's
C35: LTV Current | D35: LTV | I35: Cobalt Telecom | J35: COBA27 | K35: HORI32 | M35: 32 | P35: =T35 -> 100231 | Q35: COBA27 | R35: Cobalt Telecom | S35: 100231 | T35: 100231 | U35: TG-014 | AC35: B1 | AD35: 850 | AE35: Moody's
C36: DSC Status | D36: DSCR Status | I36: Dune Gas | J36: DUNE28 | K36: INDI33 | M36: 33 | P36: =T36 -> 100232 | Q36: DUNE28 | R36: Dune Gas | S36: 100232 | T36: 100232 | U36: TG-014 | AC36: B2 | AD36: 900 | AE36: Moody's
I37: Echo District | J37: ECHO29 | K37: JADE34 | M37: 34 | P37: =T37 -> 100233 | Q37: ECHO29 | R37: Echo District | S37: 100233 | T37: 100233 | U37: TG-015 | AC37: B3 | AD37: 950 | AE37: Moody's
I38: Fjord Student | J38: FJOR30 | K38: KITE35 | M38: 35 | P38: =T38 -> 100234 | Q38: FJOR30 | R38: Fjord Student | S38: 100234 | T38: 100234 | U38: TG-015 | AC38: Caa1 | AD38: 1000 | AE38: Moody's
I39: Glacier Hydro | J39: GLAC31 | K39: LANT36 | M39: 36 | P39: =T39 -> 100235 | Q39: GLAC31 | R39: Glacier Hydro | S39: 100235 | T39: 100235 | U39: TG-016 | AC39: Caa2 | AD39: 1050 | AE39: Moody's
I40: Horizon Airports | J40: HORI32 | K40: MIST37 | M40: 37 | P40: =T40 -> 100236 | Q40: HORI32 | R40: Horizon Airports | S40: 100236 | T40: 100236 | U40: TG-016 | AC40: NR | AD40: 0 | AE40: Not rated
I41: Indigo Fibre | J41: INDI33 | K41: NOVA38 | M41: 38 | P41: =T41 -> 100237 | Q41: INDI33 | R41: Indigo Fibre | S41: 100237 | T41: 100237 | U41: TG-017
I42: Jade Gas | J42: JADE34 | K42: OPAL39 | M42: 39 | P42: =T42 -> 100238 | Q42: JADE34 | R42: Jade Gas | S42: 100238 | T42: 100238 | U42: TG-017
I43: Kite District A | J43: KITE35 | K43: PRIS40 | M43: 40 | P43: =T43 -> 100239 | Q43: KITE35 | R43: Kite District | S43: 100239 | T43: 100239 | U43: TG-018
I44: Kite District B | J44: KITE35 | K44: QUIL41 | M44: 41 | P44: =T44 -> 100240 | Q44: KITE35 | R44: Kite District | S44: 100239 | T44: 100240 | U44: TG-018
I45: Lantern Hospitals | J45: LANT36 | K45: ROWA42 | M45: 42 | P45: =T45 -> 100241 | Q45: LANT36 | R45: Lantern Hospitals | S45: 100241 | T45: 100241 | U45: TG-018
I46: Mistral Solar | J46: MIST37 | K46: SABL43 | M46: 43 | P46: =T46 -> 100242 | Q46: MIST37 | R46: Mistral Solar | S46: 100242 | T46: 100242 | U46: TG-019
I47: Nova Ports | J47: NOVA38 | K47: TUND44 | M47: 44 | P47: =T47 -> 100243 | Q47: NOVA38 | R47: Nova Ports | S47: 100243 | T47: 100243 | U47: TG-019
I48: Opal Telecom | J48: OPAL39 | K48: ULTR45 | M48: 45 | P48: =T48 -> 100244 | Q48: OPAL39 | R48: Opal Telecom | S48: 100244 | T48: 100244 | U48: TG-020
I49: Prism Gas A | J49: PRIS40 | K49: VALE46 | M49: 46 | P49: =T49 -> 100245 | Q49: PRIS40 | R49: Prism Gas | S49: 100245 | T49: 100245 | U49: TG-020
I50: Prism Gas B | J50: PRIS40 | K50: WREN47 | M50: 47 | P50: =T50 -> 100246 | Q50: PRIS40 | R50: Prism Gas | S50: 100245 | T50: 100246 | U50: TG-020
I51: Quill District | J51: QUIL41 | P51: =T51 -> 100247 | Q51: QUIL41 | R51: Quill District | S51: 100247 | T51: 100247 | U51: TG-021
I52: Rowan Student A | J52: ROWA42 | P52: =T52 -> 100248 | Q52: ROWA42 | R52: Rowan Student | S52: 100248 | T52: 100248 | U52: TG-021
I53: Rowan Student B | J53: ROWA42 | P53: =T53 -> 100249 | Q53: ROWA42 | R53: Rowan Student | S53: 100248 | T53: 100249 | U53: TG-021
I54: Sable Solar | J54: SABL43 | P54: =T54 -> 100250 | Q54: SABL43 | R54: Sable Solar | S54: 100250 | T54: 100250 | U54: TG-022
I55: Tundra Ports | J55: TUND44 | P55: =T55 -> 100251 | Q55: TUND44 | R55: Tundra Ports | S55: 100251 | T55: 100251 | U55: TG-022
I56: Ultra Fibre | J56: ULTR45 | P56: =T56 -> 100252 | Q56: ULTR45 | R56: Ultra Fibre | S56: 100252 | T56: 100252 | U56: TG-023
I57: Vale Water | J57: VALE46 | P57: =T57 -> 100253 | Q57: VALE46 | R57: Vale Water | S57: 100253 | T57: 100253 | U57: TG-023
I58: Wren EV | J58: WREN47 | P58: =T58 -> 100254 | Q58: WREN47 | R58: Wren EV | S58: 100254 | T58: 100254 | U58: TG-024
P59: =T59 -> 100255 | Q59: YARR48 | R59: Yarrow Hospitals | S59: 100255 | T59: 100255 | U59: TG-024

Sheet Hardcoded
D2: Project Code | F2: Chronological Order | G2: Subsector | H2: Cashflow Type | I2: Description | J2: Shareholders | K2: Origination | L2: Staff Closing | M2: Upfront | N2: Prepayment Protection (1) | O2: Prepayment Protection (2) | P2: End of NC / MW | Q2: IC Date | R2: Funding Date | S2: Total Debt Offering | T2: Watchlist | U2: Jurisdiction Tier - Group | V2: Investor 21 Classification | X2: Investor 21 FX for GBP | Y2: TICCS Code | Z2: Investor 14 Sector Classification | AA2: Investor 15 Country Tier | AB2: Compliance with Financial Covenants
C3: Security ID | D3: Project Name | E3: Code Name | F3: Chronological Order | G3: Subsector | H3: Cashflow Type | I3: Description | J3: Shareholders | K3: Origination | L3: Staff Closing | M3: Upfront | N3: Prepayment Protection (1) | O3: Prepayment Protection (2) | P3: End of NC / MW | Q3: IC Date | R3: Funding Date | S3: Total Debt Offering | T3: Watchlist | U3: Jurisdiction Tier - Group | V3: Investor 21 Classification | W3: Investor 21 Sector Classification | X3: Investor 21 FX for GBP / EUR | Y3: TICCS Code | Z3: Investor 14 Sector Classification | AA3: Investor 15 Country Tier | AB3: Compliance with Financial Covenants
C4: 100226 | D4: =_xlfn.XLOOKUP(C4,Mapping!$P:$P,Mapping!$R:$R) -> Zenith Education | E4: =_xlfn.XLOOKUP(C4,Mapping!$P:$P,Mapping!$Q:$Q) -> ZENI24 | F4: 1 | G4: Education (PPP) | H4: Bullet | I4: Brownfield education (ppp) loan financing in Spain. SYNTHETIC. | J4: Atlas Core Funds | K4: Secondary | L4: C. Dubois | M4: 65 | N4: Make-whole | O4: Non-call period | P4: 45813 | Q4: 41948 | R4: 42009 | S4: 510000000 | T4: No | U4: Tier 2 | V4: Core | W4: Social | Y4: TICCS-323 | Z4: Social | AA4: Tier 3 | AB4: Waiver
C5: 100208 | D5: =_xlfn.XLOOKUP(C5,Mapping!$P:$P,Mapping!$R:$R) -> Granite Hydro | E5: =_xlfn.XLOOKUP(C5,Mapping!$P:$P,Mapping!$Q:$Q) -> GRAN07 | F5: 2 | G5: Hydro | H5: Sculpted | I5: Brownfield hydro loan financing in Ireland. SYNTHETIC. | J5: Meridian Infrastructure | K5: Primary | L5: D. Schäfer | M5: 130 | N5: None | Q5: 42072 | R5: 42133 | S5: 720000000 | T5: Watch | U5: Tier 2 | V5: Core | W5: Renewables | Y5: TICCS-306 | Z5: Renewables | AA5: Tier 2 | AB5: Waiver
C6: 100218 | D6: =_xlfn.XLOOKUP(C6,Mapping!$P:$P,Mapping!$R:$R) -> Pioneer Gas | E6: =_xlfn.XLOOKUP(C6,Mapping!$P:$P,Mapping!$Q:$Q) -> PION16 | F6: 3 | G6: Gas distribution | H6: Annuity | I6: Brownfield gas distribution loan financing in Switzerland. SYNTHETIC. | J6: Silverline Transport | K6: Primary | L6: F. Lindqvist | M6: 30 | N6: None | Q6: 42100 | R6: 42161 | S6: 640000000 | T6: No | U6: Tier 1 | V6: Core | W6: Utilities | Y6: TICCS-315 | Z6: Utilities | AA6: Tier 1 | AB6: Yes
C7: 100216 | D7: =_xlfn.XLOOKUP(C7,Mapping!$P:$P,Mapping!$R:$R) -> Nimbus Airports | E7: =_xlfn.XLOOKUP(C7,Mapping!$P:$P,Mapping!$Q:$Q) -> NIMB14 | F7: 4 | G7: Airports | H7: Sculpted | I7: Brownfield airports loan financing in Ireland. SYNTHETIC. | J7: Silverline Transport | K7: Primary | L7: A. Martin | M7: 125 | N7: None | Q7: 42156 | R7: 42217 | S7: 90000000 | T7: No | U7: Tier 1 | V7: Core+ | W7: Transport | Y7: TICCS-313 | Z7: Transport | AA7: Tier 2 | AB7: Yes
C8: 100200 | D8: =_xlfn.XLOOKUP(C8,Mapping!$P:$P,Mapping!$R:$R) -> Aurora Offshore | E8: =_xlfn.XLOOKUP(C8,Mapping!$P:$P,Mapping!$Q:$Q) -> AURO01 | F8: 5 | G8: Offshore wind | H8: Annuity | I8: Greenfield offshore wind private placement note financing in Germany. SYNTHETIC. | J8: Corvus Digital | K8: Primary | L8: E. Rossi | M8: 35 | N8: None | Q8: 42288 | R8: 42349 | S8: 650000000 | T8: No | U8: Tier 1 | V8: Core+ | W8: Renewables | Y8: TICCS-300 | Z8: Renewables | AA8: Tier 1 | AB8: Yes
C9: 100230 | D9: =_xlfn.XLOOKUP(C9,Mapping!$P:$P,Mapping!$R:$R) -> Birch Ports | E9: =_xlfn.XLOOKUP(C9,Mapping!$P:$P,Mapping!$Q:$Q) -> BIRC26 | F9: 6 | G9: Ports | H9: Bullet | I9: Brownfield ports loan financing in United States. SYNTHETIC. | J9: Terra Social Infra | K9: Primary | L9: C. Dubois | M9: 110 | N9: None | Q9: 42302 | R9: 42363 | S9: 720000000 | T9: No | U9: Tier 2 | V9: Core+ | W9: Transport | Y9: TICCS-325 | Z9: Transport | AA9: Tier 3 | AB9: Yes
C10: 100242 | D10: =_xlfn.XLOOKUP(C10,Mapping!$P:$P,Mapping!$R:$R) -> Mistral Solar | E10: =_xlfn.XLOOKUP(C10,Mapping!$P:$P,Mapping!$Q:$Q) -> MIST37 | F10: 7 | G10: Solar PV | H10: Bullet | I10: Brownfield solar pv private placement note financing in United Kingdom. SYNTHETIC. | J10: Lumen Grid | K10: Secondary | L10: C. Dubois | M10: 70 | N10: Make-whole | O10: Non-call period | P10: 45035 | Q10: 42357 | R10: 42419 | S10: 870000000 | T10: No | U10: Tier 2 | V10: Core | W10: Renewables | X10: 0.8622 | Y10: TICCS-336 | Z10: Renewables | AA10: Tier 3 | AB10: Yes
C11: 100210 | D11: =_xlfn.XLOOKUP(C11,Mapping!$P:$P,Mapping!$R:$R) -> Iris Fibre | E11: =_xlfn.XLOOKUP(C11,Mapping!$P:$P,Mapping!$Q:$Q) -> IRIS09 | F11: 8 | G11: Fibre networks | H11: Sculpted | I11: Brownfield fibre networks loan financing in United Kingdom. SYNTHETIC. | J11: Northwind Capital | K11: Primary | L11: D. Schäfer | M11: 120 | N11: None | Q11: 42477 | R11: 42538 | S11: 770000000 | T11: No | U11: Tier 1 | V11: Core | W11: Digital | X11: 0.8608 | Y11: TICCS-308 | Z11: Digital | AA11: Tier 3 | AB11: Yes
C12: 100215 | D12: =_xlfn.XLOOKUP(C12,Mapping!$P:$P,Mapping!$R:$R) -> Meridian Solar | E12: =_xlfn.XLOOKUP(C12,Mapping!$P:$P,Mapping!$Q:$Q) -> MERI13 | F12: 9 | G12: Solar PV | H12: Bullet | I12: Brownfield solar pv loan financing in Ireland. SYNTHETIC. | J12: Boreal Energy | K12: Primary | L12: D. Schäfer | M12: 110 | N12: Make-whole | O12: Non-call period | P12: 45420 | Q12: 42590 | R12: 42651 | S12: 590000000 | T12: No | U12: Tier 2 | V12: Core+ | W12: Renewables | Y12: TICCS-312 | Z12: Renewables | AA12: Tier 2 | AB12: Yes
C13: 100251 | D13: =_xlfn.XLOOKUP(C13,Mapping!$P:$P,Mapping!$R:$R) -> Tundra Ports | E13: =_xlfn.XLOOKUP(C13,Mapping!$P:$P,Mapping!$Q:$Q) -> TUND44 | F13: 10 | G13: Ports | H13: Bullet | I13: Brownfield ports loan financing in United Kingdom. SYNTHETIC. | J13: Boreal Energy | K13: Secondary | L13: E. Rossi | M13: 75 | N13: None | Q13: 42718 | R13: 42780 | S13: 400000000 | T13: No | U13: Tier 2 | V13: Core | W13: Transport | X13: 0.8644 | Y13: TICCS-343 | Z13: Transport | AA13: Tier 3 | AB13: Yes
C14: 100253 | D14: =_xlfn.XLOOKUP(C14,Mapping!$P:$P,Mapping!$R:$R) -> Vale Water | E14: =_xlfn.XLOOKUP(C14,Mapping!$P:$P,Mapping!$Q:$Q) -> VALE46 | F14: 11 | G14: Water | H14: Sculpted | I14: Brownfield water loan financing in Sweden. SYNTHETIC. | J14: Lumen Grid | K14: Primary | L14: E. Rossi | M14: 115 | N14: None | Q14: 42758 | R14: 42817 | S14: 130000000 | T14: No | U14: Tier 2 | V14: Core+ | W14: Utilities | Y14: TICCS-345 | Z14: Utilities | AA14: Tier 2 | AB14: Yes
C15: 100255 | D15: =_xlfn.XLOOKUP(C15,Mapping!$P:$P,Mapping!$R:$R) -> Yarrow Hospitals | E15: =_xlfn.XLOOKUP(C15,Mapping!$P:$P,Mapping!$Q:$Q) -> YARR48 | F15: 12 | G15: Hospitals (PPP) | H15: Sculpted | I15: Brownfield hospitals (ppp) loan financing in Sweden. SYNTHETIC. | J15: Corvus Digital | K15: Secondary | L15: B. Okoro | M15: 40 | N15: None | Q15: 42788 | R15: 42847 | S15: 820000000 | T15: No | U15: Tier 2 | V15: Core | W15: Social | Y15: TICCS-347 | Z15: Social | AA15: Tier 1 | AB15: Yes
C16: 100238 | D16: =_xlfn.XLOOKUP(C16,Mapping!$P:$P,Mapping!$R:$R) -> Jade Gas | E16: =_xlfn.XLOOKUP(C16,Mapping!$P:$P,Mapping!$Q:$Q) -> JADE34 | F16: 13 | G16: Gas distribution | H16: Sculpted | I16: Brownfield gas distribution loan financing in Sweden. SYNTHETIC. | J16: Atlas Core Funds | K16: Primary | L16: D. Schäfer | M16: 30 | N16: None | Q16: 42949 | R16: 43010 | S16: 390000000 | T16: No | U16: Tier 2 | V16: Core+ | W16: Utilities | Y16: TICCS-333 | Z16: Utilities | AA16: Tier 2 | AB16: Waiver
C17: 100241 | D17: =_xlfn.XLOOKUP(C17,Mapping!$P:$P,Mapping!$R:$R) -> Lantern Hospitals | E17: =_xlfn.XLOOKUP(C17,Mapping!$P:$P,Mapping!$Q:$Q) -> LANT36 | F17: 14 | G17: Hospitals (PPP) | H17: Sculpted | I17: Brownfield hospitals (ppp) loan financing in Ireland. SYNTHETIC. | J17: Lumen Grid | K17: Primary | L17: B. Okoro | M17: 75 | N17: None | Q17: 42993 | R17: 43054 | S17: 430000000 | T17: Watch | U17: Tier 1 | V17: Core+ | W17: Social | Y17: TICCS-335 | Z17: Social | AA17: Tier 2 | AB17: Yes
C18: 100233 | D18: =_xlfn.XLOOKUP(C18,Mapping!$P:$P,Mapping!$R:$R) -> Echo District | E18: =_xlfn.XLOOKUP(C18,Mapping!$P:$P,Mapping!$Q:$Q) -> ECHO29 | F18: 15 | G18: District heating | H18: Annuity | I18: Brownfield district heating loan financing in Ireland. SYNTHETIC. | J18: Helios Partners | K18: Primary | L18: E. Rossi | M18: 150 | N18: None | Q18: 43032 | R18: 43093 | S18: 680000000 | T18: Intensive | U18: Tier 1 | V18: Core+ | W18: Energy transition | Y18: TICCS-328 | Z18: Energy transition | AA18: Tier 1 | AB18: Yes
C19: 100248 | D19: =_xlfn.XLOOKUP(C19,Mapping!$P:$P,Mapping!$R:$R) -> Rowan Student | E19: =_xlfn.XLOOKUP(C19,Mapping!$P:$P,Mapping!$Q:$Q) -> ROWA42 | F19: 16 | G19: Student accommodation | H19: Bullet | I19: Brownfield student accommodation loan financing in Australia. SYNTHETIC. | J19: Corvus Digital | K19: Primary | L19: D. Schäfer | M19: 40 | N19: None | Q19: 43152 | R19: 43211 | S19: 330000000 | T19: No | U19: Tier 2 | V19: Core+ | W19: Social | Y19: TICCS-341 | Z19: Social | AA19: Tier 2 | AB19: Yes
C20: 100250 | D20: =_xlfn.XLOOKUP(C20,Mapping!$P:$P,Mapping!$R:$R) -> Sable Solar | E20: =_xlfn.XLOOKUP(C20,Mapping!$P:$P,Mapping!$Q:$Q) -> SABL43 | F20: 17 | G20: Solar PV | H20: Bullet | I20: Brownfield solar pv loan financing in Portugal. SYNTHETIC. | J20: Aquila Utilities | K20: Secondary | L20: A. Martin | M20: 50 | N20: None | Q20: 43213 | R20: 43274 | S20: 380000000 | T20: No | U20: Tier 2 | V20: Core | W20: Renewables | Y20: TICCS-342 | Z20: Renewables | AA20: Tier 1 | AB20: Yes
C21: 100202 | D21: =_xlfn.XLOOKUP(C21,Mapping!$P:$P,Mapping!$R:$R) -> Cascade Telecom | E21: =_xlfn.XLOOKUP(C21,Mapping!$P:$P,Mapping!$Q:$Q) -> CASC03 | F21: 18 | G21: Telecom towers | H21: Sculpted | I21: Brownfield telecom towers loan financing in Germany. SYNTHETIC. | J21: Silverline Transport | K21: Secondary | L21: C. Dubois | M21: 50 | N21: None | Q21: 43353 | R21: 43414 | S21: 510000000 | T21: No | U21: Tier 2 | V21: Core | W21: Digital | Y21: TICCS-302 | Z21: Digital | AA21: Tier 1 | AB21: Yes
C22: 100219 | D22: =_xlfn.XLOOKUP(C22,Mapping!$P:$P,Mapping!$R:$R) -> Quartz Battery | E22: =_xlfn.XLOOKUP(C22,Mapping!$P:$P,Mapping!$Q:$Q) -> QUAR17 | F22: 19 | G22: Battery storage | H22: Bullet | I22: Brownfield battery storage private placement note financing in Germany. SYNTHETIC. | J22: Boreal Energy | K22: Secondary | L22: B. Okoro | M22: 90 | N22: None | Q22: 43418 | R22: 43479 | S22: 360000000 | T22: Watch | U22: Tier 1 | V22: Core | W22: Energy transition | Y22: TICCS-316 | Z22: Energy transition | AA22: Tier 1 | AB22: Yes
C23: 100228 | D23: =_xlfn.XLOOKUP(C23,Mapping!$P:$P,Mapping!$R:$R) -> Alder Offshore | E23: =_xlfn.XLOOKUP(C23,Mapping!$P:$P,Mapping!$Q:$Q) -> ALDE25 | F23: 20 | G23: Offshore wind | H23: Annuity | I23: Brownfield offshore wind private placement note financing in Netherlands. SYNTHETIC. | J23: Corvus Digital | K23: Primary | L23: E. Rossi | M23: 95 | N23: None | Q23: 43513 | R23: 43572 | S23: 640000000 | T23: Watch | U23: Tier 1 | V23: Core+ | W23: Renewables | Y23: TICCS-324 | Z23: Renewables | AA23: Tier 3 | AB23: Yes
C24: 100254 | D24: =_xlfn.XLOOKUP(C24,Mapping!$P:$P,Mapping!$R:$R) -> Wren EV | E24: =_xlfn.XLOOKUP(C24,Mapping!$P:$P,Mapping!$Q:$Q) -> WREN47 | F24: 21 | G24: EV charging | H24: Annuity | I24: Greenfield ev charging private placement note financing in Ireland. SYNTHETIC. | J24: Boreal Energy | K24: Primary | L24: B. Okoro | M24: 55 | N24: None | Q24: 43531 | R24: 43592 | S24: 380000000 | T24: No | U24: Tier 2 | V24: Core | W24: Energy transition | Y24: TICCS-346 | Z24: Energy transition | AA24: Tier 2 | AB24: Yes
C25: 100245 | D25: =_xlfn.XLOOKUP(C25,Mapping!$P:$P,Mapping!$R:$R) -> Prism Gas | E25: =_xlfn.XLOOKUP(C25,Mapping!$P:$P,Mapping!$Q:$Q) -> PRIS40 | F25: 22 | G25: Gas distribution | H25: Sculpted | I25: Greenfield gas distribution loan financing in Portugal. SYNTHETIC. | J25: Northwind Capital | K25: Secondary | L25: D. Schäfer | M25: 130 | N25: None | Q25: 43629 | R25: 43690 | S25: 170000000 | T25: Watch | U25: Tier 2 | V25: Core+ | W25: Utilities | Y25: TICCS-339 | Z25: Utilities | AA25: Tier 2 | AB25: Yes
... C29: 100235 | D29: =_xlfn.XLOOKUP(C29,Mapping!$P:$P,Mapping!$R:$R) -> Glacier Hydro | E29: =_xlfn.XLOOKUP(C29,Mapping!$P:$P,Mapping!$Q:$Q) -> GLAC31 | F29: 26 | G29: Hydro | H29: Annuity | I29: Greenfield hydro loan financing in Belgium. SYNTHETIC. | J29: Meridian Infrastructure | K29: Primary | L29: F. Lindqvist | M29: 135 | N29: None | Q29: 43938 | R29: 43999 | S29: 230000000 | T29: No | U29: Tier 2 | V29: Core+ | W29: Renewables | Y29: TICCS-330 | Z29: Renewables | AA29: Tier 2 | AB29: Yes
C30: 100224 | D30: =_xlfn.XLOOKUP(C30,Mapping!$P:$P,Mapping!$R:$R) -> Vertex Electricity | E30: =_xlfn.XLOOKUP(C30,Mapping!$P:$P,Mapping!$Q:$Q) -> VERT22 | F30: 27 | G30: Electricity networks | H30: Bullet | I30: Brownfield electricity networks loan financing in Spain. SYNTHETIC. | J30: Aquila Utilities | K30: Primary | L30: A. Martin | M30: 140 | N30: Make-whole | O30: Non-call period | P30: 45558 | Q30: 44035 | R30: 44097 | S30: 420000000 | T30: No | U30: Tier 1 | V30: Core+ | W30: Utilities | Y30: TICCS-321 | Z30: Utilities | AA30: Tier 3 | AB30: Yes
C31: 100220 | D31: =_xlfn.XLOOKUP(C31,Mapping!$P:$P,Mapping!$R:$R) -> Ridge Student | E31: =_xlfn.XLOOKUP(C31,Mapping!$P:$P,Mapping!$Q:$Q) -> RIDG18 | F31: 28 | G31: Student accommodation | H31: Annuity | I31: Brownfield student accommodation loan financing in Sweden. SYNTHETIC. | J31: Northwind Capital | K31: Primary | L31: F. Lindqvist | M31: 55 | N31: None | Q31: 44140 | R31: 44201 | S31: 120000000 | T31: No | U31: Tier 2 | V31: Core | W31: Social | Y31: TICCS-317 | Z31: Social | AA31: Tier 2 | AB31: Yes
C32: 100217 | D32: =_xlfn.XLOOKUP(C32,Mapping!$P:$P,Mapping!$R:$R) -> Orion Fibre | E32: =_xlfn.XLOOKUP(C32,Mapping!$P:$P,Mapping!$Q:$Q) -> ORIO15 | F32: 29 | G32: Fibre networks | H32: Bullet | I32: Brownfield fibre networks loan financing in Finland. SYNTHETIC. | J32: Helios Partners | K32: Primary | L32: F. Lindqvist | M32: 145 | N32: None | Q32: 44160 | R32: 44221 | S32: 220000000 | T32: No | U32: Tier 2 | V32: Core | W32: Digital | Y32: TICCS-314 | Z32: Digital | AA32: Tier 3 | AB32: Yes
C33: 100252 | D33: =_xlfn.XLOOKUP(C33,Mapping!$P:$P,Mapping!$R:$R) -> Ultra Fibre | E33: =_xlfn.XLOOKUP(C33,Mapping!$P:$P,Mapping!$Q:$Q) -> ULTR45 | F33: 30 | G33: Fibre networks | H33: Annuity | I33: Brownfield fibre networks loan financing in Spain. SYNTHETIC. | J33: Boreal Energy | K33: Primary | L33: E. Rossi | M33: 60 | N33: None | Q33: 44179 | R33: 44241 | S33: 650000000 | T33: No | U33: Tier 2 | V33: Core+ | W33: Digital | Y33: TICCS-344 | Z33: Digital | AA33: Tier 3 | AB33: Yes
C34: 100247 | D34: =_xlfn.XLOOKUP(C34,Mapping!$P:$P,Mapping!$R:$R) -> Quill District | E34: =_xlfn.XLOOKUP(C34,Mapping!$P:$P,Mapping!$Q:$Q) -> QUIL41 | F34: 31 | G34: District heating | H34: Bullet | I34: Brownfield district heating loan financing in France. SYNTHETIC. | J34: Aquila Utilities | K34: Primary | L34: E. Rossi | M34: 60 | N34: Make-whole | O34: Non-call period | P34: 46534 | Q34: 44223 | R34: 44282 | S34: 200000000 | T34: No | U34: Tier 2 | V34: Core | W34: Energy transition | Y34: TICCS-340 | Z34: Energy transition | AA34: Tier 3 | AB34: Yes
C35: 100222 | D35: =_xlfn.XLOOKUP(C35,Mapping!$P:$P,Mapping!$R:$R) -> Tidal Toll | E35: =_xlfn.XLOOKUP(C35,Mapping!$P:$P,Mapping!$Q:$Q) -> TIDA20 | F35: 32 | G35: Toll roads | H35: Bullet | I35: Brownfield toll roads loan financing in France. SYNTHETIC. | J35: Helios Partners | K35: Primary | L35: C. Dubois | M35: 95 | N35: None | Q35: 44233 | R35: 44292 | S35: 340000000 | T35: No | U35: Tier 2 | V35: Core+ | W35: Transport | Y35: TICCS-319 | Z35: Transport | AA35: Tier 1 | AB35: Yes
C36: 100212 | D36: =_xlfn.XLOOKUP(C36,Mapping!$P:$P,Mapping!$R:$R) -> Kestrel Battery | E36: =_xlfn.XLOOKUP(C36,Mapping!$P:$P,Mapping!$Q:$Q) -> KEST11 | F36: 33 | G36: Battery storage | H36: Annuity | I36: Brownfield battery storage private placement note financing in Spain. SYNTHETIC. | J36: Meridian Infrastructure | K36: Primary | L36: E. Rossi | M36: 75 | N36: None | Q36: 44241 | R36: 44300 | S36: 160000000 | T36: No | U36: Tier 2 | V36: Core+ | W36: Energy transition | Y36: TICCS-310 | Z36: Energy transition | AA36: Tier 1 | AB36: Yes
C37: 100236 | D37: =_xlfn.XLOOKUP(C37,Mapping!$P:$P,Mapping!$R:$R) -> Horizon Airports | E37: =_xlfn.XLOOKUP(C37,Mapping!$P:$P,Mapping!$Q:$Q) -> HORI32 | F37: 34 | G37: Airports | H37: Bullet | I37: Brownfield airports loan financing in Australia. SYNTHETIC. | J37: Aquila Utilities | K37: Primary | L37: F. Lindqvist | M37: 140 | N37: Make-whole | O37: Non-call period | P37: 47757 | Q37: 44256 | R37: 44317 | S37: 670000000 | T37: No | U37: Tier 2 | V37: Core+ | W37: Transport | Y37: TICCS-331 | Z37: Transport | AA37: Tier 1 | AB37: Yes
C38: 100237 | D38: =_xlfn.XLOOKUP(C38,Mapping!$P:$P,Mapping!$R:$R) -> Indigo Fibre | E38: =_xlfn.XLOOKUP(C38,Mapping!$P:$P,Mapping!$Q:$Q) -> INDI33 | F38: 35 | G38: Fibre networks | H38: Bullet | I38: Brownfield fibre networks private placement note financing in United Kingdom. SYNTHETIC. | J38: Boreal Energy | K38: Primary | L38: E. Rossi | M38: 105 | N38: None | Q38: 44269 | R38: 44330 | S38: 260000000 | T38: No | U38: Tier 1 | V38: Core+ | W38: Digital | X38: 0.8564 | Y38: TICCS-332 | Z38: Digital | AA38: Tier 2 | AB38: Yes
C39: 100221 | D39: =_xlfn.XLOOKUP(C39,Mapping!$P:$P,Mapping!$R:$R) -> Summit Hydro | E39: =_xlfn.XLOOKUP(C39,Mapping!$P:$P,Mapping!$Q:$Q) -> SUMM19 | F39: 36 | G39: Hydro | H39: Bullet | I39: Brownfield hydro loan financing in Spain. SYNTHETIC. | J39: Terra Social Infra | K39: Primary | L39: E. Rossi | M39: 130 | N39: None | Q39: 44397 | R39: 44459 | S39: 660000000 | T39: No | U39: Tier 2 | V39: Core+ | W39: Renewables | Y39: TICCS-318 | Z39: Renewables | AA39: Tier 2 | AB39: Yes
C40: 100243 | D40: =_xlfn.XLOOKUP(C40,Mapping!$P:$P,Mapping!$R:$R) -> Nova Ports | E40: =_xlfn.XLOOKUP(C40,Mapping!$P:$P,Mapping!$Q:$Q) -> NOVA38 | F40: 37 | G40: Ports | H40: Bullet | I40: Brownfield ports loan financing in Netherlands. SYNTHETIC. | J40: Meridian Infrastructure | K40: Primary | L40: E. Rossi | M40: 120 | N40: Make-whole | O40: Non-call period | P40: 45649 | Q40: 44492 | R40: 44553 | S40: 790000000 | T40: No | U40: Tier 1 | V40: Core | W40: Transport | Y40: TICCS-337 | Z40: Transport | AA40: Tier 1 | AB40: Yes
C41: 100203 | D41: =_xlfn.XLOOKUP(C41,Mapping!$P:$P,Mapping!$R:$R) -> Delta Water | E41: =_xlfn.XLOOKUP(C41,Mapping!$P:$P,Mapping!$Q:$Q) -> DELT04 | F41: 38 | G41: Water | H41: Annuity | I41: Greenfield water private placement note financing in United Kingdom. SYNTHETIC. | J41: Corvus Digital | K41: Secondary | L41: A. Martin | M41: 25 | N41: None | Q41: 44730 | R41: 44791 | S41: 90000000 | T41: No | U41: Tier 2 | V41: Core | W41: Utilities | X41: 0.8465 | Y41: TICCS-303 | Z41: Utilities | AA41: Tier 3 | AB41: Yes
C42: 100205 | D42: =_xlfn.XLOOKUP(C42,Mapping!$P:$P,Mapping!$R:$R) -> Ember Battery | E42: =_xlfn.XLOOKUP(C42,Mapping!$P:$P,Mapping!$Q:$Q) -> EMBE05 | F42: 39 | G42: Battery storage | H42: Sculpted | I42: Brownfield battery storage loan financing in Italy. SYNTHETIC. | J42: Terra Social Infra | K42: Primary | L42: D. Schäfer | M42: 120 | N42: None | Q42: 44730 | R42: 44791 | S42: 490000000 | T42: No | U42: Tier 1 | V42: Core+ | W42: Energy transition | Y42: TICCS-304 | Z42: Energy transition | AA42: Tier 3 | AB42: Yes
C43: 100213 | D43: =_xlfn.XLOOKUP(C43,Mapping!$P:$P,Mapping!$R:$R) -> Lumen Hospitals | E43: =_xlfn.XLOOKUP(C43,Mapping!$P:$P,Mapping!$Q:$Q) -> LUME12 | F43: 40 | G43: Hospitals (PPP) | H43: Sculpted | I43: Brownfield hospitals (ppp) loan financing in Portugal. SYNTHETIC. | J43: Helios Partners | K43: Primary | L43: D. Schäfer | M43: 135 | N43: None | Q43: 44751 | R43: 44813 | S43: 240000000 | T43: Watch | U43: Tier 2 | V43: Core+ | W43: Social | Y43: TICCS-311 | Z43: Social | AA43: Tier 1 | AB43: Yes
C44: 100201 | D44: =_xlfn.XLOOKUP(C44,Mapping!$P:$P,Mapping!$R:$R) -> Beacon Airports | E44: =_xlfn.XLOOKUP(C44,Mapping!$P:$P,Mapping!$Q:$Q) -> BEAC02 | F44: 41 | G44: Airports | H44: Bullet | I44: Greenfield airports loan financing in United Kingdom. SYNTHETIC. | J44: Aquila Utilities | K44: Secondary | L44: E. Rossi | M44: 120 | N44: None | Q44: 44987 | R44: 45048 | S44: 760000000 | T44: No | U44: Tier 2 | V44: Core | W44: Transport | X44: 0.8557 | Y44: TICCS-301 | Z44: Transport | AA44: Tier 3 | AB44: Waiver
C45: 100225 | D45: =_xlfn.XLOOKUP(C45,Mapping!$P:$P,Mapping!$R:$R) -> Willow EV | E45: =_xlfn.XLOOKUP(C45,Mapping!$P:$P,Mapping!$Q:$Q) -> WILL23 | F45: 42 | G45: EV charging | H45: Annuity | I45: Greenfield ev charging loan financing in Germany. SYNTHETIC. | J45: Meridian Infrastructure | K45: Primary | L45: E. Rossi | M45: 35 | N45: None | Q45: 45121 | R45: 45183 | S45: 520000000 | T45: No | U45: Tier 2 | V45: Core+ | W45: Energy transition | Y45: TICCS-322 | Z45: Energy transition | AA45: Tier 3 | AB45: Yes
C46: 100207 | D46: =_xlfn.XLOOKUP(C46,Mapping!$P:$P,Mapping!$R:$R) -> Falcon Hospitals | E46: =_xlfn.XLOOKUP(C46,Mapping!$P:$P,Mapping!$Q:$Q) -> FALC06 | F46: 43 | G46: Hospitals (PPP) | H46: Bullet | I46: Brownfield hospitals (ppp) private placement note financing in United Kingdom. SYNTHETIC. | J46: Northwind Capital | K46: Primary | L46: B. Okoro | M46: 30 | N46: Make-whole | O46: Non-call period | P46: 47742 | Q46: 45185 | R46: 45246 | S46: 140000000 | T46: No | U46: Tier 1 | V46: Core | W46: Social | X46: 0.8501 | Y46: TICCS-305 | Z46: Social | AA46: Tier 2 | AB46: Waiver
C47: 100232 | D47: =_xlfn.XLOOKUP(C47,Mapping!$P:$P,Mapping!$R:$R) -> Dune Gas | E47: =_xlfn.XLOOKUP(C47,Mapping!$P:$P,Mapping!$Q:$Q) -> DUNE28 | F47: 44 | G47: Gas distribution | H47: Sculpted | I47: Brownfield gas distribution loan financing in Portugal. SYNTHETIC. | J47: Silverline Transport | K47: Primary | L47: C. Dubois | M47: 90 | N47: None | Q47: 45206 | R47: 45267 | S47: 600000000 | T47: No | U47: Tier 1 | V47: Core+ | W47: Utilities | Y47: TICCS-327 | Z47: Utilities | AA47: Tier 3 | AB47: Waiver
C48: 100239 | D48: =_xlfn.XLOOKUP(C48,Mapping!$P:$P,Mapping!$R:$R) -> Kite District | E48: =_xlfn.XLOOKUP(C48,Mapping!$P:$P,Mapping!$Q:$Q) -> KITE35 | F48: 45 | G48: District heating | H48: Bullet | I48: Greenfield district heating loan financing in Switzerland. SYNTHETIC. | J48: Lumen Grid | K48: Secondary | L48: F. Lindqvist | M48: 145 | N48: None | Q48: 45446 | R48: 45507 | S48: 160000000 | T48: Watch | U48: Tier 1 | V48: Core | W48: Energy transition | Y48: TICCS-334 | Z48: Energy transition | AA48: Tier 1 | AB48: Yes
C49: 100231 | D49: =_xlfn.XLOOKUP(C49,Mapping!$P:$P,Mapping!$R:$R) -> Cobalt Telecom | E49: =_xlfn.XLOOKUP(C49,Mapping!$P:$P,Mapping!$Q:$Q) -> COBA27 | F49: 46 | G49: Telecom towers | H49: Annuity | I49: Brownfield telecom towers loan financing in Portugal. SYNTHETIC. | J49: Lumen Grid | K49: Secondary | L49: F. Lindqvist | M49: 75 | N49: None | Q49: 45481 | R49: 45543 | S49: 690000000 | T49: No | U49: Tier 2 | V49: Core | W49: Digital | Y49: TICCS-326 | Z49: Digital | AA49: Tier 3 | AB49: Yes
C50: 100209 | D50: =_xlfn.XLOOKUP(C50,Mapping!$P:$P,Mapping!$R:$R) -> Harbour Toll | E50: =_xlfn.XLOOKUP(C50,Mapping!$P:$P,Mapping!$Q:$Q) -> HARB08 | F50: 47 | G50: Toll roads | H50: Bullet | I50: Brownfield toll roads loan financing in Netherlands. SYNTHETIC. | J50: Helios Partners | K50: Primary | L50: D. Schäfer | M50: 95 | N50: Make-whole | O50: Non-call period | P50: 48236 | Q50: 45680 | R50: 45739 | S50: 320000000 | T50: No | U50: Tier 1 | V50: Core+ | W50: Transport | Y50: TICCS-307 | Z50: Transport | AA50: Tier 1 | AB50: Yes
C51: 100234 | D51: =_xlfn.XLOOKUP(C51,Mapping!$P:$P,Mapping!$R:$R) -> Fjord Student | E51: =_xlfn.XLOOKUP(C51,Mapping!$P:$P,Mapping!$Q:$Q) -> FJOR30 | F51: 48 | G51: Student accommodation | H51: Bullet | I51: Greenfield student accommodation loan financing in Spain. SYNTHETIC. | J51: Aquila Utilities | K51: Primary | L51: E. Rossi | M51: 35 | N51: None | Q51: 45785 | R51: 45846 | S51: 450000000 | T51: No | U51: Tier 2 | V51: Core | W51: Social | Y51: TICCS-329 | Z51: Social | AA51: Tier 2 | AB51: Yes

Sheet ESG Hardcoded
D2: Project Name | E2: Code Name | F2: Infra code | G2: Staff Monitoring | H2: E score | I2: S score | J2: G score | K2: ESG score | L2: Shareholders | M2: CBI sector | N2: CBI subsector | O2: CBI subsubsector | P2: CBI asset type | Q2: CBI asset specific | R2: GHG Scope 1 | S2: GHG Scope 2 | T2: GHG Scope 3
C3: Security ID | D3: Project Name | E3: Code Name | F3: Infra Code | G3: FM Monitoring | H3: E Score | I3: S Score | J3: G Score | K3: ESG Score | L3: Shareholders | M3: CBI Sector | N3: CBI Subsector | O3: CBI Subsubsector | P3: CBI Asset Type | Q3: CBI Asset Specific | R3: GHG Scope 1 | S3: GHG Scope 2 | T3: GHG Scope 3
C4: 100200 | D4: Aurora Offshore | E4: AURO01 | F4: INF001 | G4: E. Rossi | H4: 52 | I4: 88 | J4: 89 | K4: 76 | L4: Corvus Digital | M4: Renewables | N4: Offshore wind | O4: Offshore wind assets | P4: Construction | Q4: Private Placement Note | R4: 18876 | S4: 12584 | T4: 185236
C5: 100201 | D5: Beacon Airports | E5: BEAC02 | F5: INF002 | G5: E. Rossi | H5: 70 | I5: 46 | J5: 63 | K5: 60 | L5: Aquila Utilities | M5: Transport | N5: Airports | O5: Airports assets | P5: Construction | Q5: Loan | R5: 1922 | S5: 1281 | T5: 10009
C6: 100202 | D6: Cascade Telecom | E6: CASC03 | F6: INF003 | G6: C. Dubois | H6: 85 | I6: 90 | J6: 62 | K6: 79 | L6: Silverline Transport | M6: Digital | N6: Telecom towers | O6: Telecom towers assets | P6: Operational | Q6: Loan | R6: 33223 | S6: 22148 | T6: 110889
C7: 100203 | D7: Delta Water | E7: DELT04 | F7: INF004 | G7: A. Martin | H7: 86 | I7: 57 | J7: 78 | K7: 74 | L7: Corvus Digital | M7: Utilities | N7: Water | O7: Water assets | P7: Construction | Q7: Private Placement Note | R7: 527 | S7: 352 | T7: 4124
C8: 100205 | D8: Ember Battery | E8: EMBE05 | F8: INF005 | G8: D. Schäfer | H8: 50 | I8: 77 | J8: 54 | K8: 60 | L8: Terra Social Infra | M8: Energy transition | N8: Battery storage | O8: Battery storage assets | P8: Operational | Q8: Loan | R8: 16804 | S8: 11202 | T8: 136376
C9: 100207 | D9: Falcon Hospitals | E9: FALC06 | F9: INF006 | G9: B. Okoro | H9: 87 | I9: 91 | J9: 59 | K9: 79 | L9: Northwind Capital | M9: Social | N9: Hospitals (PPP) | O9: Hospitals (PPP) assets | P9: Operational | Q9: Private Placement Note | R9: 34223 | S9: 22816 | T9: 236848
C10: 100208 | D10: Granite Hydro | E10: GRAN07 | F10: INF007 | G10: D. Schäfer | H10: 95 | I10: 61 | J10: 75 | K10: 77 | L10: Meridian Infrastructure | M10: Renewables | N10: Hydro | O10: Hydro assets | P10: Operational | Q10: Loan | R10: 31565 | S10: 21043 | T10: 234999
C11: 100209 | D11: Harbour Toll | E11: HARB08 | F11: INF008 | G11: D. Schäfer | H11: 65 | I11: 70 | J11: 64 | K11: 66 | L11: Helios Partners | M11: Transport | N11: Toll roads | O11: Toll roads assets | P11: Operational | Q11: Loan | R11: 12344 | S11: 8229 | T11: 105737
C12: 100210 | D12: Iris Fibre | E12: IRIS09 | F12: INF009 | G12: D. Schäfer | H12: 43 | I12: 71 | J12: 61 | K12: 58 | L12: Northwind Capital | M12: Digital | N12: Fibre networks | O12: Fibre networks assets | P12: Operational | Q12: Loan | R12: 48020 | S12: 32013 | T12: 445208
C13: 100211 | D13: Juniper Gas | E13: JUNI10 | F13: INF010 | G13: F. Lindqvist | H13: 46 | I13: 49 | J13: 71 | K13: 55 | L13: Silverline Transport | M13: Utilities | N13: Gas distribution | O13: Gas distribution assets | P13: Operational | Q13: Private Placement Note | R13: 25969 | S13: 17313 | T13: 76829
C14: 100212 | D14: Kestrel Battery | E14: KEST11 | F14: INF011 | G14: E. Rossi | H14: 67 | I14: 83 | J14: 73 | K14: 74 | L14: Meridian Infrastructure | M14: Energy transition | N14: Battery storage | O14: Battery storage assets | P14: Operational | Q14: Private Placement Note | R14: 15629 | S14: 10420 | T14: 80410
C15: 100213 | D15: Lumen Hospitals | E15: LUME12 | F15: INF012 | G15: D. Schäfer | H15: 64 | I15: 42 | J15: 88 | K15: 65 | L15: Helios Partners | M15: Social | N15: Hospitals (PPP) | O15: Hospitals (PPP) assets | P15: Operational | Q15: Loan | R15: 20200 | S15: 13467 | T15: 132239
... C50: 100255 | D50: Yarrow Hospitals | E50: YARR48 | F50: INF048 | G50: B. Okoro | H50: 63 | I50: 74 | J50: 73 | K50: 70 | L50: Corvus Digital | M50: Social | N50: Hospitals (PPP) | O50: Hospitals (PPP) assets | P50: Operational | Q50: Loan | R50: 43086 | S50: 28724 | T50: 344568
